Workbook

Sheet Report >>

Sheet Executive_Summary
B2: ='2023 Control'!$C$3 -> Concertiv
B3: =('2024 Control'!$C$4)&" Reporting Package" -> December 2025 Reporting Package
B4: Executive Summary
C5: What Went Well | D5: What Did Not Go Well | E5: Focus Areas for next month
B6: Finance | C6: - Collections improved particularly in Feb after new proccess set up with New Logo Sales + CS - Multiple 3 year deals signed, as well as other renewals - Vinay joined the team in Dec and is coming up to speed | D6: - Signficant Churn in the month (known), with more in Feb - Alpha Quest going out of business increased churn later in the year - No budget, OKRs or bonuses set given Shane's departure - Only $5k of new logo from one small PortCo | E6: - Finalizing Budget, OKRs, Comp Plans, BoD Deck - Finishing onboarding of Carta / 409A valuation
B7: Product - Development | C7: * Client Portal (MVP) was rolled out to the Cohort 0 clients. The team did a great job of responding to beta testing feedback and resolving issues. Great cross-functional collaboration during customer-facing demos. * Launched support for Navan Data Ingestion (Hotel) | D7: * Still plagued by Power BI reporting issues occurring due to configurations belonging to Jennifer W. that were not transitioned from her local machine. | E7: * Hotel Directory in Client Portal -- in progress * Rategain Data Ingestion -- in progress * Market Data Reporting and Notifications in Client Portal -- in progress * Seat-based Cost Allocation -- in progress * Market Data enhancements ready to be deployed -- (1) Fast availability of data hygiene reports to proactively audit, QC 360 and to prevent managed service breaches; (2) Incorporate automation of elementary QC checks for Managed Services to prevent further service breaches * Team is switching to Agentic AI development methods. Expect shorter build cycles and more indepth product discovery.
B8: Product - D&T | C8: -No missed renewals to clients, no breaches on Managed Services -Product Roadmap finalized for H1 -Development plans in place for all team members -Positioning statements and OKRs took significant steps forward -Attended 16 client meetings | D8: -Many conversations about OKRs with little progress -Ambiguity about value creation / metric tracking -Quality of life issues with C360 impacting daily tasks -Partnership conversations have mixed initial results at best | E8: Finalizing 2025 bonuses, outlining 2026 bonus framework Ensuring content from the Insights Factory is irresistible Data cleanse launch Salary & title architecture
B9: Product - Travel | C9: - Hotel Directory progressing quickly, due in part to engineers exploring AI tools - Internal alignment on ICP - Agreement to share Nishant's capacity in IND with Insights Team | D9: - Slow hiring process to backfill in NY + IND leading to capacity constraints - Positioning statement + collateral incomplete; creating material for pitches remains manual - Reporting still manual and ad hoc - Lack of KPIs | E9: - Transitioning Jen's work to rest of team (American deal, Avis deal, Reporting) - Feedback and testing for hotel directory - Hiring & onboarding new SME - Prioritizing key partnerships (TMCs, Navan, Concur) - Onboard Nishant
B10: Sales & Marketing | C10: - PEI Conference (6+ referrals) / Video interview - Global Alts Miami (client visits + partner activation) - C-Suite Dinner (10 senior client stakeholders) - Sales distribution (CWAN/ IQ EQ) - Veritas Enterprise PortCo / Brown Advisory / early GP prospects | D10: - Jordan Lee last day 3/6 - Positioning statement delivery - collateral delay - Pipeline cleanup/ pivot to refreshed ICP - Lack of client messaging regarding CEO tranition | E10: - Deal focus- Vertias & Brown Advisory - Revamped collateral/ website/ explainer video - March 12th Concertiv Sunset Series kick-off - March 16h IQ EQ joint diner / CWAN + IQ EQ activation
B11: Customer Success | C11: - Audax renewed for 3 years 5% increase y/y - Norwest renewed for 3 years CPI+5% increase y/y - AmSec Travel renewed $50k -> $65k - Hamilton Lane in-person reset | D11: - Lack of RevOps has caused data hygeine issues and slowed PowerBI updates - Fewer AA-joined client meetings between performance reviews, MDAs - Bonus delays + Shane exit | E11: - Morale is so so. Focused on team engagement. - Quinbrook exec alignment as blueprint for roadshow

Sheet Sprints_Special_Projects
B2: [PortCo Name]
B3: [Month] [Year] Reporting Package
B4: Sprints / Special Projects

Sheet Prod Dev
B2: ='2023 Control'!$C$3 -> Concertiv
B3: =('2024 Control'!$C$4)&" Reporting Package" -> December 2025 Reporting Package
B4: Product Development
E5: Monthly | BB5: 1 | BF5: 2 | BJ5: 3 | BN5: 4 | BR5: YTD vs. Budget
D6: Units | E6: 44957 | F6: 44985 | G6: 45016 | H6: =EOMONTH(G6,1) -> 45046 | I6: =EOMONTH(H6,1) -> 45077 | J6: =EOMONTH(I6,1) -> 45107 | K6: =EOMONTH(J6,1) -> 45138 | L6: =EOMONTH(K6,1) -> 45169 | M6: =EOMONTH(L6,1) -> 45199 | N6: =EOMONTH(M6,1) -> 45230 | O6: =EOMONTH(N6,1) -> 45260 | ... AZ6: =EOMONTH(AY6,1) -> 46387 | BB6: Act | BC6: Bgt. | BD6: Diff. | BF6: Act | BG6: Bgt. | BH6: Diff. | BJ6: Act | BK6: Bgt. | BL6: Diff. | BN6: Act | BO6: Bgt. | BP6: Diff. | BR6: YTD | BS6: Bgt. | BT6: Diff. | BV6: LTM
BB7: Q1 | BF7: Q2 | BJ7: Q3 | BN7: Q4
B8: Squads
B9: # of Squads | C9: EoP | D9: =VLOOKUP($B$4&" "&$B9,Actuals!$D$4:$AG$131,3,FALSE) -> # | E9: {=_xlfn.XLOOKUP( $B$4&" "&$B9, Actuals!$D:$D, _xlfn.XLOOKUP( E$6, Actuals!$H$3:$BD$3, Actuals!$H:$BD ) )} -> 2 | F9: {=_xlfn.XLOOKUP( $B$4&" "&$B9, Actuals!$D:$D, _xlfn.XLOOKUP( F$6, Actuals!$H$3:$BD$3, Actuals!$H:$BD ) )} -> 2 | G9: {=_xlfn.XLOOKUP( $B$4&" "&$B9, Actuals!$D:$D, _xlfn.XLOOKUP( G$6, Actuals!$H$3:$BD$3, Actuals!$H:$BD ) )} -> 2 | H9: {=_xlfn.XLOOKUP( $B$4&" "&$B9, Actuals!$D:$D, _xlfn.XLOOKUP( H$6, Actuals!$H$3:$BD$3, Actuals!$H:$BD ) )} -> 2 | I9: {=_xlfn.XLOOKUP( $B$4&" "&$B9, Actuals!$D:$D, _xlfn.XLOOKUP( I$6, Actuals!$H$3:$BD$3, Actuals!$H:$BD ) )} -> 2 | J9: {=_xlfn.XLOOKUP( $B$4&" "&$B9, Actuals!$D:$D, _xlfn.XLOOKUP( J$6, Actuals!$H$3:$BD$3, Actuals!$H:$BD ) )} -> 2 | K9: {=_xlfn.XLOOKUP( $B$4&" "&$B9, Actuals!$D:$D, _xlfn.XLOOKUP( K$6, Actuals!$H$3:$BD$3, Actuals!$H:$BD ) )} -> 3 | L9: {=_xlfn.XLOOKUP( $B$4&" "&$B9, Actuals!$D:$D, _xlfn.XLOOKUP( L$6, Actuals!$H$3:$BD$3, Actuals!$H:$BD ) )} -> 3 | ... AZ9: {=_xlfn.XLOOKUP( $B$4&" "&$B9, Actuals!$D:$D, _xlfn.XLOOKUP( AZ$6, Actuals!$H$3:$BD$3, Actuals!$H:$BD ) )} -> 0 | BB9: {=_xlfn.XLOOKUP( $B$4&" "&$B9, Actuals!$D:$D, _xlfn.XLOOKUP( BB$7, Actuals!$H$3:$BM$3, Actuals!$H:$BM ) )} -> 3 | BC9: =VLOOKUP($B$4&" "&$B9,Budget!$AG$4:$AL$132,$BB$5+1,FALSE) -> 3 | BD9: =BB9-BC9 -> 0 | BF9: {=_xlfn.XLOOKUP( $B$4&" "&$B9, Actuals!$D:$D, _xlfn.XLOOKUP( BF$7, Actuals!$H$3:$BM$3, Actuals!$H:$BM ) )} -> - | BG9: =VLOOKUP($B$4&" "&$B9,Budget!$AG$4:$AL$132,BF$5+1,FALSE) -> 3 | BH9: =BF9-BG9 -> #VALUE! | BJ9: {=_xlfn.XLOOKUP( $B$4&" "&$B9, Actuals!$D:$D, _xlfn.XLOOKUP( BJ$7, Actuals!$H$3:$BM$3, Actuals!$H:$BM ) )} -> - | BK9: =VLOOKUP($B$4&" "&$B9,Budget!$AG$4:$AL$132,BJ$5+1,FALSE) -> 3 | BL9: =BJ9-BK9 -> #VALUE! | BN9: {=_xlfn.XLOOKUP( $B$4&" "&$B9, Actuals!$D:$D, _xlfn.XLOOKUP( BN$7, Actuals!$H$3:$BM$3, Actuals!$H:$BM ) )} -> - | BO9: =VLOOKUP($B$4&" "&$B9,Budget!$AG$4:$AL$132,BN$5+1,FALSE) -> 3 | BR9: {=_xlfn.XLOOKUP( $B$4&" "&$B9, Actuals!$D:$D, _xlfn.XLOOKUP( BR$6, Actuals!$H$3:$BM$3, Actuals!$H:$BM ) )} -> 0.75 | BS9: =VLOOKUP($B$4&" "&$B9,Budget!$AG$4:$AL$132,6,FALSE) -> 3 | BT9: =IFERROR(BR9-BS9,"-") -> -2.25 | BV9: {=_xlfn.XLOOKUP( $B$4&" "&$B9, Actuals!$D:$D, _xlfn.XLOOKUP( BV$6, Actuals!$H$3:$BM$3, Actuals!$H:$BM ) )} -> 2.5
B10: # of Sprints | C10: In-period | D10: =VLOOKUP($B$4&" "&$B10,Actuals!$D$4:$AG$131,3,FALSE) -> # | E10: {=_xlfn.XLOOKUP( $B$4&" "&$B10, Actuals!$D:$D, _xlfn.XLOOKUP( E$6, Actuals!$H$3:$BD$3, Actuals!$H:$BD ) )} -> 4 | F10: {=_xlfn.XLOOKUP( $B$4&" "&$B10, Actuals!$D:$D, _xlfn.XLOOKUP( F$6, Actuals!$H$3:$BD$3, Actuals!$H:$BD ) )} -> 4 | G10: {=_xlfn.XLOOKUP( $B$4&" "&$B10, Actuals!$D:$D, _xlfn.XLOOKUP( G$6, Actuals!$H$3:$BD$3, Actuals!$H:$BD ) )} -> 4 | H10: {=_xlfn.XLOOKUP( $B$4&" "&$B10, Actuals!$D:$D, _xlfn.XLOOKUP( H$6, Actuals!$H$3:$BD$3, Actuals!$H:$BD ) )} -> 2 | I10: {=_xlfn.XLOOKUP( $B$4&" "&$B10, Actuals!$D:$D, _xlfn.XLOOKUP( I$6, Actuals!$H$3:$BD$3, Actuals!$H:$BD ) )} -> 2.2 | J10: {=_xlfn.XLOOKUP( $B$4&" "&$B10, Actuals!$D:$D, _xlfn.XLOOKUP( J$6, Actuals!$H$3:$BD$3, Actuals!$H:$BD ) )} -> 2 | K10: {=_xlfn.XLOOKUP( $B$4&" "&$B10, Actuals!$D:$D, _xlfn.XLOOKUP( K$6, Actuals!$H$3:$BD$3, Actuals!$H:$BD ) )} -> 2 | L10: {=_xlfn.XLOOKUP( $B$4&" "&$B10, Actuals!$D:$D, _xlfn.XLOOKUP( L$6, Actuals!$H$3:$BD$3, Actuals!$H:$BD ) )} -> 2 | ... AZ10: {=_xlfn.XLOOKUP( $B$4&" "&$B10, Actuals!$D:$D, _xlfn.XLOOKUP( AZ$6, Actuals!$H$3:$BD$3, Actuals!$H:$BD ) )} -> 0 | BB10: {=_xlfn.XLOOKUP( $B$4&" "&$B10, Actuals!$D:$D, _xlfn.XLOOKUP( BB$7, Actuals!$H$3:$BM$3, Actuals!$H:$BM ) )} -> 6 | BC10: =VLOOKUP($B$4&" "&$B10,Budget!$AG$4:$AL$132,$BB$5+1,FALSE) -> 6 | BD10: =BB10-BC10 -> 0 | BF10: {=_xlfn.XLOOKUP( $B$4&" "&$B10, Actuals!$D:$D, _xlfn.XLOOKUP( BF$7, Actuals!$H$3:$BM$3, Actuals!$H:$BM ) )} -> 0 | BG10: =VLOOKUP($B$4&" "&$B10,Budget!$AG$4:$AL$132,BF$5+1,FALSE) -> 6 | BH10: =BF10-BG10 -> -6 | BJ10: {=_xlfn.XLOOKUP( $B$4&" "&$B10, Actuals!$D:$D, _xlfn.XLOOKUP( BJ$7, Actuals!$H$3:$BM$3, Actuals!$H:$BM ) )} -> 0 | BK10: =VLOOKUP($B$4&" "&$B10,Budget!$AG$4:$AL$132,BJ$5+1,FALSE) -> 6 | BL10: =BJ10-BK10 -> -6 | BN10: {=_xlfn.XLOOKUP( $B$4&" "&$B10, Actuals!$D:$D, _xlfn.XLOOKUP( BN$7, Actuals!$H$3:$BM$3, Actuals!$H:$BM ) )} -> 0 | BO10: =VLOOKUP($B$4&" "&$B10,Budget!$AG$4:$AL$132,BN$5+1,FALSE) -> 6 | BR10: {=_xlfn.XLOOKUP( $B$4&" "&$B10, Actuals!$D:$D, _xlfn.XLOOKUP( BR$6, Actuals!$H$3:$BM$3, Actuals!$H:$BM ) )} -> 6 | BS10: =VLOOKUP($B$4&" "&$B10,Budget!$AG$4:$AL$132,6,FALSE) -> 24 | BT10: =IFERROR(BR10-BS10,"-") -> -18 | BV10: =VLOOKUP($B$4&" "&$B10,Actuals!$BG$4:$BM$131,7,FALSE) -> 24
B12: Production
B13: Story Points Committed | C13: In-period | D13: =VLOOKUP($B$4&" "&$B13,Actuals!$D$4:$AG$131,3,FALSE) -> # | E13: {=_xlfn.XLOOKUP( $B$4&" "&$B13, Actuals!$D:$D, _xlfn.XLOOKUP( E$6, Actuals!$H$3:$BD$3, Actuals!$H:$BD ) )} -> 220 | F13: {=_xlfn.XLOOKUP( $B$4&" "&$B13, Actuals!$D:$D, _xlfn.XLOOKUP( F$6, Actuals!$H$3:$BD$3, Actuals!$H:$BD ) )} -> 159 | G13: {=_xlfn.XLOOKUP( $B$4&" "&$B13, Actuals!$D:$D, _xlfn.XLOOKUP( G$6, Actuals!$H$3:$BD$3, Actuals!$H:$BD ) )} -> 196 | H13: {=_xlfn.XLOOKUP( $B$4&" "&$B13, Actuals!$D:$D, _xlfn.XLOOKUP( H$6, Actuals!$H$3:$BD$3, Actuals!$H:$BD ) )} -> 115 | I13: {=_xlfn.XLOOKUP( $B$4&" "&$B13, Actuals!$D:$D, _xlfn.XLOOKUP( I$6, Actuals!$H$3:$BD$3, Actuals!$H:$BD ) )} -> 265 | J13: {=_xlfn.XLOOKUP( $B$4&" "&$B13, Actuals!$D:$D, _xlfn.XLOOKUP( J$6, Actuals!$H$3:$BD$3, Actuals!$H:$BD ) )} -> 223 | K13: {=_xlfn.XLOOKUP( $B$4&" "&$B13, Actuals!$D:$D, _xlfn.XLOOKUP( K$6, Actuals!$H$3:$BD$3, Actuals!$H:$BD ) )} -> 234 | L13: {=_xlfn.XLOOKUP( $B$4&" "&$B13, Actuals!$D:$D, _xlfn.XLOOKUP( L$6, Actuals!$H$3:$BD$3, Actuals!$H:$BD ) )} -> 328 | ... AZ13: {=_xlfn.XLOOKUP( $B$4&" "&$B13, Actuals!$D:$D, _xlfn.XLOOKUP( AZ$6, Actuals!$H$3:$BD$3, Actuals!$H:$BD ) )} -> 0 | BB13: {=_xlfn.XLOOKUP( $B$4&" "&$B13, Actuals!$D:$D, _xlfn.XLOOKUP( BB$7, Actuals!$H$3:$BM$3, Actuals!$H:$BM ) )} -> 391 | BC13: =VLOOKUP($B$4&" "&$B13,Budget!$AG$4:$AL$132,$BB$5+1,FALSE) -> 702 | BD13: =BB13-BC13 -> -311 | BF13: {=_xlfn.XLOOKUP( $B$4&" "&$B13, Actuals!$D:$D, _xlfn.XLOOKUP( BF$7, Actuals!$H$3:$BM$3, Actuals!$H:$BM ) )} -> 0 | BG13: =VLOOKUP($B$4&" "&$B13,Budget!$AG$4:$AL$132,BF$5+1,FALSE) -> 773.5 | BH13: =BF13-BG13 -> -773.5 | BJ13: {=_xlfn.XLOOKUP( $B$4&" "&$B13, Actuals!$D:$D, _xlfn.XLOOKUP( BJ$7, Actuals!$H$3:$BM$3, Actuals!$H:$BM ) )} -> 0 | BK13: =VLOOKUP($B$4&" "&$B13,Budget!$AG$4:$AL$132,BJ$5+1,FALSE) -> 821.16667 | BL13: =BJ13-BK13 -> -821.16667 | BN13: {=_xlfn.XLOOKUP( $B$4&" "&$B13, Actuals!$D:$D, _xlfn.XLOOKUP( BN$7, Actuals!$H$3:$BM$3, Actuals!$H:$BM ) )} -> 0 | BO13: =VLOOKUP($B$4&" "&$B13,Budget!$AG$4:$AL$132,BN$5+1,FALSE) -> 929.5 | BR13: {=_xlfn.XLOOKUP( $B$4&" "&$B13, Actuals!$D:$D, _xlfn.XLOOKUP( BR$6, Actuals!$H$3:$BM$3, Actuals!$H:$BM ) )} -> 391 | BS13: =VLOOKUP($B$4&" "&$B13,Budget!$AG$4:$AL$132,6,FALSE) -> 3250 | BT13: =IFERROR(BR13-BS13,"-") -> -2859 | BV13: {=_xlfn.XLOOKUP( $B$4&" "&$B13, Actuals!$D:$D, _xlfn.XLOOKUP( BV$6, Actuals!$H$3:$BM$3, Actuals!$H:$BM ) )} -> 3998
B14: Story Points Completed | C14: In-period | D14: =VLOOKUP($B$4&" "&$B14,Actuals!$D$4:$AG$131,3,FALSE) -> # | E14: {=_xlfn.XLOOKUP( $B$4&" "&$B14, Actuals!$D:$D, _xlfn.XLOOKUP( E$6, Actuals!$H$3:$BD$3, Actuals!$H:$BD ) )} -> 139 | F14: {=_xlfn.XLOOKUP( $B$4&" "&$B14, Actuals!$D:$D, _xlfn.XLOOKUP( F$6, Actuals!$H$3:$BD$3, Actuals!$H:$BD ) )} -> 185 | G14: {=_xlfn.XLOOKUP( $B$4&" "&$B14, Actuals!$D:$D, _xlfn.XLOOKUP( G$6, Actuals!$H$3:$BD$3, Actuals!$H:$BD ) )} -> 117 | H14: {=_xlfn.XLOOKUP( $B$4&" "&$B14, Actuals!$D:$D, _xlfn.XLOOKUP( H$6, Actuals!$H$3:$BD$3, Actuals!$H:$BD ) )} -> 262 | I14: {=_xlfn.XLOOKUP( $B$4&" "&$B14, Actuals!$D:$D, _xlfn.XLOOKUP( I$6, Actuals!$H$3:$BD$3, Actuals!$H:$BD ) )} -> 136 | J14: {=_xlfn.XLOOKUP( $B$4&" "&$B14, Actuals!$D:$D, _xlfn.XLOOKUP( J$6, Actuals!$H$3:$BD$3, Actuals!$H:$BD ) )} -> 164 | K14: {=_xlfn.XLOOKUP( $B$4&" "&$B14, Actuals!$D:$D, _xlfn.XLOOKUP( K$6, Actuals!$H$3:$BD$3, Actuals!$H:$BD ) )} -> 142 | L14: {=_xlfn.XLOOKUP( $B$4&" "&$B14, Actuals!$D:$D, _xlfn.XLOOKUP( L$6, Actuals!$H$3:$BD$3, Actuals!$H:$BD ) )} -> 115 | ... AZ14: {=_xlfn.XLOOKUP( $B$4&" "&$B14, Actuals!$D:$D, _xlfn.XLOOKUP( AZ$6, Actuals!$H$3:$BD$3, Actuals!$H:$BD ) )} -> 0 | BB14: {=_xlfn.XLOOKUP( $B$4&" "&$B14, Actuals!$D:$D, _xlfn.XLOOKUP( BB$7, Actuals!$H$3:$BM$3, Actuals!$H:$BM ) )} -> 350 | BC14: =VLOOKUP($B$4&" "&$B14,Budget!$AG$4:$AL$132,$BB$5+1,FALSE) -> 0 | BD14: =BB14-BC14 -> 350 | BF14: {=_xlfn.XLOOKUP( $B$4&" "&$B14, Actuals!$D:$D, _xlfn.XLOOKUP( BF$7, Actuals!$H$3:$BM$3, Actuals!$H:$BM ) )} -> 0 | BG14: =VLOOKUP($B$4&" "&$B14,Budget!$AG$4:$AL$132,BF$5+1,FALSE) -> 0 | BH14: =BF14-BG14 -> 0 | BJ14: {=_xlfn.XLOOKUP( $B$4&" "&$B14, Actuals!$D:$D, _xlfn.XLOOKUP( BJ$7, Actuals!$H$3:$BM$3, Actuals!$H:$BM ) )} -> 0 | BK14: =VLOOKUP($B$4&" "&$B14,Budget!$AG$4:$AL$132,BJ$5+1,FALSE) -> 0 | BL14: =BJ14-BK14 -> 0 | BN14: {=_xlfn.XLOOKUP( $B$4&" "&$B14, Actuals!$D:$D, _xlfn.XLOOKUP( BN$7, Actuals!$H$3:$BM$3, Actuals!$H:$BM ) )} -> 0 | BO14: =VLOOKUP($B$4&" "&$B14,Budget!$AG$4:$AL$132,BN$5+1,FALSE) -> 0 | BR14: {=_xlfn.XLOOKUP( $B$4&" "&$B14, Actuals!$D:$D, _xlfn.XLOOKUP( BR$6, Actuals!$H$3:$BM$3, Actuals!$H:$BM ) )} -> 350 | BS14: =VLOOKUP($B$4&" "&$B14,Budget!$AG$4:$AL$132,6,FALSE) -> 0 | BT14: =IFERROR(BR14-BS14,"-") -> 350 | BV14: {=_xlfn.XLOOKUP( $B$4&" "&$B14, Actuals!$D:$D, _xlfn.XLOOKUP( BV$6, Actuals!$H$3:$BM$3, Actuals!$H:$BM ) )} -> 3610
B15: % Completed | C15: In-period | D15: =VLOOKUP($B$4&" "&$B15,Actuals!$D$4:$AG$131,3,FALSE) -> % | E15: {=_xlfn.XLOOKUP( $B$4&" "&$B15, Actuals!$D:$D, _xlfn.XLOOKUP( E$6, Actuals!$H$3:$BD$3, Actuals!$H:$BD ) )} -> 0.63181818 | F15: {=_xlfn.XLOOKUP( $B$4&" "&$B15, Actuals!$D:$D, _xlfn.XLOOKUP( F$6, Actuals!$H$3:$BD$3, Actuals!$H:$BD ) )} -> 1.163522 | G15: {=_xlfn.XLOOKUP( $B$4&" "&$B15, Actuals!$D:$D, _xlfn.XLOOKUP( G$6, Actuals!$H$3:$BD$3, Actuals!$H:$BD ) )} -> 0.59693878 | H15: {=_xlfn.XLOOKUP( $B$4&" "&$B15, Actuals!$D:$D, _xlfn.XLOOKUP( H$6, Actuals!$H$3:$BD$3, Actuals!$H:$BD ) )} -> 2.2782609 | I15: {=_xlfn.XLOOKUP( $B$4&" "&$B15, Actuals!$D:$D, _xlfn.XLOOKUP( I$6, Actuals!$H$3:$BD$3, Actuals!$H:$BD ) )} -> 0.51320755 | J15: {=_xlfn.XLOOKUP( $B$4&" "&$B15, Actuals!$D:$D, _xlfn.XLOOKUP( J$6, Actuals!$H$3:$BD$3, Actuals!$H:$BD ) )} -> 0.73542601 | K15: {=_xlfn.XLOOKUP( $B$4&" "&$B15, Actuals!$D:$D, _xlfn.XLOOKUP( K$6, Actuals!$H$3:$BD$3, Actuals!$H:$BD ) )} -> 0.60683761 | L15: {=_xlfn.XLOOKUP( $B$4&" "&$B15, Actuals!$D:$D, _xlfn.XLOOKUP( L$6, Actuals!$H$3:$BD$3, Actuals!$H:$BD ) )} -> 0.35060976 | ... AZ15: {=_xlfn.XLOOKUP( $B$4&" "&$B15, Actuals!$D:$D, _xlfn.XLOOKUP( AZ$6, Actuals!$H$3:$BD$3, Actuals!$H:$BD ) )} | BB15: {=_xlfn.XLOOKUP( $B$4&" "&$B15, Actuals!$D:$D, _xlfn.XLOOKUP( BB$7, Actuals!$H$3:$BM$3, Actuals!$H:$BM ) )} -> 0.89514066 | BC15: =VLOOKUP($B$4&" "&$B15,Budget!$AG$4:$AL$132,$BB$5+1,FALSE) -> 0 | BD15: =IFERROR(BB15-BC15,"-") -> 0.89514066 | BF15: {=_xlfn.XLOOKUP( $B$4&" "&$B15, Actuals!$D:$D, _xlfn.XLOOKUP( BF$7, Actuals!$H$3:$BM$3, Actuals!$H:$BM ) )} -> - | BG15: =VLOOKUP($B$4&" "&$B15,Budget!$AG$4:$AL$132,BF$5+1,FALSE) -> 0 | BH15: =IFERROR(BF15-BG15,"-") -> - | BJ15: {=_xlfn.XLOOKUP( $B$4&" "&$B15, Actuals!$D:$D, _xlfn.XLOOKUP( BJ$7, Actuals!$H$3:$BM$3, Actuals!$H:$BM ) )} -> - | BK15: =VLOOKUP($B$4&" "&$B15,Budget!$AG$4:$AL$132,BJ$5+1,FALSE) -> 0 | BL15: =IFERROR(BJ15-BK15,"-") -> - | BN15: {=_xlfn.XLOOKUP( $B$4&" "&$B15, Actuals!$D:$D, _xlfn.XLOOKUP( BN$7, Actuals!$H$3:$BM$3, Actuals!$H:$BM ) )} -> - | BO15: =VLOOKUP($B$4&" "&$B15,Budget!$AG$4:$AL$132,BN$5+1,FALSE) -> 0 | BR15: {=_xlfn.XLOOKUP( $B$4&" "&$B15, Actuals!$D:$D, _xlfn.XLOOKUP( BR$6, Actuals!$H$3:$BM$3, Actuals!$H:$BM ) )} -> 0.89514066 | BS15: =VLOOKUP($B$4&" "&$B15,Budget!$AG$4:$AL$132,6,FALSE) -> 0 | BT15: =IFERROR(BR15-BS15,"-") -> 0.89514066 | BV15: {=_xlfn.XLOOKUP( $B$4&" "&$B15, Actuals!$D:$D, _xlfn.XLOOKUP( BV$6, Actuals!$H$3:$BM$3, Actuals!$H:$BM ) )}
B17: Story Point Breakout %
B18: Product | C18: In-period | D18: =VLOOKUP($B$4&" "&$B18,Actuals!$D$4:$AG$131,3,FALSE) -> % | E18: {=_xlfn.XLOOKUP( $B$4&" "&$B18, Actuals!$D:$D, _xlfn.XLOOKUP( E$6, Actuals!$H$3:$BD$3, Actuals!$H:$BD ) )} -> 1 | F18: {=_xlfn.XLOOKUP( $B$4&" "&$B18, Actuals!$D:$D, _xlfn.XLOOKUP( F$6, Actuals!$H$3:$BD$3, Actuals!$H:$BD ) )} -> 1 | G18: {=_xlfn.XLOOKUP( $B$4&" "&$B18, Actuals!$D:$D, _xlfn.XLOOKUP( G$6, Actuals!$H$3:$BD$3, Actuals!$H:$BD ) )} -> 1 | H18: {=_xlfn.XLOOKUP( $B$4&" "&$B18, Actuals!$D:$D, _xlfn.XLOOKUP( H$6, Actuals!$H$3:$BD$3, Actuals!$H:$BD ) )} -> 0.95 | I18: {=_xlfn.XLOOKUP( $B$4&" "&$B18, Actuals!$D:$D, _xlfn.XLOOKUP( I$6, Actuals!$H$3:$BD$3, Actuals!$H:$BD ) )} -> 0.97 | J18: {=_xlfn.XLOOKUP( $B$4&" "&$B18, Actuals!$D:$D, _xlfn.XLOOKUP( J$6, Actuals!$H$3:$BD$3, Actuals!$H:$BD ) )} -> 0.98 | K18: {=_xlfn.XLOOKUP( $B$4&" "&$B18, Actuals!$D:$D, _xlfn.XLOOKUP( K$6, Actuals!$H$3:$BD$3, Actuals!$H:$BD ) )} -> 0.98 | L18: {=_xlfn.XLOOKUP( $B$4&" "&$B18, Actuals!$D:$D, _xlfn.XLOOKUP( L$6, Actuals!$H$3:$BD$3, Actuals!$H:$BD ) )} -> 0.98 | ... AZ18: {=_xlfn.XLOOKUP( $B$4&" "&$B18, Actuals!$D:$D, _xlfn.XLOOKUP( AZ$6, Actuals!$H$3:$BD$3, Actuals!$H:$BD ) )} -> 0 | BB18: {=_xlfn.XLOOKUP( $B$4&" "&$B18, Actuals!$D:$D, _xlfn.XLOOKUP( BB$7, Actuals!$H$3:$BM$3, Actuals!$H:$BM ) )} -> 0.75 | BC18: =VLOOKUP($B$4&" "&$B18,Budget!$AG$4:$AL$132,$BB$5+1,FALSE) -> 0.95 | BD18: =IFERROR(BB18-BC18,"-") -> -0.2 | BF18: {=_xlfn.XLOOKUP( $B$4&" "&$B18, Actuals!$D:$D, _xlfn.XLOOKUP( BF$7, Actuals!$H$3:$BM$3, Actuals!$H:$BM ) )} -> - | BG18: =VLOOKUP($B$4&" "&$B18,Budget!$AG$4:$AL$132,BF$5+1,FALSE) -> 0.95 | BH18: =IFERROR(BF18-BG18,"-") -> - | BJ18: {=_xlfn.XLOOKUP( $B$4&" "&$B18, Actuals!$D:$D, _xlfn.XLOOKUP( BJ$7, Actuals!$H$3:$BM$3, Actuals!$H:$BM ) )} -> - | BK18: =VLOOKUP($B$4&" "&$B18,Budget!$AG$4:$AL$132,BJ$5+1,FALSE) -> 0.95 | BL18: =IFERROR(BJ18-BK18,"-") -> - | BN18: {=_xlfn.XLOOKUP( $B$4&" "&$B18, Actuals!$D:$D, _xlfn.XLOOKUP( BN$7, Actuals!$H$3:$BM$3, Actuals!$H:$BM ) )} -> - | BO18: =VLOOKUP($B$4&" "&$B18,Budget!$AG$4:$AL$132,BN$5+1,FALSE) -> 0.95 | BR18: {=_xlfn.XLOOKUP( $B$4&" "&$B18, Actuals!$D:$D, _xlfn.XLOOKUP( BR$6, Actuals!$H$3:$BM$3, Actuals!$H:$BM ) )} -> 0.125 | BS18: =VLOOKUP($B$4&" "&$B18,Budget!$AG$4:$AL$132,6,FALSE) -> 0.95 | BT18: =IFERROR(BR18-BS18,"-") -> -0.825 | BV18: {=_xlfn.XLOOKUP( $B$4&" "&$B18, Actuals!$D:$D, _xlfn.XLOOKUP( BV$6, Actuals!$H$3:$BM$3, Actuals!$H:$BM ) )} -> 0.81833333
B19: Maintenance / Internal | C19: In-period | D19: =VLOOKUP($B$4&" "&$B19,Actuals!$D$4:$AG$131,3,FALSE) -> % | E19: {=_xlfn.XLOOKUP( $B$4&" "&$B19, Actuals!$D:$D, _xlfn.XLOOKUP( E$6, Actuals!$H$3:$BD$3, Actuals!$H:$BD ) )} -> 0 | F19: {=_xlfn.XLOOKUP( $B$4&" "&$B19, Actuals!$D:$D, _xlfn.XLOOKUP( F$6, Actuals!$H$3:$BD$3, Actuals!$H:$BD ) )} -> 0 | G19: {=_xlfn.XLOOKUP( $B$4&" "&$B19, Actuals!$D:$D, _xlfn.XLOOKUP( G$6, Actuals!$H$3:$BD$3, Actuals!$H:$BD ) )} -> 0 | H19: {=_xlfn.XLOOKUP( $B$4&" "&$B19, Actuals!$D:$D, _xlfn.XLOOKUP( H$6, Actuals!$H$3:$BD$3, Actuals!$H:$BD ) )} -> 0.05 | I19: {=_xlfn.XLOOKUP( $B$4&" "&$B19, Actuals!$D:$D, _xlfn.XLOOKUP( I$6, Actuals!$H$3:$BD$3, Actuals!$H:$BD ) )} -> 0.03 | J19: {=_xlfn.XLOOKUP( $B$4&" "&$B19, Actuals!$D:$D, _xlfn.XLOOKUP( J$6, Actuals!$H$3:$BD$3, Actuals!$H:$BD ) )} -> 0.02 | K19: {=_xlfn.XLOOKUP( $B$4&" "&$B19, Actuals!$D:$D, _xlfn.XLOOKUP( K$6, Actuals!$H$3:$BD$3, Actuals!$H:$BD ) )} -> 0.02 | L19: {=_xlfn.XLOOKUP( $B$4&" "&$B19, Actuals!$D:$D, _xlfn.XLOOKUP( L$6, Actuals!$H$3:$BD$3, Actuals!$H:$BD ) )} -> 0.02 | ... AZ19: {=_xlfn.XLOOKUP( $B$4&" "&$B19, Actuals!$D:$D, _xlfn.XLOOKUP( AZ$6, Actuals!$H$3:$BD$3, Actuals!$H:$BD ) )} -> 0 | BB19: {=_xlfn.XLOOKUP( $B$4&" "&$B19, Actuals!$D:$D, _xlfn.XLOOKUP( BB$7, Actuals!$H$3:$BM$3, Actuals!$H:$BM ) )} -> 0.25 | BC19: =VLOOKUP($B$4&" "&$B19,Budget!$AG$4:$AL$132,$BB$5+1,FALSE) -> 0.05 | BD19: =IFERROR(BB19-BC19,"-") -> 0.2 | BF19: {=_xlfn.XLOOKUP( $B$4&" "&$B19, Actuals!$D:$D, _xlfn.XLOOKUP( BF$7, Actuals!$H$3:$BM$3, Actuals!$H:$BM ) )} -> - | BG19: =VLOOKUP($B$4&" "&$B19,Budget!$AG$4:$AL$132,BF$5+1,FALSE) -> 0.05 | BH19: =IFERROR(BF19-BG19,"-") -> - | BJ19: {=_xlfn.XLOOKUP( $B$4&" "&$B19, Actuals!$D:$D, _xlfn.XLOOKUP( BJ$7, Actuals!$H$3:$BM$3, Actuals!$H:$BM ) )} -> - | BK19: =VLOOKUP($B$4&" "&$B19,Budget!$AG$4:$AL$132,BJ$5+1,FALSE) -> 0.05 | BL19: =IFERROR(BJ19-BK19,"-") -> - | BN19: {=_xlfn.XLOOKUP( $B$4&" "&$B19, Actuals!$D:$D, _xlfn.XLOOKUP( BN$7, Actuals!$H$3:$BM$3, Actuals!$H:$BM ) )} -> - | BO19: =VLOOKUP($B$4&" "&$B19,Budget!$AG$4:$AL$132,BN$5+1,FALSE) -> 0.05 | BR19: {=_xlfn.XLOOKUP( $B$4&" "&$B19, Actuals!$D:$D, _xlfn.XLOOKUP( BR$6, Actuals!$H$3:$BM$3, Actuals!$H:$BM ) )} -> 0.041666667 | BS19: =VLOOKUP($B$4&" "&$B19,Budget!$AG$4:$AL$132,6,FALSE) -> 0.05 | BT19: =IFERROR(BR19-BS19,"-") -> -0.0083333333 | BV19: {=_xlfn.XLOOKUP( $B$4&" "&$B19, Actuals!$D:$D, _xlfn.XLOOKUP( BV$6, Actuals!$H$3:$BM$3, Actuals!$H:$BM ) )} -> 0.18166667
B21: Efficiency
B22: Headcount (Total) | C22: EoP | D22: =VLOOKUP($B$4&" "&$B22,Actuals!$D$4:$AG$131,3,FALSE) -> # | E22: {=_xlfn.XLOOKUP( $B$4&" "&$B22, Actuals!$D:$D, _xlfn.XLOOKUP( E$6, Actuals!$H$3:$BD$3, Actuals!$H:$BD ) )} -> 10 | F22: {=_xlfn.XLOOKUP( $B$4&" "&$B22, Actuals!$D:$D, _xlfn.XLOOKUP( F$6, Actuals!$H$3:$BD$3, Actuals!$H:$BD ) )} -> 11 | G22: {=_xlfn.XLOOKUP( $B$4&" "&$B22, Actuals!$D:$D, _xlfn.XLOOKUP( G$6, Actuals!$H$3:$BD$3, Actuals!$H:$BD ) )} -> 12 | H22: {=_xlfn.XLOOKUP( $B$4&" "&$B22, Actuals!$D:$D, _xlfn.XLOOKUP( H$6, Actuals!$H$3:$BD$3, Actuals!$H:$BD ) )} -> 12 | I22: {=_xlfn.XLOOKUP( $B$4&" "&$B22, Actuals!$D:$D, _xlfn.XLOOKUP( I$6, Actuals!$H$3:$BD$3, Actuals!$H:$BD ) )} -> 12 | J22: {=_xlfn.XLOOKUP( $B$4&" "&$B22, Actuals!$D:$D, _xlfn.XLOOKUP( J$6, Actuals!$H$3:$BD$3, Actuals!$H:$BD ) )} -> 14 | K22: {=_xlfn.XLOOKUP( $B$4&" "&$B22, Actuals!$D:$D, _xlfn.XLOOKUP( K$6, Actuals!$H$3:$BD$3, Actuals!$H:$BD ) )} -> 17 | L22: {=_xlfn.XLOOKUP( $B$4&" "&$B22, Actuals!$D:$D, _xlfn.XLOOKUP( L$6, Actuals!$H$3:$BD$3, Actuals!$H:$BD ) )} -> 17 | ... AZ22: {=_xlfn.XLOOKUP( $B$4&" "&$B22, Actuals!$D:$D, _xlfn.XLOOKUP( AZ$6, Actuals!$H$3:$BD$3, Actuals!$H:$BD ) )} -> 0 | BB22: {=_xlfn.XLOOKUP( $B$4&" "&$B22, Actuals!$D:$D, _xlfn.XLOOKUP( BB$7, Actuals!$H$3:$BM$3, Actuals!$H:$BM ) )} -> 0 | BC22: =VLOOKUP($B$4&" "&$B22,Budget!$AG$4:$AL$132,$BB$5+1,FALSE) -> 0 | BD22: =BB22-BC22 -> 0 | BF22: {=_xlfn.XLOOKUP( $B$4&" "&$B22, Actuals!$D:$D, _xlfn.XLOOKUP( BF$7, Actuals!$H$3:$BM$3, Actuals!$H:$BM ) )} -> 0 | BG22: =VLOOKUP($B$4&" "&$B22,Budget!$AG$4:$AL$132,BF$5+1,FALSE) -> 25 | BH22: =BF22-BG22 -> -25 | BJ22: {=_xlfn.XLOOKUP( $B$4&" "&$B22, Actuals!$D:$D, _xlfn.XLOOKUP( BJ$7, Actuals!$H$3:$BM$3, Actuals!$H:$BM ) )} -> 0 | BK22: =VLOOKUP($B$4&" "&$B22,Budget!$AG$4:$AL$132,BJ$5+1,FALSE) -> 25 | BL22: =BJ22-BK22 -> -25 | BN22: {=_xlfn.XLOOKUP( $B$4&" "&$B22, Actuals!$D:$D, _xlfn.XLOOKUP( BN$7, Actuals!$H$3:$BM$3, Actuals!$H:$BM ) )} -> 0 | BO22: =VLOOKUP($B$4&" "&$B22,Budget!$AG$4:$AL$132,BN$5+1,FALSE) -> 25 | BR22: {=_xlfn.XLOOKUP( $B$4&" "&$B22, Actuals!$D:$D, _xlfn.XLOOKUP( BR$6, Actuals!$H$3:$BM$3, Actuals!$H:$BM ) )} -> 0 | BS22: =VLOOKUP($B$4&" "&$B22,Budget!$AG$4:$AL$132,6,FALSE) -> 25 | BT22: =IFERROR(BR22-BS22,"-") -> -25 | BV22: {=_xlfn.XLOOKUP( $B$4&" "&$B22, Actuals!$D:$D, _xlfn.XLOOKUP( BV$6, Actuals!$H$3:$BM$3, Actuals!$H:$BM ) )} -> 15
B23: Headcount - Squad - Onshore | C23: EoP | D23: =VLOOKUP($B$4&" "&$B23,Actuals!$D$4:$AG$131,3,FALSE) -> # | E23: {=_xlfn.XLOOKUP( $B$4&" "&$B23, Actuals!$D:$D, _xlfn.XLOOKUP( E$6, Actuals!$H$3:$BD$3, Actuals!$H:$BD ) )} -> 7 | F23: {=_xlfn.XLOOKUP( $B$4&" "&$B23, Actuals!$D:$D, _xlfn.XLOOKUP( F$6, Actuals!$H$3:$BD$3, Actuals!$H:$BD ) )} -> 6 | G23: {=_xlfn.XLOOKUP( $B$4&" "&$B23, Actuals!$D:$D, _xlfn.XLOOKUP( G$6, Actuals!$H$3:$BD$3, Actuals!$H:$BD ) )} -> 7 | H23: {=_xlfn.XLOOKUP( $B$4&" "&$B23, Actuals!$D:$D, _xlfn.XLOOKUP( H$6, Actuals!$H$3:$BD$3, Actuals!$H:$BD ) )} -> 7 | I23: {=_xlfn.XLOOKUP( $B$4&" "&$B23, Actuals!$D:$D, _xlfn.XLOOKUP( I$6, Actuals!$H$3:$BD$3, Actuals!$H:$BD ) )} -> 7 | J23: {=_xlfn.XLOOKUP( $B$4&" "&$B23, Actuals!$D:$D, _xlfn.XLOOKUP( J$6, Actuals!$H$3:$BD$3, Actuals!$H:$BD ) )} -> 7 | K23: {=_xlfn.XLOOKUP( $B$4&" "&$B23, Actuals!$D:$D, _xlfn.XLOOKUP( K$6, Actuals!$H$3:$BD$3, Actuals!$H:$BD ) )} -> 8 | L23: {=_xlfn.XLOOKUP( $B$4&" "&$B23, Actuals!$D:$D, _xlfn.XLOOKUP( L$6, Actuals!$H$3:$BD$3, Actuals!$H:$BD ) )} -> 8 | ... AZ23: {=_xlfn.XLOOKUP( $B$4&" "&$B23, Actuals!$D:$D, _xlfn.XLOOKUP( AZ$6, Actuals!$H$3:$BD$3, Actuals!$H:$BD ) )} -> 0 | BB23: {=_xlfn.XLOOKUP( $B$4&" "&$B23, Actuals!$D:$D, _xlfn.XLOOKUP( BB$7, Actuals!$H$3:$BM$3, Actuals!$H:$BM ) )} -> 0 | BC23: =VLOOKUP($B$4&" "&$B23,Budget!$AG$4:$AL$132,$BB$5+1,FALSE) -> 0 | BD23: =BB23-BC23 -> 0 | BF23: {=_xlfn.XLOOKUP( $B$4&" "&$B23, Actuals!$D:$D, _xlfn.XLOOKUP( BF$7, Actuals!$H$3:$BM$3, Actuals!$H:$BM ) )} -> 0 | BG23: =VLOOKUP($B$4&" "&$B23,Budget!$AG$4:$AL$132,BF$5+1,FALSE) -> 12 | BH23: =BF23-BG23 -> -12 | BJ23: {=_xlfn.XLOOKUP( $B$4&" "&$B23, Actuals!$D:$D, _xlfn.XLOOKUP( BJ$7, Actuals!$H$3:$BM$3, Actuals!$H:$BM ) )} -> 0 | BK23: =VLOOKUP($B$4&" "&$B23,Budget!$AG$4:$AL$132,BJ$5+1,FALSE) -> 12 | BL23: =BJ23-BK23 -> -12 | BN23: {=_xlfn.XLOOKUP( $B$4&" "&$B23, Actuals!$D:$D, _xlfn.XLOOKUP( BN$7, Actuals!$H$3:$BM$3, Actuals!$H:$BM ) )} -> 0 | BO23: =VLOOKUP($B$4&" "&$B23,Budget!$AG$4:$AL$132,BN$5+1,FALSE) -> 12 | BR23: {=_xlfn.XLOOKUP( $B$4&" "&$B23, Actuals!$D:$D, _xlfn.XLOOKUP( BR$6, Actuals!$H$3:$BM$3, Actuals!$H:$BM ) )} -> 0 | BS23: =VLOOKUP($B$4&" "&$B23,Budget!$AG$4:$AL$132,6,FALSE) -> 12 | BT23: =IFERROR(BR23-BS23,"-") -> -12 | BV23: {=_xlfn.XLOOKUP( $B$4&" "&$B23, Actuals!$D:$D, _xlfn.XLOOKUP( BV$6, Actuals!$H$3:$BM$3, Actuals!$H:$BM ) )} -> 3
B24: Headcount - Squad - Offshore | C24: EoP | D24: =VLOOKUP($B$4&" "&$B24,Actuals!$D$4:$AG$131,3,FALSE) -> # | E24: {=_xlfn.XLOOKUP( $B$4&" "&$B24, Actuals!$D:$D, _xlfn.XLOOKUP( E$6, Actuals!$H$3:$BD$3, Actuals!$H:$BD ) )} -> 3 | F24: {=_xlfn.XLOOKUP( $B$4&" "&$B24, Actuals!$D:$D, _xlfn.XLOOKUP( F$6, Actuals!$H$3:$BD$3, Actuals!$H:$BD ) )} -> 5 | G24: {=_xlfn.XLOOKUP( $B$4&" "&$B24, Actuals!$D:$D, _xlfn.XLOOKUP( G$6, Actuals!$H$3:$BD$3, Actuals!$H:$BD ) )} -> 5 | H24: {=_xlfn.XLOOKUP( $B$4&" "&$B24, Actuals!$D:$D, _xlfn.XLOOKUP( H$6, Actuals!$H$3:$BD$3, Actuals!$H:$BD ) )} -> 5 | I24: {=_xlfn.XLOOKUP( $B$4&" "&$B24, Actuals!$D:$D, _xlfn.XLOOKUP( I$6, Actuals!$H$3:$BD$3, Actuals!$H:$BD ) )} -> 5 | J24: {=_xlfn.XLOOKUP( $B$4&" "&$B24, Actuals!$D:$D, _xlfn.XLOOKUP( J$6, Actuals!$H$3:$BD$3, Actuals!$H:$BD ) )} -> 7 | K24: {=_xlfn.XLOOKUP( $B$4&" "&$B24, Actuals!$D:$D, _xlfn.XLOOKUP( K$6, Actuals!$H$3:$BD$3, Actuals!$H:$BD ) )} -> 9 | L24: {=_xlfn.XLOOKUP( $B$4&" "&$B24, Actuals!$D:$D, _xlfn.XLOOKUP( L$6, Actuals!$H$3:$BD$3, Actuals!$H:$BD ) )} -> 9 | ... AZ24: {=_xlfn.XLOOKUP( $B$4&" "&$B24, Actuals!$D:$D, _xlfn.XLOOKUP( AZ$6, Actuals!$H$3:$BD$3, Actuals!$H:$BD ) )} -> 0 | BB24: {=_xlfn.XLOOKUP( $B$4&" "&$B24, Actuals!$D:$D, _xlfn.XLOOKUP( BB$7, Actuals!$H$3:$BM$3, Actuals!$H:$BM ) )} -> 0 | BC24: =VLOOKUP($B$4&" "&$B24,Budget!$AG$4:$AL$132,$BB$5+1,FALSE) -> 0 | BD24: =BB24-BC24 -> 0 | BF24: {=_xlfn.XLOOKUP( $B$4&" "&$B24, Actuals!$D:$D, _xlfn.XLOOKUP( BF$7, Actuals!$H$3:$BM$3, Actuals!$H:$BM ) )} -> 0 | BG24: =VLOOKUP($B$4&" "&$B24,Budget!$AG$4:$AL$132,BF$5+1,FALSE) -> 13 | BH24: =BF24-BG24 -> -13 | BJ24: {=_xlfn.XLOOKUP( $B$4&" "&$B24, Actuals!$D:$D, _xlfn.XLOOKUP( BJ$7, Actuals!$H$3:$BM$3, Actuals!$H:$BM ) )} -> 0 | BK24: =VLOOKUP($B$4&" "&$B24,Budget!$AG$4:$AL$132,BJ$5+1,FALSE) -> 13 | BL24: =BJ24-BK24 -> -13 | BN24: {=_xlfn.XLOOKUP( $B$4&" "&$B24, Actuals!$D:$D, _xlfn.XLOOKUP( BN$7, Actuals!$H$3:$BM$3, Actuals!$H:$BM ) )} -> 0 | BO24: =VLOOKUP($B$4&" "&$B24,Budget!$AG$4:$AL$132,BN$5+1,FALSE) -> 13 | BR24: {=_xlfn.XLOOKUP( $B$4&" "&$B24, Actuals!$D:$D, _xlfn.XLOOKUP( BR$6, Actuals!$H$3:$BM$3, Actuals!$H:$BM ) )} -> 0 | BS24: =VLOOKUP($B$4&" "&$B24,Budget!$AG$4:$AL$132,6,FALSE) -> 13 | BT24: =IFERROR(BR24-BS24,"-") -> -13 | BV24: {=_xlfn.XLOOKUP( $B$4&" "&$B24, Actuals!$D:$D, _xlfn.XLOOKUP( BV$6, Actuals!$H$3:$BM$3, Actuals!$H:$BM ) )} -> 12
B25: Headcount - Non-Squad | C25: EoP | D25: =VLOOKUP($B$4&" "&$B25,Actuals!$D$4:$AG$131,3,FALSE) -> # | E25: {=_xlfn.XLOOKUP( $B$4&" "&$B25, Actuals!$D:$D, _xlfn.XLOOKUP( E$6, Actuals!$H$3:$BD$3, Actuals!$H:$BD ) )} -> 0 | F25: {=_xlfn.XLOOKUP( $B$4&" "&$B25, Actuals!$D:$D, _xlfn.XLOOKUP( F$6, Actuals!$H$3:$BD$3, Actuals!$H:$BD ) )} -> 0 | G25: {=_xlfn.XLOOKUP( $B$4&" "&$B25, Actuals!$D:$D, _xlfn.XLOOKUP( G$6, Actuals!$H$3:$BD$3, Actuals!$H:$BD ) )} -> 0 | H25: {=_xlfn.XLOOKUP( $B$4&" "&$B25, Actuals!$D:$D, _xlfn.XLOOKUP( H$6, Actuals!$H$3:$BD$3, Actuals!$H:$BD ) )} -> 0 | I25: {=_xlfn.XLOOKUP( $B$4&" "&$B25, Actuals!$D:$D, _xlfn.XLOOKUP( I$6, Actuals!$H$3:$BD$3, Actuals!$H:$BD ) )} -> 0 | J25: {=_xlfn.XLOOKUP( $B$4&" "&$B25, Actuals!$D:$D, _xlfn.XLOOKUP( J$6, Actuals!$H$3:$BD$3, Actuals!$H:$BD ) )} -> 0 | K25: {=_xlfn.XLOOKUP( $B$4&" "&$B25, Actuals!$D:$D, _xlfn.XLOOKUP( K$6, Actuals!$H$3:$BD$3, Actuals!$H:$BD ) )} -> 0 | L25: {=_xlfn.XLOOKUP( $B$4&" "&$B25, Actuals!$D:$D, _xlfn.XLOOKUP( L$6, Actuals!$H$3:$BD$3, Actuals!$H:$BD ) )} -> 0 | ... AZ25: {=_xlfn.XLOOKUP( $B$4&" "&$B25, Actuals!$D:$D, _xlfn.XLOOKUP( AZ$6, Actuals!$H$3:$BD$3, Actuals!$H:$BD ) )} -> 0 | BB25: {=_xlfn.XLOOKUP( $B$4&" "&$B25, Actuals!$D:$D, _xlfn.XLOOKUP( BB$7, Actuals!$H$3:$BM$3, Actuals!$H:$BM ) )} -> 0 | BC25: =VLOOKUP($B$4&" "&$B25,Budget!$AG$4:$AL$132,$BB$5+1,FALSE) -> 0 | BD25: =BB25-BC25 -> 0 | BF25: {=_xlfn.XLOOKUP( $B$4&" "&$B25, Actuals!$D:$D, _xlfn.XLOOKUP( BF$7, Actuals!$H$3:$BM$3, Actuals!$H:$BM ) )} -> 0 | BG25: =VLOOKUP($B$4&" "&$B25,Budget!$AG$4:$AL$132,BF$5+1,FALSE) -> 0 | BH25: =BF25-BG25 -> 0 | BJ25: {=_xlfn.XLOOKUP( $B$4&" "&$B25, Actuals!$D:$D, _xlfn.XLOOKUP( BJ$7, Actuals!$H$3:$BM$3, Actuals!$H:$BM ) )} -> 0 | BK25: =VLOOKUP($B$4&" "&$B25,Budget!$AG$4:$AL$132,BJ$5+1,FALSE) -> 0 | BL25: =BJ25-BK25 -> 0 | BN25: {=_xlfn.XLOOKUP( $B$4&" "&$B25, Actuals!$D:$D, _xlfn.XLOOKUP( BN$7, Actuals!$H$3:$BM$3, Actuals!$H:$BM ) )} -> 0 | BO25: =VLOOKUP($B$4&" "&$B25,Budget!$AG$4:$AL$132,BN$5+1,FALSE) -> 0 | BR25: {=_xlfn.XLOOKUP( $B$4&" "&$B25, Actuals!$D:$D, _xlfn.XLOOKUP( BR$6, Actuals!$H$3:$BM$3, Actuals!$H:$BM ) )} -> 0 | BS25: =VLOOKUP($B$4&" "&$B25,Budget!$AG$4:$AL$132,6,FALSE) -> 0 | BT25: =IFERROR(BR25-BS25,"-") -> 0 | BV25: {=_xlfn.XLOOKUP( $B$4&" "&$B25, Actuals!$D:$D, _xlfn.XLOOKUP( BV$6, Actuals!$H$3:$BM$3, Actuals!$H:$BM ) )} -> 0
B26: Avg. Personnel Cost per Squad | C26: Avg | D26: =VLOOKUP($B$4&" "&$B26,Actuals!$D$4:$AG$131,3,FALSE) -> $ | E26: {=_xlfn.XLOOKUP( $B$4&" "&$B26, Actuals!$D:$D, _xlfn.XLOOKUP( E$6, Actuals!$H$3:$BD$3, Actuals!$H:$BD ) )} -> 69121.715 | F26: {=_xlfn.XLOOKUP( $B$4&" "&$B26, Actuals!$D:$D, _xlfn.XLOOKUP( F$6, Actuals!$H$3:$BD$3, Actuals!$H:$BD ) )} -> 72497.695 | G26: {=_xlfn.XLOOKUP( $B$4&" "&$B26, Actuals!$D:$D, _xlfn.XLOOKUP( G$6, Actuals!$H$3:$BD$3, Actuals!$H:$BD ) )} -> 74103.685 | H26: {=_xlfn.XLOOKUP( $B$4&" "&$B26, Actuals!$D:$D, _xlfn.XLOOKUP( H$6, Actuals!$H$3:$BD$3, Actuals!$H:$BD ) )} -> 72135.81 | I26: {=_xlfn.XLOOKUP( $B$4&" "&$B26, Actuals!$D:$D, _xlfn.XLOOKUP( I$6, Actuals!$H$3:$BD$3, Actuals!$H:$BD ) )} -> 70305.68 | J26: {=_xlfn.XLOOKUP( $B$4&" "&$B26, Actuals!$D:$D, _xlfn.XLOOKUP( J$6, Actuals!$H$3:$BD$3, Actuals!$H:$BD ) )} -> 77211.37 | K26: {=_xlfn.XLOOKUP( $B$4&" "&$B26, Actuals!$D:$D, _xlfn.XLOOKUP( K$6, Actuals!$H$3:$BD$3, Actuals!$H:$BD ) )} -> 57329.25 | L26: {=_xlfn.XLOOKUP( $B$4&" "&$B26, Actuals!$D:$D, _xlfn.XLOOKUP( L$6, Actuals!$H$3:$BD$3, Actuals!$H:$BD ) )} -> 59369.04 | ... AZ26: {=_xlfn.XLOOKUP( $B$4&" "&$B26, Actuals!$D:$D, _xlfn.XLOOKUP( AZ$6, Actuals!$H$3:$BD$3, Actuals!$H:$BD ) )} -> 0 | BB26: {=_xlfn.XLOOKUP( $B$4&" "&$B26, Actuals!$D:$D, _xlfn.XLOOKUP( BB$7, Actuals!$H$3:$BM$3, Actuals!$H:$BM ) )} -> 84656.972 | BC26: =VLOOKUP($B$4&" "&$B26,Budget!$AG$4:$AL$132,$BB$5+1,FALSE) -> 75549.333 | BD26: =IFERROR(BB26-BC26,"-") -> 9107.6388 | BF26: {=_xlfn.XLOOKUP( $B$4&" "&$B26, Actuals!$D:$D, _xlfn.XLOOKUP( BF$7, Actuals!$H$3:$BM$3, Actuals!$H:$BM ) )} -> - | BG26: =VLOOKUP($B$4&" "&$B26,Budget!$AG$4:$AL$132,BF$5+1,FALSE) -> 75549.333 | BH26: =IFERROR(BF26-BG26,"-") -> - | BJ26: {=_xlfn.XLOOKUP( $B$4&" "&$B26, Actuals!$D:$D, _xlfn.XLOOKUP( BJ$7, Actuals!$H$3:$BM$3, Actuals!$H:$BM ) )} -> - | BK26: =VLOOKUP($B$4&" "&$B26,Budget!$AG$4:$AL$132,BJ$5+1,FALSE) -> 76843.778 | BL26: =IFERROR(BJ26-BK26,"-") -> - | BN26: {=_xlfn.XLOOKUP( $B$4&" "&$B26, Actuals!$D:$D, _xlfn.XLOOKUP( BN$7, Actuals!$H$3:$BM$3, Actuals!$H:$BM ) )} -> - | BO26: =VLOOKUP($B$4&" "&$B26,Budget!$AG$4:$AL$132,BN$5+1,FALSE) -> 77566 | BR26: {=_xlfn.XLOOKUP( $B$4&" "&$B26, Actuals!$D:$D, _xlfn.XLOOKUP( BR$6, Actuals!$H$3:$BM$3, Actuals!$H:$BM ) )} -> 21164.243 | BS26: =VLOOKUP($B$4&" "&$B26,Budget!$AG$4:$AL$132,6,FALSE) -> 76545.167 | BT26: =IFERROR(BR26-BS26,"-") -> -55380.924 | BV26: {=_xlfn.XLOOKUP( $B$4&" "&$B26, Actuals!$D:$D, _xlfn.XLOOKUP( BV$6, Actuals!$H$3:$BM$3, Actuals!$H:$BM ) )} -> 101251.9
B27: P&T Overhead | C27: In-period | D27: =VLOOKUP($B$4&" "&$B27,Actuals!$D$4:$AG$131,3,FALSE) -> $ | E27: {=_xlfn.XLOOKUP( $B$4&" "&$B27, Actuals!$D:$D, _xlfn.XLOOKUP( E$6, Actuals!$H$3:$BD$3, Actuals!$H:$BD ) )} -> 3540.88 | F27: {=_xlfn.XLOOKUP( $B$4&" "&$B27, Actuals!$D:$D, _xlfn.XLOOKUP( F$6, Actuals!$H$3:$BD$3, Actuals!$H:$BD ) )} -> 12655.84 | G27: {=_xlfn.XLOOKUP( $B$4&" "&$B27, Actuals!$D:$D, _xlfn.XLOOKUP( G$6, Actuals!$H$3:$BD$3, Actuals!$H:$BD ) )} -> 5571.23 | H27: {=_xlfn.XLOOKUP( $B$4&" "&$B27, Actuals!$D:$D, _xlfn.XLOOKUP( H$6, Actuals!$H$3:$BD$3, Actuals!$H:$BD ) )} -> 3952.25 | I27: {=_xlfn.XLOOKUP( $B$4&" "&$B27, Actuals!$D:$D, _xlfn.XLOOKUP( I$6, Actuals!$H$3:$BD$3, Actuals!$H:$BD ) )} -> 7151.77 | J27: {=_xlfn.XLOOKUP( $B$4&" "&$B27, Actuals!$D:$D, _xlfn.XLOOKUP( J$6, Actuals!$H$3:$BD$3, Actuals!$H:$BD ) )} -> 3481.27 | K27: {=_xlfn.XLOOKUP( $B$4&" "&$B27, Actuals!$D:$D, _xlfn.XLOOKUP( K$6, Actuals!$H$3:$BD$3, Actuals!$H:$BD ) )} -> 28391.06 | L27: {=_xlfn.XLOOKUP( $B$4&" "&$B27, Actuals!$D:$D, _xlfn.XLOOKUP( L$6, Actuals!$H$3:$BD$3, Actuals!$H:$BD ) )} -> 3604.27 | ... AZ27: {=_xlfn.XLOOKUP( $B$4&" "&$B27, Actuals!$D:$D, _xlfn.XLOOKUP( AZ$6, Actuals!$H$3:$BD$3, Actuals!$H:$BD ) )} -> 0 | BB27: {=_xlfn.XLOOKUP( $B$4&" "&$B27, Actuals!$D:$D, _xlfn.XLOOKUP( BB$7, Actuals!$H$3:$BM$3, Actuals!$H:$BM ) )} -> 38869.1 | BC27: =VLOOKUP($B$4&" "&$B27,Budget!$AG$4:$AL$132,$BB$5+1,FALSE) -> 80112 | BD27: =BB27-BC27 -> -41242.9 | BF27: {=_xlfn.XLOOKUP( $B$4&" "&$B27, Actuals!$D:$D, _xlfn.XLOOKUP( BF$7, Actuals!$H$3:$BM$3, Actuals!$H:$BM ) )} -> 0 | BG27: =VLOOKUP($B$4&" "&$B27,Budget!$AG$4:$AL$132,BF$5+1,FALSE) -> 19044 | BH27: =BF27-BG27 -> -19044 | BJ27: {=_xlfn.XLOOKUP( $B$4&" "&$B27, Actuals!$D:$D, _xlfn.XLOOKUP( BJ$7, Actuals!$H$3:$BM$3, Actuals!$H:$BM ) )} -> 0 | BK27: =VLOOKUP($B$4&" "&$B27,Budget!$AG$4:$AL$132,BJ$5+1,FALSE) -> 30904 | BL27: =BJ27-BK27 -> -30904 | BN27: {=_xlfn.XLOOKUP( $B$4&" "&$B27, Actuals!$D:$D, _xlfn.XLOOKUP( BN$7, Actuals!$H$3:$BM$3, Actuals!$H:$BM ) )} -> 0 | BO27: =VLOOKUP($B$4&" "&$B27,Budget!$AG$4:$AL$132,BN$5+1,FALSE) -> 29584 | BR27: {=_xlfn.XLOOKUP( $B$4&" "&$B27, Actuals!$D:$D, _xlfn.XLOOKUP( BR$6, Actuals!$H$3:$BM$3, Actuals!$H:$BM ) )} -> 38869.1 | BS27: =VLOOKUP($B$4&" "&$B27,Budget!$AG$4:$AL$132,6,FALSE) -> 165824 | BT27: =IFERROR(BR27-BS27,"-") -> -126954.9 | BV27: {=_xlfn.XLOOKUP( $B$4&" "&$B27, Actuals!$D:$D, _xlfn.XLOOKUP( BV$6, Actuals!$H$3:$BM$3, Actuals!$H:$BM ) )} -> 104740.92

Sheet Sales
B2: ='2023 Control'!$C$3 -> Concertiv
B3: =('2024 Control'!$C$4)&" Reporting Package" -> December 2025 Reporting Package
B4: Sales
E5: Monthly | BB5: 1 | BF5: 2 | BJ5: 3 | BN5: 4 | BR5: YTD vs. Budget
D6: Units | E6: 44957 | F6: 44985 | G6: 45016 | H6: =EOMONTH(G6,1) -> 45046 | I6: =EOMONTH(H6,1) -> 45077 | J6: =EOMONTH(I6,1) -> 45107 | K6: =EOMONTH(J6,1) -> 45138 | L6: =EOMONTH(K6,1) -> 45169 | M6: =EOMONTH(L6,1) -> 45199 | N6: =EOMONTH(M6,1) -> 45230 | O6: =EOMONTH(N6,1) -> 45260 | ... AZ6: =EOMONTH(AY6,1) -> 46387 | BB6: Act | BC6: Bgt. | BD6: Diff. | BF6: Act | BG6: Bgt. | BH6: Diff. | BJ6: Act | BK6: Bgt. | BL6: Diff. | BN6: Act | BO6: Bgt. | BP6: Diff. | BR6: YTD | BS6: Bgt. | BT6: Diff. | BV6: LTM
BB7: Q1 | BF7: Q2 | BJ7: Q3 | BN7: Q4
B8: Sales ARR ($)
B9: New Logo ARR ($) | C9: In-period | D9: =VLOOKUP($B$4&" "&$B9,Actuals!$D$4:$AG$131,3,FALSE) -> $ | E9: {=_xlfn.XLOOKUP( $B$4&" "&$B9, Actuals!$D:$D, _xlfn.XLOOKUP( E$6, Actuals!$H$3:$BD$3, Actuals!$H:$BD ) )} -> 49000 | F9: {=_xlfn.XLOOKUP( $B$4&" "&$B9, Actuals!$D:$D, _xlfn.XLOOKUP( F$6, Actuals!$H$3:$BD$3, Actuals!$H:$BD ) )} -> 0 | G9: {=_xlfn.XLOOKUP( $B$4&" "&$B9, Actuals!$D:$D, _xlfn.XLOOKUP( G$6, Actuals!$H$3:$BD$3, Actuals!$H:$BD ) )} -> 67000 | H9: {=_xlfn.XLOOKUP( $B$4&" "&$B9, Actuals!$D:$D, _xlfn.XLOOKUP( H$6, Actuals!$H$3:$BD$3, Actuals!$H:$BD ) )} -> 6250 | I9: {=_xlfn.XLOOKUP( $B$4&" "&$B9, Actuals!$D:$D, _xlfn.XLOOKUP( I$6, Actuals!$H$3:$BD$3, Actuals!$H:$BD ) )} -> 0 | J9: {=_xlfn.XLOOKUP( $B$4&" "&$B9, Actuals!$D:$D, _xlfn.XLOOKUP( J$6, Actuals!$H$3:$BD$3, Actuals!$H:$BD ) )} -> 215055 | K9: {=_xlfn.XLOOKUP( $B$4&" "&$B9, Actuals!$D:$D, _xlfn.XLOOKUP( K$6, Actuals!$H$3:$BD$3, Actuals!$H:$BD ) )} -> 0 | L9: {=_xlfn.XLOOKUP( $B$4&" "&$B9, Actuals!$D:$D, _xlfn.XLOOKUP( L$6, Actuals!$H$3:$BD$3, Actuals!$H:$BD ) )} -> 362940 | ... AZ9: {=_xlfn.XLOOKUP( $B$4&" "&$B9, Actuals!$D:$D, _xlfn.XLOOKUP( AZ$6, Actuals!$H$3:$BD$3, Actuals!$H:$BD ) )} -> 0 | BB9: {=_xlfn.XLOOKUP( $B$4&" "&$B9, Actuals!$D:$D, _xlfn.XLOOKUP( BB$7, Actuals!$H$3:$BM$3, Actuals!$H:$BM ) )} -> 0 | BC9: =VLOOKUP($B$4&" "&$B9,Budget!$AG$4:$AL$132,$BB$5+1,FALSE) -> 320000 | BD9: =BB9-BC9 -> -320000 | BF9: {=_xlfn.XLOOKUP( $B$4&" "&$B9, Actuals!$D:$D, _xlfn.XLOOKUP( BF$7, Actuals!$H$3:$BM$3, Actuals!$H:$BM ) )} -> 0 | BG9: =VLOOKUP($B$4&" "&$B9,Budget!$AG$4:$AL$132,BF$5+1,FALSE) -> 450000 | BH9: =BF9-BG9 -> -450000 | BJ9: {=_xlfn.XLOOKUP( $B$4&" "&$B9, Actuals!$D:$D, _xlfn.XLOOKUP( BJ$7, Actuals!$H$3:$BM$3, Actuals!$H:$BM ) )} -> 0 | BK9: =VLOOKUP($B$4&" "&$B9,Budget!$AG$4:$AL$132,BJ$5+1,FALSE) -> 450000 | BL9: =BJ9-BK9 -> -450000 | BN9: {=_xlfn.XLOOKUP( $B$4&" "&$B9, Actuals!$D:$D, _xlfn.XLOOKUP( BN$7, Actuals!$H$3:$BM$3, Actuals!$H:$BM ) )} -> 0 | BO9: =VLOOKUP($B$4&" "&$B9,Budget!$AG$4:$AL$132,BN$5+1,FALSE) -> 580000 | BR9: {=_xlfn.XLOOKUP( $B$4&" "&$B9, Actuals!$D:$D, _xlfn.XLOOKUP( BR$6, Actuals!$H$3:$BM$3, Actuals!$H:$BM ) )} -> 0 | BS9: =VLOOKUP($B$4&" "&$B9,Budget!$AG$4:$AL$132,6,FALSE) -> 1800000 | BT9: =BR9-BS9 -> -1800000 | BV9: {=_xlfn.XLOOKUP( $B$4&" "&$B9, Actuals!$D:$D, _xlfn.XLOOKUP( BV$6, Actuals!$H$3:$BM$3, Actuals!$H:$BM ) )} -> 387500
B11: Pipeline Activity (in-period)
B12: Sales Generated Opps. | C12: In-period | D12: =VLOOKUP($B$4&" "&$B12,Actuals!$D$4:$AG$131,3,FALSE) -> # | E12: {=_xlfn.XLOOKUP( $B$4&" "&$B12, Actuals!$D:$D, _xlfn.XLOOKUP( E$6, Actuals!$H$3:$BD$3, Actuals!$H:$BD ) )} -> 3 | F12: {=_xlfn.XLOOKUP( $B$4&" "&$B12, Actuals!$D:$D, _xlfn.XLOOKUP( F$6, Actuals!$H$3:$BD$3, Actuals!$H:$BD ) )} -> 1 | G12: {=_xlfn.XLOOKUP( $B$4&" "&$B12, Actuals!$D:$D, _xlfn.XLOOKUP( G$6, Actuals!$H$3:$BD$3, Actuals!$H:$BD ) )} -> 2 | H12: {=_xlfn.XLOOKUP( $B$4&" "&$B12, Actuals!$D:$D, _xlfn.XLOOKUP( H$6, Actuals!$H$3:$BD$3, Actuals!$H:$BD ) )} -> 7 | I12: {=_xlfn.XLOOKUP( $B$4&" "&$B12, Actuals!$D:$D, _xlfn.XLOOKUP( I$6, Actuals!$H$3:$BD$3, Actuals!$H:$BD ) )} -> 12 | J12: {=_xlfn.XLOOKUP( $B$4&" "&$B12, Actuals!$D:$D, _xlfn.XLOOKUP( J$6, Actuals!$H$3:$BD$3, Actuals!$H:$BD ) )} -> 3 | K12: {=_xlfn.XLOOKUP( $B$4&" "&$B12, Actuals!$D:$D, _xlfn.XLOOKUP( K$6, Actuals!$H$3:$BD$3, Actuals!$H:$BD ) )} -> 5 | L12: {=_xlfn.XLOOKUP( $B$4&" "&$B12, Actuals!$D:$D, _xlfn.XLOOKUP( L$6, Actuals!$H$3:$BD$3, Actuals!$H:$BD ) )} -> 4 | ... AZ12: {=_xlfn.XLOOKUP( $B$4&" "&$B12, Actuals!$D:$D, _xlfn.XLOOKUP( AZ$6, Actuals!$H$3:$BD$3, Actuals!$H:$BD ) )} -> 0 | BB12: {=_xlfn.XLOOKUP( $B$4&" "&$B12, Actuals!$D:$D, _xlfn.XLOOKUP( BB$7, Actuals!$H$3:$BM$3, Actuals!$H:$BM ) )} -> 0 | BC12: =VLOOKUP($B$4&" "&$B12,Budget!$AG$4:$AL$132,$BB$5+1,FALSE) -> 0 | BD12: =BB12-BC12 -> 0 | BF12: {=_xlfn.XLOOKUP( $B$4&" "&$B12, Actuals!$D:$D, _xlfn.XLOOKUP( BF$7, Actuals!$H$3:$BM$3, Actuals!$H:$BM ) )} -> 0 | BG12: =VLOOKUP($B$4&" "&$B12,Budget!$AG$4:$AL$132,BF$5+1,FALSE) -> 0 | BH12: =BF12-BG12 -> 0 | BJ12: {=_xlfn.XLOOKUP( $B$4&" "&$B12, Actuals!$D:$D, _xlfn.XLOOKUP( BJ$7, Actuals!$H$3:$BM$3, Actuals!$H:$BM ) )} -> 0 | BK12: =VLOOKUP($B$4&" "&$B12,Budget!$AG$4:$AL$132,BJ$5+1,FALSE) -> 0 | BL12: =BJ12-BK12 -> 0 | BN12: {=_xlfn.XLOOKUP( $B$4&" "&$B12, Actuals!$D:$D, _xlfn.XLOOKUP( BN$7, Actuals!$H$3:$BM$3, Actuals!$H:$BM ) )} -> 0 | BO12: =VLOOKUP($B$4&" "&$B12,Budget!$AG$4:$AL$132,BN$5+1,FALSE) -> 0 | BR12: {=_xlfn.XLOOKUP( $B$4&" "&$B12, Actuals!$D:$D, _xlfn.XLOOKUP( BR$6, Actuals!$H$3:$BM$3, Actuals!$H:$BM ) )} -> 0 | BS12: =VLOOKUP($B$4&" "&$B12,Budget!$AG$4:$AL$132,6,FALSE) -> 0 | BT12: =BR12-BS12 -> 0 | BV12: {=_xlfn.XLOOKUP( $B$4&" "&$B12, Actuals!$D:$D, _xlfn.XLOOKUP( BV$6, Actuals!$H$3:$BM$3, Actuals!$H:$BM ) )} -> 64
B13: Marketing Generated Opps. | C13: In-period | D13: =VLOOKUP($B$4&" "&$B13,Actuals!$D$4:$AG$131,3,FALSE) -> # | E13: {=_xlfn.XLOOKUP( $B$4&" "&$B13, Actuals!$D:$D, _xlfn.XLOOKUP( E$6, Actuals!$H$3:$BD$3, Actuals!$H:$BD ) )} -> 5 | F13: {=_xlfn.XLOOKUP( $B$4&" "&$B13, Actuals!$D:$D, _xlfn.XLOOKUP( F$6, Actuals!$H$3:$BD$3, Actuals!$H:$BD ) )} -> 1 | G13: {=_xlfn.XLOOKUP( $B$4&" "&$B13, Actuals!$D:$D, _xlfn.XLOOKUP( G$6, Actuals!$H$3:$BD$3, Actuals!$H:$BD ) )} -> 2 | H13: {=_xlfn.XLOOKUP( $B$4&" "&$B13, Actuals!$D:$D, _xlfn.XLOOKUP( H$6, Actuals!$H$3:$BD$3, Actuals!$H:$BD ) )} -> 0 | I13: {=_xlfn.XLOOKUP( $B$4&" "&$B13, Actuals!$D:$D, _xlfn.XLOOKUP( I$6, Actuals!$H$3:$BD$3, Actuals!$H:$BD ) )} -> 3 | J13: {=_xlfn.XLOOKUP( $B$4&" "&$B13, Actuals!$D:$D, _xlfn.XLOOKUP( J$6, Actuals!$H$3:$BD$3, Actuals!$H:$BD ) )} -> 7 | K13: {=_xlfn.XLOOKUP( $B$4&" "&$B13, Actuals!$D:$D, _xlfn.XLOOKUP( K$6, Actuals!$H$3:$BD$3, Actuals!$H:$BD ) )} -> 4 | L13: {=_xlfn.XLOOKUP( $B$4&" "&$B13, Actuals!$D:$D, _xlfn.XLOOKUP( L$6, Actuals!$H$3:$BD$3, Actuals!$H:$BD ) )} -> 2 | ... AZ13: {=_xlfn.XLOOKUP( $B$4&" "&$B13, Actuals!$D:$D, _xlfn.XLOOKUP( AZ$6, Actuals!$H$3:$BD$3, Actuals!$H:$BD ) )} -> 0 | BB13: {=_xlfn.XLOOKUP( $B$4&" "&$B13, Actuals!$D:$D, _xlfn.XLOOKUP( BB$7, Actuals!$H$3:$BM$3, Actuals!$H:$BM ) )} -> 0 | BC13: =VLOOKUP($B$4&" "&$B13,Budget!$AG$4:$AL$132,$BB$5+1,FALSE) -> 60 | BD13: =BB13-BC13 -> -60 | BF13: {=_xlfn.XLOOKUP( $B$4&" "&$B13, Actuals!$D:$D, _xlfn.XLOOKUP( BF$7, Actuals!$H$3:$BM$3, Actuals!$H:$BM ) )} -> 0 | BG13: =VLOOKUP($B$4&" "&$B13,Budget!$AG$4:$AL$132,BF$5+1,FALSE) -> 60 | BH13: =BF13-BG13 -> -60 | BJ13: {=_xlfn.XLOOKUP( $B$4&" "&$B13, Actuals!$D:$D, _xlfn.XLOOKUP( BJ$7, Actuals!$H$3:$BM$3, Actuals!$H:$BM ) )} -> 0 | BK13: =VLOOKUP($B$4&" "&$B13,Budget!$AG$4:$AL$132,BJ$5+1,FALSE) -> 60 | BL13: =BJ13-BK13 -> -60 | BN13: {=_xlfn.XLOOKUP( $B$4&" "&$B13, Actuals!$D:$D, _xlfn.XLOOKUP( BN$7, Actuals!$H$3:$BM$3, Actuals!$H:$BM ) )} -> 0 | BO13: =VLOOKUP($B$4&" "&$B13,Budget!$AG$4:$AL$132,BN$5+1,FALSE) -> 60 | BR13: {=_xlfn.XLOOKUP( $B$4&" "&$B13, Actuals!$D:$D, _xlfn.XLOOKUP( BR$6, Actuals!$H$3:$BM$3, Actuals!$H:$BM ) )} -> 0 | BS13: =VLOOKUP($B$4&" "&$B13,Budget!$AG$4:$AL$132,6,FALSE) -> 240 | BT13: =BR13-BS13 -> -240 | BV13: {=_xlfn.XLOOKUP( $B$4&" "&$B13, Actuals!$D:$D, _xlfn.XLOOKUP( BV$6, Actuals!$H$3:$BM$3, Actuals!$H:$BM ) )} -> 48
B14: Referral Generated Opps. | C14: In-period | D14: =VLOOKUP($B$4&" "&$B14,Actuals!$D$4:$AG$131,3,FALSE) -> # | E14: {=_xlfn.XLOOKUP( $B$4&" "&$B14, Actuals!$D:$D, _xlfn.XLOOKUP( E$6, Actuals!$H$3:$BD$3, Actuals!$H:$BD ) )} -> 2 | F14: {=_xlfn.XLOOKUP( $B$4&" "&$B14, Actuals!$D:$D, _xlfn.XLOOKUP( F$6, Actuals!$H$3:$BD$3, Actuals!$H:$BD ) )} -> 0 | G14: {=_xlfn.XLOOKUP( $B$4&" "&$B14, Actuals!$D:$D, _xlfn.XLOOKUP( G$6, Actuals!$H$3:$BD$3, Actuals!$H:$BD ) )} -> 2 | H14: {=_xlfn.XLOOKUP( $B$4&" "&$B14, Actuals!$D:$D, _xlfn.XLOOKUP( H$6, Actuals!$H$3:$BD$3, Actuals!$H:$BD ) )} -> 0 | I14: {=_xlfn.XLOOKUP( $B$4&" "&$B14, Actuals!$D:$D, _xlfn.XLOOKUP( I$6, Actuals!$H$3:$BD$3, Actuals!$H:$BD ) )} -> 3 | J14: {=_xlfn.XLOOKUP( $B$4&" "&$B14, Actuals!$D:$D, _xlfn.XLOOKUP( J$6, Actuals!$H$3:$BD$3, Actuals!$H:$BD ) )} -> 1 | K14: {=_xlfn.XLOOKUP( $B$4&" "&$B14, Actuals!$D:$D, _xlfn.XLOOKUP( K$6, Actuals!$H$3:$BD$3, Actuals!$H:$BD ) )} -> 3 | L14: {=_xlfn.XLOOKUP( $B$4&" "&$B14, Actuals!$D:$D, _xlfn.XLOOKUP( L$6, Actuals!$H$3:$BD$3, Actuals!$H:$BD ) )} -> 2 | ... AZ14: {=_xlfn.XLOOKUP( $B$4&" "&$B14, Actuals!$D:$D, _xlfn.XLOOKUP( AZ$6, Actuals!$H$3:$BD$3, Actuals!$H:$BD ) )} -> 0 | BB14: {=_xlfn.XLOOKUP( $B$4&" "&$B14, Actuals!$D:$D, _xlfn.XLOOKUP( BB$7, Actuals!$H$3:$BM$3, Actuals!$H:$BM ) )} -> 0 | BC14: =VLOOKUP($B$4&" "&$B14,Budget!$AG$4:$AL$132,$BB$5+1,FALSE) -> 0 | BD14: =BB14-BC14 -> 0 | BF14: {=_xlfn.XLOOKUP( $B$4&" "&$B14, Actuals!$D:$D, _xlfn.XLOOKUP( BF$7, Actuals!$H$3:$BM$3, Actuals!$H:$BM ) )} -> 0 | BG14: =VLOOKUP($B$4&" "&$B14,Budget!$AG$4:$AL$132,BF$5+1,FALSE) -> 0 | BH14: =BF14-BG14 -> 0 | BJ14: {=_xlfn.XLOOKUP( $B$4&" "&$B14, Actuals!$D:$D, _xlfn.XLOOKUP( BJ$7, Actuals!$H$3:$BM$3, Actuals!$H:$BM ) )} -> 0 | BK14: =VLOOKUP($B$4&" "&$B14,Budget!$AG$4:$AL$132,BJ$5+1,FALSE) -> 0 | BL14: =BJ14-BK14 -> 0 | BN14: {=_xlfn.XLOOKUP( $B$4&" "&$B14, Actuals!$D:$D, _xlfn.XLOOKUP( BN$7, Actuals!$H$3:$BM$3, Actuals!$H:$BM ) )} -> 0 | BO14: =VLOOKUP($B$4&" "&$B14,Budget!$AG$4:$AL$132,BN$5+1,FALSE) -> 0 | BR14: {=_xlfn.XLOOKUP( $B$4&" "&$B14, Actuals!$D:$D, _xlfn.XLOOKUP( BR$6, Actuals!$H$3:$BM$3, Actuals!$H:$BM ) )} -> 0 | BS14: =VLOOKUP($B$4&" "&$B14,Budget!$AG$4:$AL$132,6,FALSE) -> 0 | BT14: =BR14-BS14 -> 0 | BV14: {=_xlfn.XLOOKUP( $B$4&" "&$B14, Actuals!$D:$D, _xlfn.XLOOKUP( BV$6, Actuals!$H$3:$BM$3, Actuals!$H:$BM ) )} -> 61
B15: New Pipeline Opportunities | C15: In-period | D15: =VLOOKUP($B$4&" "&$B15,Actuals!$D$4:$AG$131,3,FALSE) -> # | E15: {=_xlfn.XLOOKUP( $B$4&" "&$B15, Actuals!$D:$D, _xlfn.XLOOKUP( E$6, Actuals!$H$3:$BD$3, Actuals!$H:$BD ) )} -> 10 | F15: {=_xlfn.XLOOKUP( $B$4&" "&$B15, Actuals!$D:$D, _xlfn.XLOOKUP( F$6, Actuals!$H$3:$BD$3, Actuals!$H:$BD ) )} -> 2 | G15: {=_xlfn.XLOOKUP( $B$4&" "&$B15, Actuals!$D:$D, _xlfn.XLOOKUP( G$6, Actuals!$H$3:$BD$3, Actuals!$H:$BD ) )} -> 6 | H15: {=_xlfn.XLOOKUP( $B$4&" "&$B15, Actuals!$D:$D, _xlfn.XLOOKUP( H$6, Actuals!$H$3:$BD$3, Actuals!$H:$BD ) )} -> 7 | I15: {=_xlfn.XLOOKUP( $B$4&" "&$B15, Actuals!$D:$D, _xlfn.XLOOKUP( I$6, Actuals!$H$3:$BD$3, Actuals!$H:$BD ) )} -> 18 | J15: {=_xlfn.XLOOKUP( $B$4&" "&$B15, Actuals!$D:$D, _xlfn.XLOOKUP( J$6, Actuals!$H$3:$BD$3, Actuals!$H:$BD ) )} -> 11 | K15: {=_xlfn.XLOOKUP( $B$4&" "&$B15, Actuals!$D:$D, _xlfn.XLOOKUP( K$6, Actuals!$H$3:$BD$3, Actuals!$H:$BD ) )} -> 12 | L15: {=_xlfn.XLOOKUP( $B$4&" "&$B15, Actuals!$D:$D, _xlfn.XLOOKUP( L$6, Actuals!$H$3:$BD$3, Actuals!$H:$BD ) )} -> 8 | ... AZ15: {=_xlfn.XLOOKUP( $B$4&" "&$B15, Actuals!$D:$D, _xlfn.XLOOKUP( AZ$6, Actuals!$H$3:$BD$3, Actuals!$H:$BD ) )} -> 0 | BB15: {=_xlfn.XLOOKUP( $B$4&" "&$B15, Actuals!$D:$D, _xlfn.XLOOKUP( BB$7, Actuals!$H$3:$BM$3, Actuals!$H:$BM ) )} -> 0 | BC15: =VLOOKUP($B$4&" "&$B15,Budget!$AG$4:$AL$132,$BB$5+1,FALSE) -> 60 | BD15: =BB15-BC15 -> -60 | BF15: {=_xlfn.XLOOKUP( $B$4&" "&$B15, Actuals!$D:$D, _xlfn.XLOOKUP( BF$7, Actuals!$H$3:$BM$3, Actuals!$H:$BM ) )} -> 0 | BG15: =VLOOKUP($B$4&" "&$B15,Budget!$AG$4:$AL$132,BF$5+1,FALSE) -> 60 | BH15: =BF15-BG15 -> -60 | BJ15: {=_xlfn.XLOOKUP( $B$4&" "&$B15, Actuals!$D:$D, _xlfn.XLOOKUP( BJ$7, Actuals!$H$3:$BM$3, Actuals!$H:$BM ) )} -> 0 | BK15: =VLOOKUP($B$4&" "&$B15,Budget!$AG$4:$AL$132,BJ$5+1,FALSE) -> 60 | BL15: =BJ15-BK15 -> -60 | BN15: {=_xlfn.XLOOKUP( $B$4&" "&$B15, Actuals!$D:$D, _xlfn.XLOOKUP( BN$7, Actuals!$H$3:$BM$3, Actuals!$H:$BM ) )} -> 0 | BO15: =VLOOKUP($B$4&" "&$B15,Budget!$AG$4:$AL$132,BN$5+1,FALSE) -> 60 | BR15: {=_xlfn.XLOOKUP( $B$4&" "&$B15, Actuals!$D:$D, _xlfn.XLOOKUP( BR$6, Actuals!$H$3:$BM$3, Actuals!$H:$BM ) )} -> 0 | BS15: =VLOOKUP($B$4&" "&$B15,Budget!$AG$4:$AL$132,6,FALSE) -> 240 | BT15: =BR15-BS15 -> -240 | BV15: {=_xlfn.XLOOKUP( $B$4&" "&$B15, Actuals!$D:$D, _xlfn.XLOOKUP( BV$6, Actuals!$H$3:$BM$3, Actuals!$H:$BM ) )} -> 173
B16: Won | C16: In-period | D16: =VLOOKUP($B$4&" "&$B16,Actuals!$D$4:$AG$131,3,FALSE) -> # | E16: {=_xlfn.XLOOKUP( $B$4&" "&$B16, Actuals!$D:$D, _xlfn.XLOOKUP( E$6, Actuals!$H$3:$BD$3, Actuals!$H:$BD ) )} -> 1 | F16: {=_xlfn.XLOOKUP( $B$4&" "&$B16, Actuals!$D:$D, _xlfn.XLOOKUP( F$6, Actuals!$H$3:$BD$3, Actuals!$H:$BD ) )} -> 0 | G16: {=_xlfn.XLOOKUP( $B$4&" "&$B16, Actuals!$D:$D, _xlfn.XLOOKUP( G$6, Actuals!$H$3:$BD$3, Actuals!$H:$BD ) )} -> 1 | H16: {=_xlfn.XLOOKUP( $B$4&" "&$B16, Actuals!$D:$D, _xlfn.XLOOKUP( H$6, Actuals!$H$3:$BD$3, Actuals!$H:$BD ) )} -> 0 | I16: {=_xlfn.XLOOKUP( $B$4&" "&$B16, Actuals!$D:$D, _xlfn.XLOOKUP( I$6, Actuals!$H$3:$BD$3, Actuals!$H:$BD ) )} -> 0 | J16: {=_xlfn.XLOOKUP( $B$4&" "&$B16, Actuals!$D:$D, _xlfn.XLOOKUP( J$6, Actuals!$H$3:$BD$3, Actuals!$H:$BD ) )} -> 1 | K16: {=_xlfn.XLOOKUP( $B$4&" "&$B16, Actuals!$D:$D, _xlfn.XLOOKUP( K$6, Actuals!$H$3:$BD$3, Actuals!$H:$BD ) )} -> 0 | L16: {=_xlfn.XLOOKUP( $B$4&" "&$B16, Actuals!$D:$D, _xlfn.XLOOKUP( L$6, Actuals!$H$3:$BD$3, Actuals!$H:$BD ) )} -> 2 | ... AZ16: {=_xlfn.XLOOKUP( $B$4&" "&$B16, Actuals!$D:$D, _xlfn.XLOOKUP( AZ$6, Actuals!$H$3:$BD$3, Actuals!$H:$BD ) )} -> 0 | BB16: {=_xlfn.XLOOKUP( $B$4&" "&$B16, Actuals!$D:$D, _xlfn.XLOOKUP( BB$7, Actuals!$H$3:$BM$3, Actuals!$H:$BM ) )} -> 0 | BC16: =VLOOKUP($B$4&" "&$B16,Budget!$AG$4:$AL$132,$BB$5+1,FALSE) -> 4.2666667 | BD16: =BB16-BC16 -> -4.2666667 | BF16: {=_xlfn.XLOOKUP( $B$4&" "&$B16, Actuals!$D:$D, _xlfn.XLOOKUP( BF$7, Actuals!$H$3:$BM$3, Actuals!$H:$BM ) )} -> 0 | BG16: =VLOOKUP($B$4&" "&$B16,Budget!$AG$4:$AL$132,BF$5+1,FALSE) -> 6 | BH16: =BF16-BG16 -> -6 | BJ16: {=_xlfn.XLOOKUP( $B$4&" "&$B16, Actuals!$D:$D, _xlfn.XLOOKUP( BJ$7, Actuals!$H$3:$BM$3, Actuals!$H:$BM ) )} -> 0 | BK16: =VLOOKUP($B$4&" "&$B16,Budget!$AG$4:$AL$132,BJ$5+1,FALSE) -> 6 | BL16: =BJ16-BK16 -> -6 | BN16: {=_xlfn.XLOOKUP( $B$4&" "&$B16, Actuals!$D:$D, _xlfn.XLOOKUP( BN$7, Actuals!$H$3:$BM$3, Actuals!$H:$BM ) )} -> 0 | BO16: =VLOOKUP($B$4&" "&$B16,Budget!$AG$4:$AL$132,BN$5+1,FALSE) -> 7.7333333 | BR16: {=_xlfn.XLOOKUP( $B$4&" "&$B16, Actuals!$D:$D, _xlfn.XLOOKUP( BR$6, Actuals!$H$3:$BM$3, Actuals!$H:$BM ) )} -> 0 | BS16: =VLOOKUP($B$4&" "&$B16,Budget!$AG$4:$AL$132,6,FALSE) -> 24 | BT16: =BR16-BS16 -> -24 | BV16: {=_xlfn.XLOOKUP( $B$4&" "&$B16, Actuals!$D:$D, _xlfn.XLOOKUP( BV$6, Actuals!$H$3:$BM$3, Actuals!$H:$BM ) )} -> 22
B17: Lost + Nurture | C17: In-period | D17: =VLOOKUP($B$4&" "&$B17,Actuals!$D$4:$AG$131,3,FALSE) -> # | E17: {=_xlfn.XLOOKUP( $B$4&" "&$B17, Actuals!$D:$D, _xlfn.XLOOKUP( E$6, Actuals!$H$3:$BD$3, Actuals!$H:$BD ) )} -> 4 | F17: {=_xlfn.XLOOKUP( $B$4&" "&$B17, Actuals!$D:$D, _xlfn.XLOOKUP( F$6, Actuals!$H$3:$BD$3, Actuals!$H:$BD ) )} -> 8 | G17: {=_xlfn.XLOOKUP( $B$4&" "&$B17, Actuals!$D:$D, _xlfn.XLOOKUP( G$6, Actuals!$H$3:$BD$3, Actuals!$H:$BD ) )} -> 19 | H17: {=_xlfn.XLOOKUP( $B$4&" "&$B17, Actuals!$D:$D, _xlfn.XLOOKUP( H$6, Actuals!$H$3:$BD$3, Actuals!$H:$BD ) )} -> 3 | I17: {=_xlfn.XLOOKUP( $B$4&" "&$B17, Actuals!$D:$D, _xlfn.XLOOKUP( I$6, Actuals!$H$3:$BD$3, Actuals!$H:$BD ) )} -> 3 | J17: {=_xlfn.XLOOKUP( $B$4&" "&$B17, Actuals!$D:$D, _xlfn.XLOOKUP( J$6, Actuals!$H$3:$BD$3, Actuals!$H:$BD ) )} -> 11 | K17: {=_xlfn.XLOOKUP( $B$4&" "&$B17, Actuals!$D:$D, _xlfn.XLOOKUP( K$6, Actuals!$H$3:$BD$3, Actuals!$H:$BD ) )} -> 6 | L17: {=_xlfn.XLOOKUP( $B$4&" "&$B17, Actuals!$D:$D, _xlfn.XLOOKUP( L$6, Actuals!$H$3:$BD$3, Actuals!$H:$BD ) )} -> 11 | ... AZ17: {=_xlfn.XLOOKUP( $B$4&" "&$B17, Actuals!$D:$D, _xlfn.XLOOKUP( AZ$6, Actuals!$H$3:$BD$3, Actuals!$H:$BD ) )} -> 0 | BB17: {=_xlfn.XLOOKUP( $B$4&" "&$B17, Actuals!$D:$D, _xlfn.XLOOKUP( BB$7, Actuals!$H$3:$BM$3, Actuals!$H:$BM ) )} -> 0 | BC17: =VLOOKUP($B$4&" "&$B17,Budget!$AG$4:$AL$132,$BB$5+1,FALSE) -> 0 | BD17: =BB17-BC17 -> 0 | BF17: {=_xlfn.XLOOKUP( $B$4&" "&$B17, Actuals!$D:$D, _xlfn.XLOOKUP( BF$7, Actuals!$H$3:$BM$3, Actuals!$H:$BM ) )} -> 0 | BG17: =VLOOKUP($B$4&" "&$B17,Budget!$AG$4:$AL$132,BF$5+1,FALSE) -> 0 | BH17: =BF17-BG17 -> 0 | BJ17: {=_xlfn.XLOOKUP( $B$4&" "&$B17, Actuals!$D:$D, _xlfn.XLOOKUP( BJ$7, Actuals!$H$3:$BM$3, Actuals!$H:$BM ) )} -> 0 | BK17: =VLOOKUP($B$4&" "&$B17,Budget!$AG$4:$AL$132,BJ$5+1,FALSE) -> 0 | BL17: =BJ17-BK17 -> 0 | BN17: {=_xlfn.XLOOKUP( $B$4&" "&$B17, Actuals!$D:$D, _xlfn.XLOOKUP( BN$7, Actuals!$H$3:$BM$3, Actuals!$H:$BM ) )} -> 0 | BO17: =VLOOKUP($B$4&" "&$B17,Budget!$AG$4:$AL$132,BN$5+1,FALSE) -> 0 | BR17: {=_xlfn.XLOOKUP( $B$4&" "&$B17, Actuals!$D:$D, _xlfn.XLOOKUP( BR$6, Actuals!$H$3:$BM$3, Actuals!$H:$BM ) )} -> 0 | BS17: =VLOOKUP($B$4&" "&$B17,Budget!$AG$4:$AL$132,6,FALSE) -> 0 | BT17: =BR17-BS17 -> 0 | BV17: {=_xlfn.XLOOKUP( $B$4&" "&$B17, Actuals!$D:$D, _xlfn.XLOOKUP( BV$6, Actuals!$H$3:$BM$3, Actuals!$H:$BM ) )} -> 27
B18: Win rate: Total | C18: In-period | D18: =VLOOKUP($B$4&" "&$B18,Actuals!$D$4:$AG$131,3,FALSE) -> # | E18: {=_xlfn.XLOOKUP( $B$4&" "&$B18, Actuals!$D:$D, _xlfn.XLOOKUP( E$6, Actuals!$H$3:$BD$3, Actuals!$H:$BD ) )} -> 0.25 | F18: {=_xlfn.XLOOKUP( $B$4&" "&$B18, Actuals!$D:$D, _xlfn.XLOOKUP( F$6, Actuals!$H$3:$BD$3, Actuals!$H:$BD ) )} -> 0 | G18: {=_xlfn.XLOOKUP( $B$4&" "&$B18, Actuals!$D:$D, _xlfn.XLOOKUP( G$6, Actuals!$H$3:$BD$3, Actuals!$H:$BD ) )} -> 0.052631579 | H18: {=_xlfn.XLOOKUP( $B$4&" "&$B18, Actuals!$D:$D, _xlfn.XLOOKUP( H$6, Actuals!$H$3:$BD$3, Actuals!$H:$BD ) )} -> 0 | I18: {=_xlfn.XLOOKUP( $B$4&" "&$B18, Actuals!$D:$D, _xlfn.XLOOKUP( I$6, Actuals!$H$3:$BD$3, Actuals!$H:$BD ) )} -> 0 | J18: {=_xlfn.XLOOKUP( $B$4&" "&$B18, Actuals!$D:$D, _xlfn.XLOOKUP( J$6, Actuals!$H$3:$BD$3, Actuals!$H:$BD ) )} -> 0.090909091 | K18: {=_xlfn.XLOOKUP( $B$4&" "&$B18, Actuals!$D:$D, _xlfn.XLOOKUP( K$6, Actuals!$H$3:$BD$3, Actuals!$H:$BD ) )} -> 0 | L18: {=_xlfn.XLOOKUP( $B$4&" "&$B18, Actuals!$D:$D, _xlfn.XLOOKUP( L$6, Actuals!$H$3:$BD$3, Actuals!$H:$BD ) )} -> 0.18181818 | ... AZ18: {=_xlfn.XLOOKUP( $B$4&" "&$B18, Actuals!$D:$D, _xlfn.XLOOKUP( AZ$6, Actuals!$H$3:$BD$3, Actuals!$H:$BD ) )} -> #DIV/0! | BB18: {=_xlfn.XLOOKUP( $B$4&" "&$B18, Actuals!$D:$D, _xlfn.XLOOKUP( BB$7, Actuals!$H$3:$BM$3, Actuals!$H:$BM ) )} -> - | BC18: =IFERROR(VLOOKUP($B$4&" "&$B18,Budget!$AG$4:$AL$132,$BB$5+1,FALSE),"n.a.") -> - | BD18: =IFERROR(BB18-BC18,"-") -> - | BF18: {=_xlfn.XLOOKUP( $B$4&" "&$B18, Actuals!$D:$D, _xlfn.XLOOKUP( BF$7, Actuals!$H$3:$BM$3, Actuals!$H:$BM ) )} -> - | BG18: =IFERROR(VLOOKUP($B$4&" "&$B18,Budget!$AG$4:$AL$132,$BF$5+1,FALSE),"n.a.") -> - | BH18: =IFERROR(BF18-BG18,"-") -> - | BJ18: {=_xlfn.XLOOKUP( $B$4&" "&$B18, Actuals!$D:$D, _xlfn.XLOOKUP( BJ$7, Actuals!$H$3:$BM$3, Actuals!$H:$BM ) )} -> - | BK18: =IFERROR(VLOOKUP($B$4&" "&$B18,Budget!$AG$4:$AL$132,$BJ$5+1,FALSE),"n.a.") -> - | BL18: =IFERROR(BJ18-BK18,"-") -> - | BN18: {=_xlfn.XLOOKUP( $B$4&" "&$B18, Actuals!$D:$D, _xlfn.XLOOKUP( BN$7, Actuals!$H$3:$BM$3, Actuals!$H:$BM ) )} -> - | BO18: =IFERROR(VLOOKUP($B$4&" "&$B18,Budget!$AG$4:$AL$132,$BN$5+1,FALSE),"n.a.") -> - | BR18: {=_xlfn.XLOOKUP( $B$4&" "&$B18, Actuals!$D:$D, _xlfn.XLOOKUP( BR$6, Actuals!$H$3:$BM$3, Actuals!$H:$BM ) )} -> #DIV/0! | BS18: =VLOOKUP($B$4&" "&$B18,Budget!$AG$4:$AL$132,6,FALSE) -> 0 | BT18: =BR18-BS18 -> #DIV/0! | BV18: {=_xlfn.XLOOKUP( $B$4&" "&$B18, Actuals!$D:$D, _xlfn.XLOOKUP( BV$6, Actuals!$H$3:$BM$3, Actuals!$H:$BM ) )} -> #DIV/0!
B19: Avg ACV | C19: In-period | D19: =VLOOKUP($B$4&" "&$B19,Actuals!$D$4:$AG$131,3,FALSE) -> # | E19: {=_xlfn.XLOOKUP( $B$4&" "&$B19, Actuals!$D:$D, _xlfn.XLOOKUP( E$6, Actuals!$H$3:$BD$3, Actuals!$H:$BD ) )} -> 49000 | F19: {=_xlfn.XLOOKUP( $B$4&" "&$B19, Actuals!$D:$D, _xlfn.XLOOKUP( F$6, Actuals!$H$3:$BD$3, Actuals!$H:$BD ) )} -> 0 | G19: {=_xlfn.XLOOKUP( $B$4&" "&$B19, Actuals!$D:$D, _xlfn.XLOOKUP( G$6, Actuals!$H$3:$BD$3, Actuals!$H:$BD ) )} -> 67000 | H19: {=_xlfn.XLOOKUP( $B$4&" "&$B19, Actuals!$D:$D, _xlfn.XLOOKUP( H$6, Actuals!$H$3:$BD$3, Actuals!$H:$BD ) )} -> 6250 | I19: {=_xlfn.XLOOKUP( $B$4&" "&$B19, Actuals!$D:$D, _xlfn.XLOOKUP( I$6, Actuals!$H$3:$BD$3, Actuals!$H:$BD ) )} -> 0 | J19: {=_xlfn.XLOOKUP( $B$4&" "&$B19, Actuals!$D:$D, _xlfn.XLOOKUP( J$6, Actuals!$H$3:$BD$3, Actuals!$H:$BD ) )} -> 198625 | K19: {=_xlfn.XLOOKUP( $B$4&" "&$B19, Actuals!$D:$D, _xlfn.XLOOKUP( K$6, Actuals!$H$3:$BD$3, Actuals!$H:$BD ) )} -> 0 | L19: {=_xlfn.XLOOKUP( $B$4&" "&$B19, Actuals!$D:$D, _xlfn.XLOOKUP( L$6, Actuals!$H$3:$BD$3, Actuals!$H:$BD ) )} -> 181300 | ... AZ19: {=_xlfn.XLOOKUP( $B$4&" "&$B19, Actuals!$D:$D, _xlfn.XLOOKUP( AZ$6, Actuals!$H$3:$BD$3, Actuals!$H:$BD ) )} -> 0 | BB19: {=_xlfn.XLOOKUP( $B$4&" "&$B19, Actuals!$D:$D, _xlfn.XLOOKUP( BB$7, Actuals!$H$3:$BM$3, Actuals!$H:$BM ) )} -> - | BC19: =IFERROR(VLOOKUP($B$4&" "&$B19,Budget!$AG$4:$AL$132,$BB$5+1,FALSE),"n.a.") -> 75000 | BD19: =IFERROR(BB19-BC19,"-") -> - | BF19: {=_xlfn.XLOOKUP( $B$4&" "&$B19, Actuals!$D:$D, _xlfn.XLOOKUP( BF$7, Actuals!$H$3:$BM$3, Actuals!$H:$BM ) )} -> - | BG19: =IFERROR(VLOOKUP($B$4&" "&$B19,Budget!$AG$4:$AL$132,$BF$5+1,FALSE),"n.a.") -> 75000 | BH19: =IFERROR(BF19-BG19,"-") -> - | BJ19: {=_xlfn.XLOOKUP( $B$4&" "&$B19, Actuals!$D:$D, _xlfn.XLOOKUP( BJ$7, Actuals!$H$3:$BM$3, Actuals!$H:$BM ) )} -> - | BK19: =IFERROR(VLOOKUP($B$4&" "&$B19,Budget!$AG$4:$AL$132,$BJ$5+1,FALSE),"n.a.") -> 75000 | BL19: =IFERROR(BJ19-BK19,"-") -> - | BN19: {=_xlfn.XLOOKUP( $B$4&" "&$B19, Actuals!$D:$D, _xlfn.XLOOKUP( BN$7, Actuals!$H$3:$BM$3, Actuals!$H:$BM ) )} -> - | BO19: =IFERROR(VLOOKUP($B$4&" "&$B19,Budget!$AG$4:$AL$132,$BN$5+1,FALSE),"n.a.") -> 75000 | BR19: {=_xlfn.XLOOKUP( $B$4&" "&$B19, Actuals!$D:$D, _xlfn.XLOOKUP( BR$6, Actuals!$H$3:$BM$3, Actuals!$H:$BM ) )} -> - | BS19: =VLOOKUP($B$4&" "&$B19,Budget!$AG$4:$AL$132,6,FALSE) -> 75000 | BT19: =BR19-BS19 -> #VALUE! | BV19: {=_xlfn.XLOOKUP( $B$4&" "&$B19, Actuals!$D:$D, _xlfn.XLOOKUP( BV$6, Actuals!$H$3:$BM$3, Actuals!$H:$BM ) )}
B20: Avg Age of Opps Won in Period | C20: In-period | D20: =VLOOKUP($B$4&" "&$B20,Actuals!$D$4:$AG$131,3,FALSE) -> # | E20: {=_xlfn.XLOOKUP( $B$4&" "&$B20, Actuals!$D:$D, _xlfn.XLOOKUP( E$6, Actuals!$H$3:$BD$3, Actuals!$H:$BD ) )} -> 12.857143 | F20: {=_xlfn.XLOOKUP( $B$4&" "&$B20, Actuals!$D:$D, _xlfn.XLOOKUP( F$6, Actuals!$H$3:$BD$3, Actuals!$H:$BD ) )} -> 0 | G20: {=_xlfn.XLOOKUP( $B$4&" "&$B20, Actuals!$D:$D, _xlfn.XLOOKUP( G$6, Actuals!$H$3:$BD$3, Actuals!$H:$BD ) )} -> 21.571429 | H20: {=_xlfn.XLOOKUP( $B$4&" "&$B20, Actuals!$D:$D, _xlfn.XLOOKUP( H$6, Actuals!$H$3:$BD$3, Actuals!$H:$BD ) )} -> 0 | I20: {=_xlfn.XLOOKUP( $B$4&" "&$B20, Actuals!$D:$D, _xlfn.XLOOKUP( I$6, Actuals!$H$3:$BD$3, Actuals!$H:$BD ) )} -> 0 | J20: {=_xlfn.XLOOKUP( $B$4&" "&$B20, Actuals!$D:$D, _xlfn.XLOOKUP( J$6, Actuals!$H$3:$BD$3, Actuals!$H:$BD ) )} -> 34.428571 | K20: {=_xlfn.XLOOKUP( $B$4&" "&$B20, Actuals!$D:$D, _xlfn.XLOOKUP( K$6, Actuals!$H$3:$BD$3, Actuals!$H:$BD ) )} -> 0 | L20: {=_xlfn.XLOOKUP( $B$4&" "&$B20, Actuals!$D:$D, _xlfn.XLOOKUP( L$6, Actuals!$H$3:$BD$3, Actuals!$H:$BD ) )} -> 16.142857 | ... AZ20: {=_xlfn.XLOOKUP( $B$4&" "&$B20, Actuals!$D:$D, _xlfn.XLOOKUP( AZ$6, Actuals!$H$3:$BD$3, Actuals!$H:$BD ) )} -> 0 | BB20: {=_xlfn.XLOOKUP( $B$4&" "&$B20, Actuals!$D:$D, _xlfn.XLOOKUP( BB$7, Actuals!$H$3:$BM$3, Actuals!$H:$BM ) )} -> - | BC20: =IFERROR(VLOOKUP($B$4&" "&$B20,Budget!$AG$4:$AL$132,$BB$5+1,FALSE),"n.a.") -> - | BD20: =IFERROR(BB20-BC20,"-") -> - | BF20: {=_xlfn.XLOOKUP( $B$4&" "&$B20, Actuals!$D:$D, _xlfn.XLOOKUP( BF$7, Actuals!$H$3:$BM$3, Actuals!$H:$BM ) )} -> - | BG20: =IFERROR(VLOOKUP($B$4&" "&$B20,Budget!$AG$4:$AL$132,$BF$5+1,FALSE),"n.a.") -> - | BH20: =IFERROR(BF20-BG20,"-") -> - | BJ20: {=_xlfn.XLOOKUP( $B$4&" "&$B20, Actuals!$D:$D, _xlfn.XLOOKUP( BJ$7, Actuals!$H$3:$BM$3, Actuals!$H:$BM ) )} -> - | BK20: =IFERROR(VLOOKUP($B$4&" "&$B20,Budget!$AG$4:$AL$132,$BJ$5+1,FALSE),"n.a.") -> - | BL20: =IFERROR(BJ20-BK20,"-") -> - | BN20: {=_xlfn.XLOOKUP( $B$4&" "&$B20, Actuals!$D:$D, _xlfn.XLOOKUP( BN$7, Actuals!$H$3:$BM$3, Actuals!$H:$BM ) )} -> - | BO20: =IFERROR(VLOOKUP($B$4&" "&$B20,Budget!$AG$4:$AL$132,$BN$5+1,FALSE),"n.a.") -> - | BR20: {=_xlfn.XLOOKUP( $B$4&" "&$B20, Actuals!$D:$D, _xlfn.XLOOKUP( BR$6, Actuals!$H$3:$BM$3, Actuals!$H:$BM ) )} -> 0 | BS20: =VLOOKUP($B$4&" "&$B20,Budget!$AG$4:$AL$132,6,FALSE) -> 0 | BT20: =BR20-BS20 -> 0 | BV20: {=_xlfn.XLOOKUP( $B$4&" "&$B20, Actuals!$D:$D, _xlfn.XLOOKUP( BV$6, Actuals!$H$3:$BM$3, Actuals!$H:$BM ) )} -> 89.5
B22: Pipeline Value (EoP) by Stage
B23: EoP Value - Early Stage | C23: EoP | D23: =VLOOKUP($B$4&" "&$B23,Actuals!$D$4:$AG$131,3,FALSE) -> # | E23: {=_xlfn.XLOOKUP( $B$4&" "&$B23, Actuals!$D:$D, _xlfn.XLOOKUP( E$6, Actuals!$H$3:$BD$3, Actuals!$H:$BD ) )} -> 2375783 | F23: {=_xlfn.XLOOKUP( $B$4&" "&$B23, Actuals!$D:$D, _xlfn.XLOOKUP( F$6, Actuals!$H$3:$BD$3, Actuals!$H:$BD ) )} -> 1779783 | G23: {=_xlfn.XLOOKUP( $B$4&" "&$B23, Actuals!$D:$D, _xlfn.XLOOKUP( G$6, Actuals!$H$3:$BD$3, Actuals!$H:$BD ) )} -> 1400000 | H23: {=_xlfn.XLOOKUP( $B$4&" "&$B23, Actuals!$D:$D, _xlfn.XLOOKUP( H$6, Actuals!$H$3:$BD$3, Actuals!$H:$BD ) )} -> 1711000 | I23: {=_xlfn.XLOOKUP( $B$4&" "&$B23, Actuals!$D:$D, _xlfn.XLOOKUP( I$6, Actuals!$H$3:$BD$3, Actuals!$H:$BD ) )} -> 1984000 | J23: {=_xlfn.XLOOKUP( $B$4&" "&$B23, Actuals!$D:$D, _xlfn.XLOOKUP( J$6, Actuals!$H$3:$BD$3, Actuals!$H:$BD ) )} -> 1760000 | K23: {=_xlfn.XLOOKUP( $B$4&" "&$B23, Actuals!$D:$D, _xlfn.XLOOKUP( K$6, Actuals!$H$3:$BD$3, Actuals!$H:$BD ) )} -> 2232000 | L23: {=_xlfn.XLOOKUP( $B$4&" "&$B23, Actuals!$D:$D, _xlfn.XLOOKUP( L$6, Actuals!$H$3:$BD$3, Actuals!$H:$BD ) )} -> 2250000 | ... AZ23: {=_xlfn.XLOOKUP( $B$4&" "&$B23, Actuals!$D:$D, _xlfn.XLOOKUP( AZ$6, Actuals!$H$3:$BD$3, Actuals!$H:$BD ) )} -> 0 | BB23: {=_xlfn.XLOOKUP( $B$4&" "&$B23, Actuals!$D:$D, _xlfn.XLOOKUP( BB$7, Actuals!$H$3:$BM$3, Actuals!$H:$BM ) )} -> 0 | BC23: =VLOOKUP($B$4&" "&$B23,Budget!$AG$4:$AL$132,$BB$5+1,FALSE) -> 0 | BD23: =BB23-BC23 -> 0 | BF23: {=_xlfn.XLOOKUP( $B$4&" "&$B23, Actuals!$D:$D, _xlfn.XLOOKUP( BF$7, Actuals!$H$3:$BM$3, Actuals!$H:$BM ) )} -> 0 | BG23: =VLOOKUP($B$4&" "&$B23,Budget!$AG$4:$AL$132,BF$5+1,FALSE) -> 0 | BH23: =BF23-BG23 -> 0 | BJ23: {=_xlfn.XLOOKUP( $B$4&" "&$B23, Actuals!$D:$D, _xlfn.XLOOKUP( BJ$7, Actuals!$H$3:$BM$3, Actuals!$H:$BM ) )} -> 0 | BK23: =VLOOKUP($B$4&" "&$B23,Budget!$AG$4:$AL$132,BJ$5+1,FALSE) -> 0 | BL23: =BJ23-BK23 -> 0 | BN23: {=_xlfn.XLOOKUP( $B$4&" "&$B23, Actuals!$D:$D, _xlfn.XLOOKUP( BN$7, Actuals!$H$3:$BM$3, Actuals!$H:$BM ) )} -> 0 | BO23: =VLOOKUP($B$4&" "&$B23,Budget!$AG$4:$AL$132,BN$5+1,FALSE) -> 0 | BR23: {=_xlfn.XLOOKUP( $B$4&" "&$B23, Actuals!$D:$D, _xlfn.XLOOKUP( BR$6, Actuals!$H$3:$BM$3, Actuals!$H:$BM ) )} -> 0 | BS23: =VLOOKUP($B$4&" "&$B23,Budget!$AG$4:$AL$132,6,FALSE) -> 0 | BT23: =BR23-BS23 -> 0 | BV23: {=_xlfn.XLOOKUP( $B$4&" "&$B23, Actuals!$D:$D, _xlfn.XLOOKUP( BV$6, Actuals!$H$3:$BM$3, Actuals!$H:$BM ) )} -> 0
B24: EoP Value - Intermediate Stage | C24: EoP | D24: =VLOOKUP($B$4&" "&$B24,Actuals!$D$4:$AG$131,3,FALSE) -> # | E24: {=_xlfn.XLOOKUP( $B$4&" "&$B24, Actuals!$D:$D, _xlfn.XLOOKUP( E$6, Actuals!$H$3:$BD$3, Actuals!$H:$BD ) )} -> 1334000 | F24: {=_xlfn.XLOOKUP( $B$4&" "&$B24, Actuals!$D:$D, _xlfn.XLOOKUP( F$6, Actuals!$H$3:$BD$3, Actuals!$H:$BD ) )} -> 1114000 | G24: {=_xlfn.XLOOKUP( $B$4&" "&$B24, Actuals!$D:$D, _xlfn.XLOOKUP( G$6, Actuals!$H$3:$BD$3, Actuals!$H:$BD ) )} -> 644000 | H24: {=_xlfn.XLOOKUP( $B$4&" "&$B24, Actuals!$D:$D, _xlfn.XLOOKUP( H$6, Actuals!$H$3:$BD$3, Actuals!$H:$BD ) )} -> 616000 | I24: {=_xlfn.XLOOKUP( $B$4&" "&$B24, Actuals!$D:$D, _xlfn.XLOOKUP( I$6, Actuals!$H$3:$BD$3, Actuals!$H:$BD ) )} -> 766000 | J24: {=_xlfn.XLOOKUP( $B$4&" "&$B24, Actuals!$D:$D, _xlfn.XLOOKUP( J$6, Actuals!$H$3:$BD$3, Actuals!$H:$BD ) )} -> 1049000 | K24: {=_xlfn.XLOOKUP( $B$4&" "&$B24, Actuals!$D:$D, _xlfn.XLOOKUP( K$6, Actuals!$H$3:$BD$3, Actuals!$H:$BD ) )} -> 1084600 | L24: {=_xlfn.XLOOKUP( $B$4&" "&$B24, Actuals!$D:$D, _xlfn.XLOOKUP( L$6, Actuals!$H$3:$BD$3, Actuals!$H:$BD ) )} -> 523000 | ... AZ24: {=_xlfn.XLOOKUP( $B$4&" "&$B24, Actuals!$D:$D, _xlfn.XLOOKUP( AZ$6, Actuals!$H$3:$BD$3, Actuals!$H:$BD ) )} -> 0 | BB24: {=_xlfn.XLOOKUP( $B$4&" "&$B24, Actuals!$D:$D, _xlfn.XLOOKUP( BB$7, Actuals!$H$3:$BM$3, Actuals!$H:$BM ) )} -> 0 | BC24: =VLOOKUP($B$4&" "&$B24,Budget!$AG$4:$AL$132,$BB$5+1,FALSE) -> 0 | BD24: =BB24-BC24 -> 0 | BF24: {=_xlfn.XLOOKUP( $B$4&" "&$B24, Actuals!$D:$D, _xlfn.XLOOKUP( BF$7, Actuals!$H$3:$BM$3, Actuals!$H:$BM ) )} -> 0 | BG24: =VLOOKUP($B$4&" "&$B24,Budget!$AG$4:$AL$132,BF$5+1,FALSE) -> 0 | BH24: =BF24-BG24 -> 0 | BJ24: {=_xlfn.XLOOKUP( $B$4&" "&$B24, Actuals!$D:$D, _xlfn.XLOOKUP( BJ$7, Actuals!$H$3:$BM$3, Actuals!$H:$BM ) )} -> 0 | BK24: =VLOOKUP($B$4&" "&$B24,Budget!$AG$4:$AL$132,BJ$5+1,FALSE) -> 0 | BL24: =BJ24-BK24 -> 0 | BN24: {=_xlfn.XLOOKUP( $B$4&" "&$B24, Actuals!$D:$D, _xlfn.XLOOKUP( BN$7, Actuals!$H$3:$BM$3, Actuals!$H:$BM ) )} -> 0 | BO24: =VLOOKUP($B$4&" "&$B24,Budget!$AG$4:$AL$132,BN$5+1,FALSE) -> 0 | BR24: {=_xlfn.XLOOKUP( $B$4&" "&$B24, Actuals!$D:$D, _xlfn.XLOOKUP( BR$6, Actuals!$H$3:$BM$3, Actuals!$H:$BM ) )} -> 0 | BS24: =VLOOKUP($B$4&" "&$B24,Budget!$AG$4:$AL$132,6,FALSE) -> 0 | BT24: =BR24-BS24 -> 0 | BV24: {=_xlfn.XLOOKUP( $B$4&" "&$B24, Actuals!$D:$D, _xlfn.XLOOKUP( BV$6, Actuals!$H$3:$BM$3, Actuals!$H:$BM ) )} -> 0
B25: EoP Value - Advanced Stage | C25: EoP | D25: =VLOOKUP($B$4&" "&$B25,Actuals!$D$4:$AG$131,3,FALSE) -> # | E25: {=_xlfn.XLOOKUP( $B$4&" "&$B25, Actuals!$D:$D, _xlfn.XLOOKUP( E$6, Actuals!$H$3:$BD$3, Actuals!$H:$BD ) )} -> 314000 | F25: {=_xlfn.XLOOKUP( $B$4&" "&$B25, Actuals!$D:$D, _xlfn.XLOOKUP( F$6, Actuals!$H$3:$BD$3, Actuals!$H:$BD ) )} -> 396000 | G25: {=_xlfn.XLOOKUP( $B$4&" "&$B25, Actuals!$D:$D, _xlfn.XLOOKUP( G$6, Actuals!$H$3:$BD$3, Actuals!$H:$BD ) )} -> 396000 | H25: {=_xlfn.XLOOKUP( $B$4&" "&$B25, Actuals!$D:$D, _xlfn.XLOOKUP( H$6, Actuals!$H$3:$BD$3, Actuals!$H:$BD ) )} -> 182000 | I25: {=_xlfn.XLOOKUP( $B$4&" "&$B25, Actuals!$D:$D, _xlfn.XLOOKUP( I$6, Actuals!$H$3:$BD$3, Actuals!$H:$BD ) )} -> 198625 | J25: {=_xlfn.XLOOKUP( $B$4&" "&$B25, Actuals!$D:$D, _xlfn.XLOOKUP( J$6, Actuals!$H$3:$BD$3, Actuals!$H:$BD ) )} -> 0 | K25: {=_xlfn.XLOOKUP( $B$4&" "&$B25, Actuals!$D:$D, _xlfn.XLOOKUP( K$6, Actuals!$H$3:$BD$3, Actuals!$H:$BD ) )} -> 0 | L25: {=_xlfn.XLOOKUP( $B$4&" "&$B25, Actuals!$D:$D, _xlfn.XLOOKUP( L$6, Actuals!$H$3:$BD$3, Actuals!$H:$BD ) )} -> 148000 | ... AZ25: {=_xlfn.XLOOKUP( $B$4&" "&$B25, Actuals!$D:$D, _xlfn.XLOOKUP( AZ$6, Actuals!$H$3:$BD$3, Actuals!$H:$BD ) )} -> 0 | BB25: {=_xlfn.XLOOKUP( $B$4&" "&$B25, Actuals!$D:$D, _xlfn.XLOOKUP( BB$7, Actuals!$H$3:$BM$3, Actuals!$H:$BM ) )} -> 0 | BC25: =VLOOKUP($B$4&" "&$B25,Budget!$AG$4:$AL$132,$BB$5+1,FALSE) -> 0 | BD25: =BB25-BC25 -> 0 | BF25: {=_xlfn.XLOOKUP( $B$4&" "&$B25, Actuals!$D:$D, _xlfn.XLOOKUP( BF$7, Actuals!$H$3:$BM$3, Actuals!$H:$BM ) )} -> 0 | BG25: =VLOOKUP($B$4&" "&$B25,Budget!$AG$4:$AL$132,BF$5+1,FALSE) -> 0 | BH25: =BF25-BG25 -> 0 | BJ25: {=_xlfn.XLOOKUP( $B$4&" "&$B25, Actuals!$D:$D, _xlfn.XLOOKUP( BJ$7, Actuals!$H$3:$BM$3, Actuals!$H:$BM ) )} -> 0 | BK25: =VLOOKUP($B$4&" "&$B25,Budget!$AG$4:$AL$132,BJ$5+1,FALSE) -> 0 | BL25: =BJ25-BK25 -> 0 | BN25: {=_xlfn.XLOOKUP( $B$4&" "&$B25, Actuals!$D:$D, _xlfn.XLOOKUP( BN$7, Actuals!$H$3:$BM$3, Actuals!$H:$BM ) )} -> 0 | BO25: =VLOOKUP($B$4&" "&$B25,Budget!$AG$4:$AL$132,BN$5+1,FALSE) -> 0 | BR25: {=_xlfn.XLOOKUP( $B$4&" "&$B25, Actuals!$D:$D, _xlfn.XLOOKUP( BR$6, Actuals!$H$3:$BM$3, Actuals!$H:$BM ) )} -> 0 | BS25: =VLOOKUP($B$4&" "&$B25,Budget!$AG$4:$AL$132,6,FALSE) -> 0 | BT25: =BR25-BS25 -> 0 | BV25: {=_xlfn.XLOOKUP( $B$4&" "&$B25, Actuals!$D:$D, _xlfn.XLOOKUP( BV$6, Actuals!$H$3:$BM$3, Actuals!$H:$BM ) )} -> 0
B26: EoP Value - Total | C26: EoP | D26: =VLOOKUP($B$4&" "&$B26,Actuals!$D$4:$AG$131,3,FALSE) -> # | E26: {=_xlfn.XLOOKUP( $B$4&" "&$B26, Actuals!$D:$D, _xlfn.XLOOKUP( E$6, Actuals!$H$3:$BD$3, Actuals!$H:$BD ) )} -> 4023783 | F26: {=_xlfn.XLOOKUP( $B$4&" "&$B26, Actuals!$D:$D, _xlfn.XLOOKUP( F$6, Actuals!$H$3:$BD$3, Actuals!$H:$BD ) )} -> 3289783 | G26: {=_xlfn.XLOOKUP( $B$4&" "&$B26, Actuals!$D:$D, _xlfn.XLOOKUP( G$6, Actuals!$H$3:$BD$3, Actuals!$H:$BD ) )} -> 2440000 | H26: {=_xlfn.XLOOKUP( $B$4&" "&$B26, Actuals!$D:$D, _xlfn.XLOOKUP( H$6, Actuals!$H$3:$BD$3, Actuals!$H:$BD ) )} -> 2509000 | I26: {=_xlfn.XLOOKUP( $B$4&" "&$B26, Actuals!$D:$D, _xlfn.XLOOKUP( I$6, Actuals!$H$3:$BD$3, Actuals!$H:$BD ) )} -> 2948625 | J26: {=_xlfn.XLOOKUP( $B$4&" "&$B26, Actuals!$D:$D, _xlfn.XLOOKUP( J$6, Actuals!$H$3:$BD$3, Actuals!$H:$BD ) )} -> 2809000 | K26: {=_xlfn.XLOOKUP( $B$4&" "&$B26, Actuals!$D:$D, _xlfn.XLOOKUP( K$6, Actuals!$H$3:$BD$3, Actuals!$H:$BD ) )} -> 3316600 | L26: {=_xlfn.XLOOKUP( $B$4&" "&$B26, Actuals!$D:$D, _xlfn.XLOOKUP( L$6, Actuals!$H$3:$BD$3, Actuals!$H:$BD ) )} -> 2921000 | ... AZ26: {=_xlfn.XLOOKUP( $B$4&" "&$B26, Actuals!$D:$D, _xlfn.XLOOKUP( AZ$6, Actuals!$H$3:$BD$3, Actuals!$H:$BD ) )} -> 0 | BB26: {=_xlfn.XLOOKUP( $B$4&" "&$B26, Actuals!$D:$D, _xlfn.XLOOKUP( BB$7, Actuals!$H$3:$BM$3, Actuals!$H:$BM ) )} -> 0 | BC26: =VLOOKUP($B$4&" "&$B26,Budget!$AG$4:$AL$132,$BB$5+1,FALSE) -> 0 | BD26: =BB26-BC26 -> 0 | BF26: {=_xlfn.XLOOKUP( $B$4&" "&$B26, Actuals!$D:$D, _xlfn.XLOOKUP( BF$7, Actuals!$H$3:$BM$3, Actuals!$H:$BM ) )} -> 0 | BG26: =VLOOKUP($B$4&" "&$B26,Budget!$AG$4:$AL$132,BF$5+1,FALSE) -> 0 | BH26: =BF26-BG26 -> 0 | BJ26: {=_xlfn.XLOOKUP( $B$4&" "&$B26, Actuals!$D:$D, _xlfn.XLOOKUP( BJ$7, Actuals!$H$3:$BM$3, Actuals!$H:$BM ) )} -> 0 | BK26: =VLOOKUP($B$4&" "&$B26,Budget!$AG$4:$AL$132,BJ$5+1,FALSE) -> 0 | BL26: =BJ26-BK26 -> 0 | BN26: {=_xlfn.XLOOKUP( $B$4&" "&$B26, Actuals!$D:$D, _xlfn.XLOOKUP( BN$7, Actuals!$H$3:$BM$3, Actuals!$H:$BM ) )} -> 0 | BO26: =VLOOKUP($B$4&" "&$B26,Budget!$AG$4:$AL$132,BN$5+1,FALSE) -> 0 | BR26: {=_xlfn.XLOOKUP( $B$4&" "&$B26, Actuals!$D:$D, _xlfn.XLOOKUP( BR$6, Actuals!$H$3:$BM$3, Actuals!$H:$BM ) )} -> 0 | BS26: =VLOOKUP($B$4&" "&$B26,Budget!$AG$4:$AL$132,6,FALSE) -> 0 | BT26: =BR26-BS26 -> 0 | BV26: {=_xlfn.XLOOKUP( $B$4&" "&$B26, Actuals!$D:$D, _xlfn.XLOOKUP( BV$6, Actuals!$H$3:$BM$3, Actuals!$H:$BM ) )} -> 0
B28: Pipeline Count (EoP) by Stage
B29: EoP Count - Early Stage | C29: EoP | D29: =VLOOKUP($B$4&" "&$B29,Actuals!$D$4:$AG$131,3,FALSE) -> # | E29: {=_xlfn.XLOOKUP( $B$4&" "&$B29, Actuals!$D:$D, _xlfn.XLOOKUP( E$6, Actuals!$H$3:$BD$3, Actuals!$H:$BD ) )} -> 45 | F29: {=_xlfn.XLOOKUP( $B$4&" "&$B29, Actuals!$D:$D, _xlfn.XLOOKUP( F$6, Actuals!$H$3:$BD$3, Actuals!$H:$BD ) )} -> 40 | G29: {=_xlfn.XLOOKUP( $B$4&" "&$B29, Actuals!$D:$D, _xlfn.XLOOKUP( G$6, Actuals!$H$3:$BD$3, Actuals!$H:$BD ) )} -> 28 | H29: {=_xlfn.XLOOKUP( $B$4&" "&$B29, Actuals!$D:$D, _xlfn.XLOOKUP( H$6, Actuals!$H$3:$BD$3, Actuals!$H:$BD ) )} -> 34 | I29: {=_xlfn.XLOOKUP( $B$4&" "&$B29, Actuals!$D:$D, _xlfn.XLOOKUP( I$6, Actuals!$H$3:$BD$3, Actuals!$H:$BD ) )} -> 48 | J29: {=_xlfn.XLOOKUP( $B$4&" "&$B29, Actuals!$D:$D, _xlfn.XLOOKUP( J$6, Actuals!$H$3:$BD$3, Actuals!$H:$BD ) )} -> 41 | K29: {=_xlfn.XLOOKUP( $B$4&" "&$B29, Actuals!$D:$D, _xlfn.XLOOKUP( K$6, Actuals!$H$3:$BD$3, Actuals!$H:$BD ) )} -> 50 | L29: {=_xlfn.XLOOKUP( $B$4&" "&$B29, Actuals!$D:$D, _xlfn.XLOOKUP( L$6, Actuals!$H$3:$BD$3, Actuals!$H:$BD ) )} -> 48 | ... AZ29: {=_xlfn.XLOOKUP( $B$4&" "&$B29, Actuals!$D:$D, _xlfn.XLOOKUP( AZ$6, Actuals!$H$3:$BD$3, Actuals!$H:$BD ) )} -> 0 | BB29: {=_xlfn.XLOOKUP( $B$4&" "&$B29, Actuals!$D:$D, _xlfn.XLOOKUP( BB$7, Actuals!$H$3:$BM$3, Actuals!$H:$BM ) )} -> 0 | BC29: =VLOOKUP($B$4&" "&$B29,Budget!$AG$4:$AL$132,$BB$5+1,FALSE) -> 0 | BD29: =BB29-BC29 -> 0 | BF29: {=_xlfn.XLOOKUP( $B$4&" "&$B29, Actuals!$D:$D, _xlfn.XLOOKUP( BF$7, Actuals!$H$3:$BM$3, Actuals!$H:$BM ) )} -> 0 | BG29: =VLOOKUP($B$4&" "&$B29,Budget!$AG$4:$AL$132,BF$5+1,FALSE) -> 0 | BH29: =BF29-BG29 -> 0 | BJ29: {=_xlfn.XLOOKUP( $B$4&" "&$B29, Actuals!$D:$D, _xlfn.XLOOKUP( BJ$7, Actuals!$H$3:$BM$3, Actuals!$H:$BM ) )} -> 0 | BK29: =VLOOKUP($B$4&" "&$B29,Budget!$AG$4:$AL$132,BJ$5+1,FALSE) -> 0 | BL29: =BJ29-BK29 -> 0 | BN29: {=_xlfn.XLOOKUP( $B$4&" "&$B29, Actuals!$D:$D, _xlfn.XLOOKUP( BN$7, Actuals!$H$3:$BM$3, Actuals!$H:$BM ) )} -> 0 | BO29: =VLOOKUP($B$4&" "&$B29,Budget!$AG$4:$AL$132,BN$5+1,FALSE) -> 0 | BR29: {=_xlfn.XLOOKUP( $B$4&" "&$B29, Actuals!$D:$D, _xlfn.XLOOKUP( BR$6, Actuals!$H$3:$BM$3, Actuals!$H:$BM ) )} -> 0 | BS29: =VLOOKUP($B$4&" "&$B29,Budget!$AG$4:$AL$132,6,FALSE) -> 0 | BT29: =BR29-BS29 -> 0 | BV29: {=_xlfn.XLOOKUP( $B$4&" "&$B29, Actuals!$D:$D, _xlfn.XLOOKUP( BV$6, Actuals!$H$3:$BM$3, Actuals!$H:$BM ) )} -> 0
B30: EoP Count - Intermediate Stage | C30: EoP | D30: =VLOOKUP($B$4&" "&$B30,Actuals!$D$4:$AG$131,3,FALSE) -> # | E30: {=_xlfn.XLOOKUP( $B$4&" "&$B30, Actuals!$D:$D, _xlfn.XLOOKUP( E$6, Actuals!$H$3:$BD$3, Actuals!$H:$BD ) )} -> 14 | F30: {=_xlfn.XLOOKUP( $B$4&" "&$B30, Actuals!$D:$D, _xlfn.XLOOKUP( F$6, Actuals!$H$3:$BD$3, Actuals!$H:$BD ) )} -> 10 | G30: {=_xlfn.XLOOKUP( $B$4&" "&$B30, Actuals!$D:$D, _xlfn.XLOOKUP( G$6, Actuals!$H$3:$BD$3, Actuals!$H:$BD ) )} -> 6 | H30: {=_xlfn.XLOOKUP( $B$4&" "&$B30, Actuals!$D:$D, _xlfn.XLOOKUP( H$6, Actuals!$H$3:$BD$3, Actuals!$H:$BD ) )} -> 5 | I30: {=_xlfn.XLOOKUP( $B$4&" "&$B30, Actuals!$D:$D, _xlfn.XLOOKUP( I$6, Actuals!$H$3:$BD$3, Actuals!$H:$BD ) )} -> 6 | J30: {=_xlfn.XLOOKUP( $B$4&" "&$B30, Actuals!$D:$D, _xlfn.XLOOKUP( J$6, Actuals!$H$3:$BD$3, Actuals!$H:$BD ) )} -> 13 | K30: {=_xlfn.XLOOKUP( $B$4&" "&$B30, Actuals!$D:$D, _xlfn.XLOOKUP( K$6, Actuals!$H$3:$BD$3, Actuals!$H:$BD ) )} -> 10 | L30: {=_xlfn.XLOOKUP( $B$4&" "&$B30, Actuals!$D:$D, _xlfn.XLOOKUP( L$6, Actuals!$H$3:$BD$3, Actuals!$H:$BD ) )} -> 6 | ... AZ30: {=_xlfn.XLOOKUP( $B$4&" "&$B30, Actuals!$D:$D, _xlfn.XLOOKUP( AZ$6, Actuals!$H$3:$BD$3, Actuals!$H:$BD ) )} -> 0 | BB30: {=_xlfn.XLOOKUP( $B$4&" "&$B30, Actuals!$D:$D, _xlfn.XLOOKUP( BB$7, Actuals!$H$3:$BM$3, Actuals!$H:$BM ) )} -> 0 | BC30: =VLOOKUP($B$4&" "&$B30,Budget!$AG$4:$AL$132,$BB$5+1,FALSE) -> 0 | BD30: =BB30-BC30 -> 0 | BF30: {=_xlfn.XLOOKUP( $B$4&" "&$B30, Actuals!$D:$D, _xlfn.XLOOKUP( BF$7, Actuals!$H$3:$BM$3, Actuals!$H:$BM ) )} -> 0 | BG30: =VLOOKUP($B$4&" "&$B30,Budget!$AG$4:$AL$132,BF$5+1,FALSE) -> 0 | BH30: =BF30-BG30 -> 0 | BJ30: {=_xlfn.XLOOKUP( $B$4&" "&$B30, Actuals!$D:$D, _xlfn.XLOOKUP( BJ$7, Actuals!$H$3:$BM$3, Actuals!$H:$BM ) )} -> 0 | BK30: =VLOOKUP($B$4&" "&$B30,Budget!$AG$4:$AL$132,BJ$5+1,FALSE) -> 0 | BL30: =BJ30-BK30 -> 0 | BN30: {=_xlfn.XLOOKUP( $B$4&" "&$B30, Actuals!$D:$D, _xlfn.XLOOKUP( BN$7, Actuals!$H$3:$BM$3, Actuals!$H:$BM ) )} -> 0 | BO30: =VLOOKUP($B$4&" "&$B30,Budget!$AG$4:$AL$132,BN$5+1,FALSE) -> 0 | BR30: {=_xlfn.XLOOKUP( $B$4&" "&$B30, Actuals!$D:$D, _xlfn.XLOOKUP( BR$6, Actuals!$H$3:$BM$3, Actuals!$H:$BM ) )} -> 0 | BS30: =VLOOKUP($B$4&" "&$B30,Budget!$AG$4:$AL$132,6,FALSE) -> 0 | BT30: =BR30-BS30 -> 0 | BV30: {=_xlfn.XLOOKUP( $B$4&" "&$B30, Actuals!$D:$D, _xlfn.XLOOKUP( BV$6, Actuals!$H$3:$BM$3, Actuals!$H:$BM ) )} -> 0
B31: EoP Count - Advanced Stage | C31: EoP | D31: =VLOOKUP($B$4&" "&$B31,Actuals!$D$4:$AG$131,3,FALSE) -> # | E31: {=_xlfn.XLOOKUP( $B$4&" "&$B31, Actuals!$D:$D, _xlfn.XLOOKUP( E$6, Actuals!$H$3:$BD$3, Actuals!$H:$BD ) )} -> 2 | F31: {=_xlfn.XLOOKUP( $B$4&" "&$B31, Actuals!$D:$D, _xlfn.XLOOKUP( F$6, Actuals!$H$3:$BD$3, Actuals!$H:$BD ) )} -> 3 | G31: {=_xlfn.XLOOKUP( $B$4&" "&$B31, Actuals!$D:$D, _xlfn.XLOOKUP( G$6, Actuals!$H$3:$BD$3, Actuals!$H:$BD ) )} -> 4 | H31: {=_xlfn.XLOOKUP( $B$4&" "&$B31, Actuals!$D:$D, _xlfn.XLOOKUP( H$6, Actuals!$H$3:$BD$3, Actuals!$H:$BD ) )} -> 1 | I31: {=_xlfn.XLOOKUP( $B$4&" "&$B31, Actuals!$D:$D, _xlfn.XLOOKUP( I$6, Actuals!$H$3:$BD$3, Actuals!$H:$BD ) )} -> 1 | J31: {=_xlfn.XLOOKUP( $B$4&" "&$B31, Actuals!$D:$D, _xlfn.XLOOKUP( J$6, Actuals!$H$3:$BD$3, Actuals!$H:$BD ) )} -> 0 | K31: {=_xlfn.XLOOKUP( $B$4&" "&$B31, Actuals!$D:$D, _xlfn.XLOOKUP( K$6, Actuals!$H$3:$BD$3, Actuals!$H:$BD ) )} -> 0 | L31: {=_xlfn.XLOOKUP( $B$4&" "&$B31, Actuals!$D:$D, _xlfn.XLOOKUP( L$6, Actuals!$H$3:$BD$3, Actuals!$H:$BD ) )} -> 1 | ... AZ31: {=_xlfn.XLOOKUP( $B$4&" "&$B31, Actuals!$D:$D, _xlfn.XLOOKUP( AZ$6, Actuals!$H$3:$BD$3, Actuals!$H:$BD ) )} -> 0 | BB31: {=_xlfn.XLOOKUP( $B$4&" "&$B31, Actuals!$D:$D, _xlfn.XLOOKUP( BB$7, Actuals!$H$3:$BM$3, Actuals!$H:$BM ) )} -> 0 | BC31: =VLOOKUP($B$4&" "&$B31,Budget!$AG$4:$AL$132,$BB$5+1,FALSE) -> 0 | BD31: =BB31-BC31 -> 0 | BF31: {=_xlfn.XLOOKUP( $B$4&" "&$B31, Actuals!$D:$D, _xlfn.XLOOKUP( BF$7, Actuals!$H$3:$BM$3, Actuals!$H:$BM ) )} -> 0 | BG31: =VLOOKUP($B$4&" "&$B31,Budget!$AG$4:$AL$132,BF$5+1,FALSE) -> 0 | BH31: =BF31-BG31 -> 0 | BJ31: {=_xlfn.XLOOKUP( $B$4&" "&$B31, Actuals!$D:$D, _xlfn.XLOOKUP( BJ$7, Actuals!$H$3:$BM$3, Actuals!$H:$BM ) )} -> 0 | BK31: =VLOOKUP($B$4&" "&$B31,Budget!$AG$4:$AL$132,BJ$5+1,FALSE) -> 0 | BL31: =BJ31-BK31 -> 0 | BN31: {=_xlfn.XLOOKUP( $B$4&" "&$B31, Actuals!$D:$D, _xlfn.XLOOKUP( BN$7, Actuals!$H$3:$BM$3, Actuals!$H:$BM ) )} -> 0 | BO31: =VLOOKUP($B$4&" "&$B31,Budget!$AG$4:$AL$132,BN$5+1,FALSE) -> 0 | BR31: {=_xlfn.XLOOKUP( $B$4&" "&$B31, Actuals!$D:$D, _xlfn.XLOOKUP( BR$6, Actuals!$H$3:$BM$3, Actuals!$H:$BM ) )} -> 0 | BS31: =VLOOKUP($B$4&" "&$B31,Budget!$AG$4:$AL$132,6,FALSE) -> 0 | BT31: =BR31-BS31 -> 0 | BV31: {=_xlfn.XLOOKUP( $B$4&" "&$B31, Actuals!$D:$D, _xlfn.XLOOKUP( BV$6, Actuals!$H$3:$BM$3, Actuals!$H:$BM ) )} -> 0
B32: EoP Count - Total | C32: EoP | D32: =VLOOKUP($B$4&" "&$B32,Actuals!$D$4:$AG$131,3,FALSE) -> # | E32: {=_xlfn.XLOOKUP( $B$4&" "&$B32, Actuals!$D:$D, _xlfn.XLOOKUP( E$6, Actuals!$H$3:$BD$3, Actuals!$H:$BD ) )} -> 61 | F32: {=_xlfn.XLOOKUP( $B$4&" "&$B32, Actuals!$D:$D, _xlfn.XLOOKUP( F$6, Actuals!$H$3:$BD$3, Actuals!$H:$BD ) )} -> 53 | G32: {=_xlfn.XLOOKUP( $B$4&" "&$B32, Actuals!$D:$D, _xlfn.XLOOKUP( G$6, Actuals!$H$3:$BD$3, Actuals!$H:$BD ) )} -> 38 | H32: {=_xlfn.XLOOKUP( $B$4&" "&$B32, Actuals!$D:$D, _xlfn.XLOOKUP( H$6, Actuals!$H$3:$BD$3, Actuals!$H:$BD ) )} -> 40 | I32: {=_xlfn.XLOOKUP( $B$4&" "&$B32, Actuals!$D:$D, _xlfn.XLOOKUP( I$6, Actuals!$H$3:$BD$3, Actuals!$H:$BD ) )} -> 55 | J32: {=_xlfn.XLOOKUP( $B$4&" "&$B32, Actuals!$D:$D, _xlfn.XLOOKUP( J$6, Actuals!$H$3:$BD$3, Actuals!$H:$BD ) )} -> 54 | K32: {=_xlfn.XLOOKUP( $B$4&" "&$B32, Actuals!$D:$D, _xlfn.XLOOKUP( K$6, Actuals!$H$3:$BD$3, Actuals!$H:$BD ) )} -> 60 | L32: {=_xlfn.XLOOKUP( $B$4&" "&$B32, Actuals!$D:$D, _xlfn.XLOOKUP( L$6, Actuals!$H$3:$BD$3, Actuals!$H:$BD ) )} -> 55 | ... AZ32: {=_xlfn.XLOOKUP( $B$4&" "&$B32, Actuals!$D:$D, _xlfn.XLOOKUP( AZ$6, Actuals!$H$3:$BD$3, Actuals!$H:$BD ) )} -> 0 | BB32: {=_xlfn.XLOOKUP( $B$4&" "&$B32, Actuals!$D:$D, _xlfn.XLOOKUP( BB$7, Actuals!$H$3:$BM$3, Actuals!$H:$BM ) )} -> 0 | BC32: =VLOOKUP($B$4&" "&$B32,Budget!$AG$4:$AL$132,$BB$5+1,FALSE) -> 0 | BD32: =BB32-BC32 -> 0 | BF32: {=_xlfn.XLOOKUP( $B$4&" "&$B32, Actuals!$D:$D, _xlfn.XLOOKUP( BF$7, Actuals!$H$3:$BM$3, Actuals!$H:$BM ) )} -> 0 | BG32: =VLOOKUP($B$4&" "&$B32,Budget!$AG$4:$AL$132,BF$5+1,FALSE) -> 0 | BH32: =BF32-BG32 -> 0 | BJ32: {=_xlfn.XLOOKUP( $B$4&" "&$B32, Actuals!$D:$D, _xlfn.XLOOKUP( BJ$7, Actuals!$H$3:$BM$3, Actuals!$H:$BM ) )} -> 0 | BK32: =VLOOKUP($B$4&" "&$B32,Budget!$AG$4:$AL$132,BJ$5+1,FALSE) -> 0 | BL32: =BJ32-BK32 -> 0 | BN32: {=_xlfn.XLOOKUP( $B$4&" "&$B32, Actuals!$D:$D, _xlfn.XLOOKUP( BN$7, Actuals!$H$3:$BM$3, Actuals!$H:$BM ) )} -> 0 | BO32: =VLOOKUP($B$4&" "&$B32,Budget!$AG$4:$AL$132,BN$5+1,FALSE) -> 0 | BR32: {=_xlfn.XLOOKUP( $B$4&" "&$B32, Actuals!$D:$D, _xlfn.XLOOKUP( BR$6, Actuals!$H$3:$BM$3, Actuals!$H:$BM ) )} -> 0 | BS32: =VLOOKUP($B$4&" "&$B32,Budget!$AG$4:$AL$132,6,FALSE) -> 0 | BT32: =BR32-BS32 -> 0 | BV32: {=_xlfn.XLOOKUP( $B$4&" "&$B32, Actuals!$D:$D, _xlfn.XLOOKUP( BV$6, Actuals!$H$3:$BM$3, Actuals!$H:$BM ) )} -> 0
B34: Pipeline Weeks by Stage
B35: Pipeline Weeks - Early | C35: Avg | D35: =VLOOKUP($B$4&" "&$B35,Actuals!$D$4:$AG$131,3,FALSE) -> # | E35: {=_xlfn.XLOOKUP( $B$4&" "&$B35, Actuals!$D:$D, _xlfn.XLOOKUP( E$6, Actuals!$H$3:$BD$3, Actuals!$H:$BD ) )} -> 15 | F35: {=_xlfn.XLOOKUP( $B$4&" "&$B35, Actuals!$D:$D, _xlfn.XLOOKUP( F$6, Actuals!$H$3:$BD$3, Actuals!$H:$BD ) )} -> 18 | G35: {=_xlfn.XLOOKUP( $B$4&" "&$B35, Actuals!$D:$D, _xlfn.XLOOKUP( G$6, Actuals!$H$3:$BD$3, Actuals!$H:$BD ) )} -> 0 | H35: {=_xlfn.XLOOKUP( $B$4&" "&$B35, Actuals!$D:$D, _xlfn.XLOOKUP( H$6, Actuals!$H$3:$BD$3, Actuals!$H:$BD ) )} -> 22 | I35: {=_xlfn.XLOOKUP( $B$4&" "&$B35, Actuals!$D:$D, _xlfn.XLOOKUP( I$6, Actuals!$H$3:$BD$3, Actuals!$H:$BD ) )} -> 18.669643 | J35: {=_xlfn.XLOOKUP( $B$4&" "&$B35, Actuals!$D:$D, _xlfn.XLOOKUP( J$6, Actuals!$H$3:$BD$3, Actuals!$H:$BD ) )} -> 18.1568 | K35: {=_xlfn.XLOOKUP( $B$4&" "&$B35, Actuals!$D:$D, _xlfn.XLOOKUP( K$6, Actuals!$H$3:$BD$3, Actuals!$H:$BD ) )} -> 20.291429 | L35: {=_xlfn.XLOOKUP( $B$4&" "&$B35, Actuals!$D:$D, _xlfn.XLOOKUP( L$6, Actuals!$H$3:$BD$3, Actuals!$H:$BD ) )} -> 20.196429 | ... AZ35: {=_xlfn.XLOOKUP( $B$4&" "&$B35, Actuals!$D:$D, _xlfn.XLOOKUP( AZ$6, Actuals!$H$3:$BD$3, Actuals!$H:$BD ) )} -> 0 | BB35: {=_xlfn.XLOOKUP( $B$4&" "&$B35, Actuals!$D:$D, _xlfn.XLOOKUP( BB$7, Actuals!$H$3:$BM$3, Actuals!$H:$BM ) )} -> - | BC35: =VLOOKUP($B$4&" "&$B35,Budget!$AG$4:$AL$132,$BB$5+1,FALSE) -> - | BD35: =IFERROR(BB35-BC35,"-") -> - | BF35: {=_xlfn.XLOOKUP( $B$4&" "&$B35, Actuals!$D:$D, _xlfn.XLOOKUP( BF$7, Actuals!$H$3:$BM$3, Actuals!$H:$BM ) )} -> - | BG35: =IFERROR(VLOOKUP($B$4&" "&$B35,Budget!$AG$4:$AL$132,$BF$5+1,FALSE),"n.a.") -> - | BH35: =IFERROR(BF35-BG35,"-") -> - | BJ35: {=_xlfn.XLOOKUP( $B$4&" "&$B35, Actuals!$D:$D, _xlfn.XLOOKUP( BJ$7, Actuals!$H$3:$BM$3, Actuals!$H:$BM ) )} -> - | BK35: =IFERROR(VLOOKUP($B$4&" "&$B35,Budget!$AG$4:$AL$132,$BJ$5+1,FALSE),"n.a.") -> - | BL35: =IFERROR(BJ35-BK35,"-") -> - | BN35: {=_xlfn.XLOOKUP( $B$4&" "&$B35, Actuals!$D:$D, _xlfn.XLOOKUP( BN$7, Actuals!$H$3:$BM$3, Actuals!$H:$BM ) )} -> - | BO35: =IFERROR(VLOOKUP($B$4&" "&$B35,Budget!$AG$4:$AL$132,$BN$5+1,FALSE),"n.a.") -> - | BR35: {=_xlfn.XLOOKUP( $B$4&" "&$B35, Actuals!$D:$D, _xlfn.XLOOKUP( BR$6, Actuals!$H$3:$BM$3, Actuals!$H:$BM ) )} -> 0 | BS35: =VLOOKUP($B$4&" "&$B35,Budget!$AG$4:$AL$132,6,FALSE) -> 0 | BT35: =BR35-BS35 -> 0 | BV35: {=_xlfn.XLOOKUP( $B$4&" "&$B35, Actuals!$D:$D, _xlfn.XLOOKUP( BV$6, Actuals!$H$3:$BM$3, Actuals!$H:$BM ) )} -> #DIV/0!
B36: Pipeline Weeks - Intermediate | C36: Avg | D36: =VLOOKUP($B$4&" "&$B36,Actuals!$D$4:$AG$131,3,FALSE) -> # | E36: {=_xlfn.XLOOKUP( $B$4&" "&$B36, Actuals!$D:$D, _xlfn.XLOOKUP( E$6, Actuals!$H$3:$BD$3, Actuals!$H:$BD ) )} -> 25 | F36: {=_xlfn.XLOOKUP( $B$4&" "&$B36, Actuals!$D:$D, _xlfn.XLOOKUP( F$6, Actuals!$H$3:$BD$3, Actuals!$H:$BD ) )} -> 15 | G36: {=_xlfn.XLOOKUP( $B$4&" "&$B36, Actuals!$D:$D, _xlfn.XLOOKUP( G$6, Actuals!$H$3:$BD$3, Actuals!$H:$BD ) )} -> 0 | H36: {=_xlfn.XLOOKUP( $B$4&" "&$B36, Actuals!$D:$D, _xlfn.XLOOKUP( H$6, Actuals!$H$3:$BD$3, Actuals!$H:$BD ) )} -> 21 | I36: {=_xlfn.XLOOKUP( $B$4&" "&$B36, Actuals!$D:$D, _xlfn.XLOOKUP( I$6, Actuals!$H$3:$BD$3, Actuals!$H:$BD ) )} -> 22.857143 | J36: {=_xlfn.XLOOKUP( $B$4&" "&$B36, Actuals!$D:$D, _xlfn.XLOOKUP( J$6, Actuals!$H$3:$BD$3, Actuals!$H:$BD ) )} -> 17.351643 | K36: {=_xlfn.XLOOKUP( $B$4&" "&$B36, Actuals!$D:$D, _xlfn.XLOOKUP( K$6, Actuals!$H$3:$BD$3, Actuals!$H:$BD ) )} -> 13.857143 | L36: {=_xlfn.XLOOKUP( $B$4&" "&$B36, Actuals!$D:$D, _xlfn.XLOOKUP( L$6, Actuals!$H$3:$BD$3, Actuals!$H:$BD ) )} -> 30.738571 | ... AZ36: {=_xlfn.XLOOKUP( $B$4&" "&$B36, Actuals!$D:$D, _xlfn.XLOOKUP( AZ$6, Actuals!$H$3:$BD$3, Actuals!$H:$BD ) )} -> 0 | BB36: {=_xlfn.XLOOKUP( $B$4&" "&$B36, Actuals!$D:$D, _xlfn.XLOOKUP( BB$7, Actuals!$H$3:$BM$3, Actuals!$H:$BM ) )} -> - | BC36: =VLOOKUP($B$4&" "&$B36,Budget!$AG$4:$AL$132,$BB$5+1,FALSE) -> - | BD36: =IFERROR(BB36-BC36,"-") -> - | BF36: {=_xlfn.XLOOKUP( $B$4&" "&$B36, Actuals!$D:$D, _xlfn.XLOOKUP( BF$7, Actuals!$H$3:$BM$3, Actuals!$H:$BM ) )} -> - | BG36: =IFERROR(VLOOKUP($B$4&" "&$B36,Budget!$AG$4:$AL$132,$BF$5+1,FALSE),"n.a.") -> - | BH36: =IFERROR(BF36-BG36,"-") -> - | BJ36: {=_xlfn.XLOOKUP( $B$4&" "&$B36, Actuals!$D:$D, _xlfn.XLOOKUP( BJ$7, Actuals!$H$3:$BM$3, Actuals!$H:$BM ) )} -> - | BK36: =IFERROR(VLOOKUP($B$4&" "&$B36,Budget!$AG$4:$AL$132,$BJ$5+1,FALSE),"n.a.") -> - | BL36: =IFERROR(BJ36-BK36,"-") -> - | BN36: {=_xlfn.XLOOKUP( $B$4&" "&$B36, Actuals!$D:$D, _xlfn.XLOOKUP( BN$7, Actuals!$H$3:$BM$3, Actuals!$H:$BM ) )} -> - | BO36: =IFERROR(VLOOKUP($B$4&" "&$B36,Budget!$AG$4:$AL$132,$BN$5+1,FALSE),"n.a.") -> - | BR36: {=_xlfn.XLOOKUP( $B$4&" "&$B36, Actuals!$D:$D, _xlfn.XLOOKUP( BR$6, Actuals!$H$3:$BM$3, Actuals!$H:$BM ) )} -> 0 | BS36: =VLOOKUP($B$4&" "&$B36,Budget!$AG$4:$AL$132,6,FALSE) -> 0 | BT36: =BR36-BS36 -> 0 | BV36: {=_xlfn.XLOOKUP( $B$4&" "&$B36, Actuals!$D:$D, _xlfn.XLOOKUP( BV$6, Actuals!$H$3:$BM$3, Actuals!$H:$BM ) )} -> #DIV/0!
B37: Pipeline Weeks - Advanced | C37: Avg | D37: =VLOOKUP($B$4&" "&$B37,Actuals!$D$4:$AG$131,3,FALSE) -> # | E37: {=_xlfn.XLOOKUP( $B$4&" "&$B37, Actuals!$D:$D, _xlfn.XLOOKUP( E$6, Actuals!$H$3:$BD$3, Actuals!$H:$BD ) )} -> 30 | F37: {=_xlfn.XLOOKUP( $B$4&" "&$B37, Actuals!$D:$D, _xlfn.XLOOKUP( F$6, Actuals!$H$3:$BD$3, Actuals!$H:$BD ) )} -> 21 | G37: {=_xlfn.XLOOKUP( $B$4&" "&$B37, Actuals!$D:$D, _xlfn.XLOOKUP( G$6, Actuals!$H$3:$BD$3, Actuals!$H:$BD ) )} -> 0 | H37: {=_xlfn.XLOOKUP( $B$4&" "&$B37, Actuals!$D:$D, _xlfn.XLOOKUP( H$6, Actuals!$H$3:$BD$3, Actuals!$H:$BD ) )} -> 26 | I37: {=_xlfn.XLOOKUP( $B$4&" "&$B37, Actuals!$D:$D, _xlfn.XLOOKUP( I$6, Actuals!$H$3:$BD$3, Actuals!$H:$BD ) )} -> 30.142857 | J37: {=_xlfn.XLOOKUP( $B$4&" "&$B37, Actuals!$D:$D, _xlfn.XLOOKUP( J$6, Actuals!$H$3:$BD$3, Actuals!$H:$BD ) )} -> 0 | K37: {=_xlfn.XLOOKUP( $B$4&" "&$B37, Actuals!$D:$D, _xlfn.XLOOKUP( K$6, Actuals!$H$3:$BD$3, Actuals!$H:$BD ) )} -> 0 | L37: {=_xlfn.XLOOKUP( $B$4&" "&$B37, Actuals!$D:$D, _xlfn.XLOOKUP( L$6, Actuals!$H$3:$BD$3, Actuals!$H:$BD ) )} -> 11.428571 | ... AZ37: {=_xlfn.XLOOKUP( $B$4&" "&$B37, Actuals!$D:$D, _xlfn.XLOOKUP( AZ$6, Actuals!$H$3:$BD$3, Actuals!$H:$BD ) )} -> 0 | BB37: {=_xlfn.XLOOKUP( $B$4&" "&$B37, Actuals!$D:$D, _xlfn.XLOOKUP( BB$7, Actuals!$H$3:$BM$3, Actuals!$H:$BM ) )} -> - | BC37: =VLOOKUP($B$4&" "&$B37,Budget!$AG$4:$AL$132,$BB$5+1,FALSE) -> - | BD37: =IFERROR(BB37-BC37,"-") -> - | BF37: {=_xlfn.XLOOKUP( $B$4&" "&$B37, Actuals!$D:$D, _xlfn.XLOOKUP( BF$7, Actuals!$H$3:$BM$3, Actuals!$H:$BM ) )} -> - | BG37: =IFERROR(VLOOKUP($B$4&" "&$B37,Budget!$AG$4:$AL$132,$BF$5+1,FALSE),"n.a.") -> - | BH37: =IFERROR(BF37-BG37,"-") -> - | BJ37: {=_xlfn.XLOOKUP( $B$4&" "&$B37, Actuals!$D:$D, _xlfn.XLOOKUP( BJ$7, Actuals!$H$3:$BM$3, Actuals!$H:$BM ) )} -> - | BK37: =IFERROR(VLOOKUP($B$4&" "&$B37,Budget!$AG$4:$AL$132,$BJ$5+1,FALSE),"n.a.") -> - | BL37: =IFERROR(BJ37-BK37,"-") -> - | BN37: {=_xlfn.XLOOKUP( $B$4&" "&$B37, Actuals!$D:$D, _xlfn.XLOOKUP( BN$7, Actuals!$H$3:$BM$3, Actuals!$H:$BM ) )} -> - | BO37: =IFERROR(VLOOKUP($B$4&" "&$B37,Budget!$AG$4:$AL$132,$BN$5+1,FALSE),"n.a.") -> - | BR37: {=_xlfn.XLOOKUP( $B$4&" "&$B37, Actuals!$D:$D, _xlfn.XLOOKUP( BR$6, Actuals!$H$3:$BM$3, Actuals!$H:$BM ) )} -> 0 | BS37: =VLOOKUP($B$4&" "&$B37,Budget!$AG$4:$AL$132,6,FALSE) -> 0 | BT37: =BR37-BS37 -> 0 | BV37: {=_xlfn.XLOOKUP( $B$4&" "&$B37, Actuals!$D:$D, _xlfn.XLOOKUP( BV$6, Actuals!$H$3:$BM$3, Actuals!$H:$BM ) )} -> #DIV/0!
B39: Lost + Nurtured by Stage
B40: Lost + Nutured - Early | C40: In-period | D40: =VLOOKUP($B$4&" "&$B40,Actuals!$D$4:$AG$131,3,FALSE) -> # | E40: =VLOOKUP($B$4&" "&$B40,Actuals!$D$4:$AG$131,MONTH(E$6)+4,FALSE) -> 4 | F40: =VLOOKUP($B$4&" "&$B40,Actuals!$D$4:$AG$131,MONTH(F$6)+4,FALSE) -> 6 | G40: =VLOOKUP($B$4&" "&$B40,Actuals!$D$4:$AG$131,MONTH(G$6)+4,FALSE) -> 16 | H40: =VLOOKUP($B$4&" "&$B40,Actuals!$D$4:$AG$131,MONTH(H$6)+4,FALSE) -> 1 | I40: =VLOOKUP($B$4&" "&$B40,Actuals!$D$4:$AG$131,MONTH(I$6)+4,FALSE) -> 3 | J40: =VLOOKUP($B$4&" "&$B40,Actuals!$D$4:$AG$131,MONTH(J$6)+4,FALSE) -> 11 | K40: =VLOOKUP($B$4&" "&$B40,Actuals!$D$4:$AG$131,MONTH(K$6)+4,FALSE) -> 4 | L40: =VLOOKUP($B$4&" "&$B40,Actuals!$D$4:$AG$131,MONTH(L$6)+4,FALSE) -> 9 | ... P40: =VLOOKUP($B$4&" "&$B40,Actuals!$D$4:$AG$131,MONTH(P$6)+4,FALSE) -> 0 | Q40: =VLOOKUP($B$4&" "&$B40,Actuals!$D$4:$AR$131,MONTH(Q$6)+16,FALSE) -> 0 | R40: =VLOOKUP($B$4&" "&$B40,Actuals!$D$4:$AR$131,MONTH(R$6)+16,FALSE) -> 0 | S40: =VLOOKUP($B$4&" "&$B40,Actuals!$D$4:$AR$131,MONTH(S$6)+16,FALSE) -> 0 | T40: =VLOOKUP($B$4&" "&$B40,Actuals!$D$4:$AR$131,MONTH(T$6)+16,FALSE) -> 0 | U40: =VLOOKUP($B$4&" "&$B40,Actuals!$D$4:$AR$131,MONTH(U$6)+16,FALSE) -> 0 | V40: {=_xlfn.XLOOKUP( $B$4&" "&$B40, Actuals!$D:$D, _xlfn.XLOOKUP( V$6, Actuals!$H$3:$BD$3, Actuals!$H:$BD ) )} -> 0 | W40: {=_xlfn.XLOOKUP( $B$4&" "&$B40, Actuals!$D:$D, _xlfn.XLOOKUP( W$6, Actuals!$H$3:$BD$3, Actuals!$H:$BD ) )} -> 0 | X40: {=_xlfn.XLOOKUP( $B$4&" "&$B40, Actuals!$D:$D, _xlfn.XLOOKUP( X$6, Actuals!$H$3:$BD$3, Actuals!$H:$BD ) )} -> 0 | Y40: {=_xlfn.XLOOKUP( $B$4&" "&$B40, Actuals!$D:$D, _xlfn.XLOOKUP( Y$6, Actuals!$H$3:$BD$3, Actuals!$H:$BD ) )} -> 0 | Z40: {=_xlfn.XLOOKUP( $B$4&" "&$B40, Actuals!$D:$D, _xlfn.XLOOKUP( Z$6, Actuals!$H$3:$BD$3, Actuals!$H:$BD ) )} -> 0 | AA40: {=_xlfn.XLOOKUP( $B$4&" "&$B40, Actuals!$D:$D, _xlfn.XLOOKUP( AA$6, Actuals!$H$3:$BD$3, Actuals!$H:$BD ) )} -> 0 | AB40: {=_xlfn.XLOOKUP( $B$4&" "&$B40, Actuals!$D:$D, _xlfn.XLOOKUP( AB$6, Actuals!$H$3:$BD$3, Actuals!$H:$BD ) )} -> 0 | AC40: {=_xlfn.XLOOKUP( $B$4&" "&$B40, Actuals!$D:$D, _xlfn.XLOOKUP( AC$6, Actuals!$H$3:$BD$3, Actuals!$H:$BD ) )} -> 14 | ... AZ40: {=_xlfn.XLOOKUP( $B$4&" "&$B40, Actuals!$D:$D, _xlfn.XLOOKUP( AZ$6, Actuals!$H$3:$BD$3, Actuals!$H:$BD ) )} -> 0 | BB40: {=_xlfn.XLOOKUP( $B$4&" "&$B40, Actuals!$D:$D, _xlfn.XLOOKUP( BB$7, Actuals!$H$3:$BM$3, Actuals!$H:$BM ) )} -> 0 | BC40: =VLOOKUP($B$4&" "&$B40,Budget!$AG$4:$AL$132,$BB$5+1,FALSE) -> 0 | BD40: =BB40-BC40 -> 0 | BF40: {=_xlfn.XLOOKUP( $B$4&" "&$B40, Actuals!$D:$D, _xlfn.XLOOKUP( BF$7, Actuals!$H$3:$BM$3, Actuals!$H:$BM ) )} -> 0 | BG40: =VLOOKUP($B$4&" "&$B40,Budget!$AG$4:$AL$132,BF$5+1,FALSE) -> 0 | BH40: =BF40-BG40 -> 0 | BJ40: {=_xlfn.XLOOKUP( $B$4&" "&$B40, Actuals!$D:$D, _xlfn.XLOOKUP( BJ$7, Actuals!$H$3:$BM$3, Actuals!$H:$BM ) )} -> 0 | BK40: =VLOOKUP($B$4&" "&$B40,Budget!$AG$4:$AL$132,BJ$5+1,FALSE) -> 0 | BL40: =BJ40-BK40 -> 0 | BN40: {=_xlfn.XLOOKUP( $B$4&" "&$B40, Actuals!$D:$D, _xlfn.XLOOKUP( BN$7, Actuals!$H$3:$BM$3, Actuals!$H:$BM ) )} -> 0 | BO40: =VLOOKUP($B$4&" "&$B40,Budget!$AG$4:$AL$132,BN$5+1,FALSE) -> 0 | BR40: {=_xlfn.XLOOKUP( $B$4&" "&$B40, Actuals!$D:$D, _xlfn.XLOOKUP( BR$6, Actuals!$H$3:$BM$3, Actuals!$H:$BM ) )} -> 0 | BS40: =VLOOKUP($B$4&" "&$B40,Budget!$AG$4:$AL$132,6,FALSE) -> 0 | BT40: =BR40-BS40 -> 0 | BV40: {=_xlfn.XLOOKUP( $B$4&" "&$B40, Actuals!$D:$D, _xlfn.XLOOKUP( BV$6, Actuals!$H$3:$BM$3, Actuals!$H:$BM ) )} -> 21
B41: Lost + Nutured - Intermediate | C41: In-period | D41: =VLOOKUP($B$4&" "&$B41,Actuals!$D$4:$AG$131,3,FALSE) -> # | E41: =VLOOKUP($B$4&" "&$B41,Actuals!$D$4:$AG$131,MONTH(E$6)+4,FALSE) -> 0 | F41: =VLOOKUP($B$4&" "&$B41,Actuals!$D$4:$AG$131,MONTH(F$6)+4,FALSE) -> 4 | G41: =VLOOKUP($B$4&" "&$B41,Actuals!$D$4:$AG$131,MONTH(G$6)+4,FALSE) -> 2 | H41: =VLOOKUP($B$4&" "&$B41,Actuals!$D$4:$AG$131,MONTH(H$6)+4,FALSE) -> 1 | I41: =VLOOKUP($B$4&" "&$B41,Actuals!$D$4:$AG$131,MONTH(I$6)+4,FALSE) -> 0 | J41: =VLOOKUP($B$4&" "&$B41,Actuals!$D$4:$AG$131,MONTH(J$6)+4,FALSE) -> 0 | K41: =VLOOKUP($B$4&" "&$B41,Actuals!$D$4:$AG$131,MONTH(K$6)+4,FALSE) -> 2 | L41: =VLOOKUP($B$4&" "&$B41,Actuals!$D$4:$AG$131,MONTH(L$6)+4,FALSE) -> 2 | ... P41: =VLOOKUP($B$4&" "&$B41,Actuals!$D$4:$AG$131,MONTH(P$6)+4,FALSE) -> 0 | Q41: =VLOOKUP($B$4&" "&$B41,Actuals!$D$4:$AR$131,MONTH(Q$6)+16,FALSE) -> 0 | R41: =VLOOKUP($B$4&" "&$B41,Actuals!$D$4:$AR$131,MONTH(R$6)+16,FALSE) -> 0 | S41: =VLOOKUP($B$4&" "&$B41,Actuals!$D$4:$AR$131,MONTH(S$6)+16,FALSE) -> 0 | T41: =VLOOKUP($B$4&" "&$B41,Actuals!$D$4:$AR$131,MONTH(T$6)+16,FALSE) -> 0 | U41: =VLOOKUP($B$4&" "&$B41,Actuals!$D$4:$AR$131,MONTH(U$6)+16,FALSE) -> 0 | V41: {=_xlfn.XLOOKUP( $B$4&" "&$B41, Actuals!$D:$D, _xlfn.XLOOKUP( V$6, Actuals!$H$3:$BD$3, Actuals!$H:$BD ) )} -> 0 | W41: {=_xlfn.XLOOKUP( $B$4&" "&$B41, Actuals!$D:$D, _xlfn.XLOOKUP( W$6, Actuals!$H$3:$BD$3, Actuals!$H:$BD ) )} -> 0 | X41: {=_xlfn.XLOOKUP( $B$4&" "&$B41, Actuals!$D:$D, _xlfn.XLOOKUP( X$6, Actuals!$H$3:$BD$3, Actuals!$H:$BD ) )} -> 0 | Y41: {=_xlfn.XLOOKUP( $B$4&" "&$B41, Actuals!$D:$D, _xlfn.XLOOKUP( Y$6, Actuals!$H$3:$BD$3, Actuals!$H:$BD ) )} -> 0 | Z41: {=_xlfn.XLOOKUP( $B$4&" "&$B41, Actuals!$D:$D, _xlfn.XLOOKUP( Z$6, Actuals!$H$3:$BD$3, Actuals!$H:$BD ) )} -> 0 | AA41: {=_xlfn.XLOOKUP( $B$4&" "&$B41, Actuals!$D:$D, _xlfn.XLOOKUP( AA$6, Actuals!$H$3:$BD$3, Actuals!$H:$BD ) )} -> 0 | AB41: {=_xlfn.XLOOKUP( $B$4&" "&$B41, Actuals!$D:$D, _xlfn.XLOOKUP( AB$6, Actuals!$H$3:$BD$3, Actuals!$H:$BD ) )} -> 0 | AC41: {=_xlfn.XLOOKUP( $B$4&" "&$B41, Actuals!$D:$D, _xlfn.XLOOKUP( AC$6, Actuals!$H$3:$BD$3, Actuals!$H:$BD ) )} -> 6 | ... AZ41: {=_xlfn.XLOOKUP( $B$4&" "&$B41, Actuals!$D:$D, _xlfn.XLOOKUP( AZ$6, Actuals!$H$3:$BD$3, Actuals!$H:$BD ) )} -> 0 | BB41: {=_xlfn.XLOOKUP( $B$4&" "&$B41, Actuals!$D:$D, _xlfn.XLOOKUP( BB$7, Actuals!$H$3:$BM$3, Actuals!$H:$BM ) )} -> 0 | BC41: =VLOOKUP($B$4&" "&$B41,Budget!$AG$4:$AL$132,$BB$5+1,FALSE) -> 0 | BD41: =BB41-BC41 -> 0 | BF41: {=_xlfn.XLOOKUP( $B$4&" "&$B41, Actuals!$D:$D, _xlfn.XLOOKUP( BF$7, Actuals!$H$3:$BM$3, Actuals!$H:$BM ) )} -> 0 | BG41: =VLOOKUP($B$4&" "&$B41,Budget!$AG$4:$AL$132,BF$5+1,FALSE) -> 0 | BH41: =BF41-BG41 -> 0 | BJ41: {=_xlfn.XLOOKUP( $B$4&" "&$B41, Actuals!$D:$D, _xlfn.XLOOKUP( BJ$7, Actuals!$H$3:$BM$3, Actuals!$H:$BM ) )} -> 0 | BK41: =VLOOKUP($B$4&" "&$B41,Budget!$AG$4:$AL$132,BJ$5+1,FALSE) -> 0 | BL41: =BJ41-BK41 -> 0 | BN41: {=_xlfn.XLOOKUP( $B$4&" "&$B41, Actuals!$D:$D, _xlfn.XLOOKUP( BN$7, Actuals!$H$3:$BM$3, Actuals!$H:$BM ) )} -> 0 | BO41: =VLOOKUP($B$4&" "&$B41,Budget!$AG$4:$AL$132,BN$5+1,FALSE) -> 0 | BR41: {=_xlfn.XLOOKUP( $B$4&" "&$B41, Actuals!$D:$D, _xlfn.XLOOKUP( BR$6, Actuals!$H$3:$BM$3, Actuals!$H:$BM ) )} -> 0 | BS41: =VLOOKUP($B$4&" "&$B41,Budget!$AG$4:$AL$132,6,FALSE) -> 0 | BT41: =BR41-BS41 -> 0 | BV41: {=_xlfn.XLOOKUP( $B$4&" "&$B41, Actuals!$D:$D, _xlfn.XLOOKUP( BV$6, Actuals!$H$3:$BM$3, Actuals!$H:$BM ) )} -> 4
B42: Lost + Nutured - Advanced | C42: In-period | D42: =VLOOKUP($B$4&" "&$B42,Actuals!$D$4:$AG$131,3,FALSE) -> # | E42: =VLOOKUP($B$4&" "&$B42,Actuals!$D$4:$AG$131,MONTH(E$6)+4,FALSE) -> 2 | F42: =VLOOKUP($B$4&" "&$B42,Actuals!$D$4:$AG$131,MONTH(F$6)+4,FALSE) -> 0 | G42: =VLOOKUP($B$4&" "&$B42,Actuals!$D$4:$AG$131,MONTH(G$6)+4,FALSE) -> 1 | H42: =VLOOKUP($B$4&" "&$B42,Actuals!$D$4:$AG$131,MONTH(H$6)+4,FALSE) -> 0 | I42: =VLOOKUP($B$4&" "&$B42,Actuals!$D$4:$AG$131,MONTH(I$6)+4,FALSE) -> 0 | J42: =VLOOKUP($B$4&" "&$B42,Actuals!$D$4:$AG$131,MONTH(J$6)+4,FALSE) -> 0 | K42: =VLOOKUP($B$4&" "&$B42,Actuals!$D$4:$AG$131,MONTH(K$6)+4,FALSE) -> 0 | L42: =VLOOKUP($B$4&" "&$B42,Actuals!$D$4:$AG$131,MONTH(L$6)+4,FALSE) -> 0 | ... P42: =VLOOKUP($B$4&" "&$B42,Actuals!$D$4:$AG$131,MONTH(P$6)+4,FALSE) -> 0 | Q42: =VLOOKUP($B$4&" "&$B42,Actuals!$D$4:$AR$131,MONTH(Q$6)+16,FALSE) -> 0 | R42: =VLOOKUP($B$4&" "&$B42,Actuals!$D$4:$AR$131,MONTH(R$6)+16,FALSE) -> 0 | S42: =VLOOKUP($B$4&" "&$B42,Actuals!$D$4:$AR$131,MONTH(S$6)+16,FALSE) -> 0 | T42: =VLOOKUP($B$4&" "&$B42,Actuals!$D$4:$AR$131,MONTH(T$6)+16,FALSE) -> 0 | U42: =VLOOKUP($B$4&" "&$B42,Actuals!$D$4:$AR$131,MONTH(U$6)+16,FALSE) -> 0 | V42: {=_xlfn.XLOOKUP( $B$4&" "&$B42, Actuals!$D:$D, _xlfn.XLOOKUP( V$6, Actuals!$H$3:$BD$3, Actuals!$H:$BD ) )} -> 0 | W42: {=_xlfn.XLOOKUP( $B$4&" "&$B42, Actuals!$D:$D, _xlfn.XLOOKUP( W$6, Actuals!$H$3:$BD$3, Actuals!$H:$BD ) )} -> 0 | X42: {=_xlfn.XLOOKUP( $B$4&" "&$B42, Actuals!$D:$D, _xlfn.XLOOKUP( X$6, Actuals!$H$3:$BD$3, Actuals!$H:$BD ) )} -> 0 | Y42: {=_xlfn.XLOOKUP( $B$4&" "&$B42, Actuals!$D:$D, _xlfn.XLOOKUP( Y$6, Actuals!$H$3:$BD$3, Actuals!$H:$BD ) )} -> 0 | Z42: {=_xlfn.XLOOKUP( $B$4&" "&$B42, Actuals!$D:$D, _xlfn.XLOOKUP( Z$6, Actuals!$H$3:$BD$3, Actuals!$H:$BD ) )} -> 0 | AA42: {=_xlfn.XLOOKUP( $B$4&" "&$B42, Actuals!$D:$D, _xlfn.XLOOKUP( AA$6, Actuals!$H$3:$BD$3, Actuals!$H:$BD ) )} -> 0 | AB42: {=_xlfn.XLOOKUP( $B$4&" "&$B42, Actuals!$D:$D, _xlfn.XLOOKUP( AB$6, Actuals!$H$3:$BD$3, Actuals!$H:$BD ) )} -> 0 | AC42: {=_xlfn.XLOOKUP( $B$4&" "&$B42, Actuals!$D:$D, _xlfn.XLOOKUP( AC$6, Actuals!$H$3:$BD$3, Actuals!$H:$BD ) )} -> 1 | ... AZ42: {=_xlfn.XLOOKUP( $B$4&" "&$B42, Actuals!$D:$D, _xlfn.XLOOKUP( AZ$6, Actuals!$H$3:$BD$3, Actuals!$H:$BD ) )} -> 0 | BB42: {=_xlfn.XLOOKUP( $B$4&" "&$B42, Actuals!$D:$D, _xlfn.XLOOKUP( BB$7, Actuals!$H$3:$BM$3, Actuals!$H:$BM ) )} -> 0 | BC42: =VLOOKUP($B$4&" "&$B42,Budget!$AG$4:$AL$132,$BB$5+1,FALSE) -> 0 | BD42: =BB42-BC42 -> 0 | BF42: {=_xlfn.XLOOKUP( $B$4&" "&$B42, Actuals!$D:$D, _xlfn.XLOOKUP( BF$7, Actuals!$H$3:$BM$3, Actuals!$H:$BM ) )} -> 0 | BG42: =VLOOKUP($B$4&" "&$B42,Budget!$AG$4:$AL$132,BF$5+1,FALSE) -> 0 | BH42: =BF42-BG42 -> 0 | BJ42: {=_xlfn.XLOOKUP( $B$4&" "&$B42, Actuals!$D:$D, _xlfn.XLOOKUP( BJ$7, Actuals!$H$3:$BM$3, Actuals!$H:$BM ) )} -> 0 | BK42: =VLOOKUP($B$4&" "&$B42,Budget!$AG$4:$AL$132,BJ$5+1,FALSE) -> 0 | BL42: =BJ42-BK42 -> 0 | BN42: {=_xlfn.XLOOKUP( $B$4&" "&$B42, Actuals!$D:$D, _xlfn.XLOOKUP( BN$7, Actuals!$H$3:$BM$3, Actuals!$H:$BM ) )} -> 0 | BO42: =VLOOKUP($B$4&" "&$B42,Budget!$AG$4:$AL$132,BN$5+1,FALSE) -> 0 | BR42: {=_xlfn.XLOOKUP( $B$4&" "&$B42, Actuals!$D:$D, _xlfn.XLOOKUP( BR$6, Actuals!$H$3:$BM$3, Actuals!$H:$BM ) )} -> 0 | BS42: =VLOOKUP($B$4&" "&$B42,Budget!$AG$4:$AL$132,6,FALSE) -> 0 | BT42: =BR42-BS42 -> 0 | BV42: {=_xlfn.XLOOKUP( $B$4&" "&$B42, Actuals!$D:$D, _xlfn.XLOOKUP( BV$6, Actuals!$H$3:$BM$3, Actuals!$H:$BM ) )} -> 1
B43: Lost + Nutured - Total | C43: In-period | D43: =VLOOKUP($B$4&" "&$B43,Actuals!$D$4:$AG$131,3,FALSE) -> # | E43: =VLOOKUP($B$4&" "&$B43,Actuals!$D$4:$AG$131,MONTH(E$6)+4,FALSE) -> 6 | F43: =VLOOKUP($B$4&" "&$B43,Actuals!$D$4:$AG$131,MONTH(F$6)+4,FALSE) -> 10 | G43: =VLOOKUP($B$4&" "&$B43,Actuals!$D$4:$AG$131,MONTH(G$6)+4,FALSE) -> 19 | H43: =VLOOKUP($B$4&" "&$B43,Actuals!$D$4:$AG$131,MONTH(H$6)+4,FALSE) -> 2 | I43: =VLOOKUP($B$4&" "&$B43,Actuals!$D$4:$AG$131,MONTH(I$6)+4,FALSE) -> 3 | J43: =VLOOKUP($B$4&" "&$B43,Actuals!$D$4:$AG$131,MONTH(J$6)+4,FALSE) -> 11 | K43: =VLOOKUP($B$4&" "&$B43,Actuals!$D$4:$AG$131,MONTH(K$6)+4,FALSE) -> 6 | L43: =VLOOKUP($B$4&" "&$B43,Actuals!$D$4:$AG$131,MONTH(L$6)+4,FALSE) -> 11 | ... P43: =VLOOKUP($B$4&" "&$B43,Actuals!$D$4:$AG$131,MONTH(P$6)+4,FALSE) -> 0 | Q43: =VLOOKUP($B$4&" "&$B43,Actuals!$D$4:$AR$131,MONTH(Q$6)+16,FALSE) -> 0 | R43: =VLOOKUP($B$4&" "&$B43,Actuals!$D$4:$AR$131,MONTH(R$6)+16,FALSE) -> 0 | S43: =VLOOKUP($B$4&" "&$B43,Actuals!$D$4:$AR$131,MONTH(S$6)+16,FALSE) -> 0 | T43: =VLOOKUP($B$4&" "&$B43,Actuals!$D$4:$AR$131,MONTH(T$6)+16,FALSE) -> 0 | U43: =VLOOKUP($B$4&" "&$B43,Actuals!$D$4:$AR$131,MONTH(U$6)+16,FALSE) -> 0 | V43: {=_xlfn.XLOOKUP( $B$4&" "&$B43, Actuals!$D:$D, _xlfn.XLOOKUP( V$6, Actuals!$H$3:$BD$3, Actuals!$H:$BD ) )} -> 0 | W43: {=_xlfn.XLOOKUP( $B$4&" "&$B43, Actuals!$D:$D, _xlfn.XLOOKUP( W$6, Actuals!$H$3:$BD$3, Actuals!$H:$BD ) )} -> 0 | X43: {=_xlfn.XLOOKUP( $B$4&" "&$B43, Actuals!$D:$D, _xlfn.XLOOKUP( X$6, Actuals!$H$3:$BD$3, Actuals!$H:$BD ) )} -> 0 | Y43: {=_xlfn.XLOOKUP( $B$4&" "&$B43, Actuals!$D:$D, _xlfn.XLOOKUP( Y$6, Actuals!$H$3:$BD$3, Actuals!$H:$BD ) )} -> 0 | Z43: {=_xlfn.XLOOKUP( $B$4&" "&$B43, Actuals!$D:$D, _xlfn.XLOOKUP( Z$6, Actuals!$H$3:$BD$3, Actuals!$H:$BD ) )} -> 0 | AA43: {=_xlfn.XLOOKUP( $B$4&" "&$B43, Actuals!$D:$D, _xlfn.XLOOKUP( AA$6, Actuals!$H$3:$BD$3, Actuals!$H:$BD ) )} -> 0 | AB43: {=_xlfn.XLOOKUP( $B$4&" "&$B43, Actuals!$D:$D, _xlfn.XLOOKUP( AB$6, Actuals!$H$3:$BD$3, Actuals!$H:$BD ) )} -> 0 | AC43: {=_xlfn.XLOOKUP( $B$4&" "&$B43, Actuals!$D:$D, _xlfn.XLOOKUP( AC$6, Actuals!$H$3:$BD$3, Actuals!$H:$BD ) )} -> 2 | ... AZ43: {=_xlfn.XLOOKUP( $B$4&" "&$B43, Actuals!$D:$D, _xlfn.XLOOKUP( AZ$6, Actuals!$H$3:$BD$3, Actuals!$H:$BD ) )} -> 0 | BB43: {=_xlfn.XLOOKUP( $B$4&" "&$B43, Actuals!$D:$D, _xlfn.XLOOKUP( BB$7, Actuals!$H$3:$BM$3, Actuals!$H:$BM ) )} -> 0 | BC43: =VLOOKUP($B$4&" "&$B43,Budget!$AG$4:$AL$132,$BB$5+1,FALSE) -> 0 | BD43: =BB43-BC43 -> 0 | BF43: {=_xlfn.XLOOKUP( $B$4&" "&$B43, Actuals!$D:$D, _xlfn.XLOOKUP( BF$7, Actuals!$H$3:$BM$3, Actuals!$H:$BM ) )} -> 0 | BG43: =VLOOKUP($B$4&" "&$B43,Budget!$AG$4:$AL$132,BF$5+1,FALSE) -> 0 | BH43: =BF43-BG43 -> 0 | BJ43: {=_xlfn.XLOOKUP( $B$4&" "&$B43, Actuals!$D:$D, _xlfn.XLOOKUP( BJ$7, Actuals!$H$3:$BM$3, Actuals!$H:$BM ) )} -> 0 | BK43: =VLOOKUP($B$4&" "&$B43,Budget!$AG$4:$AL$132,BJ$5+1,FALSE) -> 0 | BL43: =BJ43-BK43 -> 0 | BN43: {=_xlfn.XLOOKUP( $B$4&" "&$B43, Actuals!$D:$D, _xlfn.XLOOKUP( BN$7, Actuals!$H$3:$BM$3, Actuals!$H:$BM ) )} -> 0 | BO43: =VLOOKUP($B$4&" "&$B43,Budget!$AG$4:$AL$132,BN$5+1,FALSE) -> 0 | BR43: {=_xlfn.XLOOKUP( $B$4&" "&$B43, Actuals!$D:$D, _xlfn.XLOOKUP( BR$6, Actuals!$H$3:$BM$3, Actuals!$H:$BM ) )} -> 0 | BS43: =VLOOKUP($B$4&" "&$B43,Budget!$AG$4:$AL$132,6,FALSE) -> 0 | BT43: =BR43-BS43 -> 0 | BV43: {=_xlfn.XLOOKUP( $B$4&" "&$B43, Actuals!$D:$D, _xlfn.XLOOKUP( BV$6, Actuals!$H$3:$BM$3, Actuals!$H:$BM ) )} -> 30
B45: Efficiency
B46: Headcount | C46: EoP | D46: =VLOOKUP($B$4&" "&$B46,Actuals!$D$4:$AG$131,3,FALSE) -> # | E46: =VLOOKUP($B$4&" "&$B46,Actuals!$D$4:$AG$131,MONTH(E$6)+4,FALSE) -> 6 | F46: =VLOOKUP($B$4&" "&$B46,Actuals!$D$4:$AG$131,MONTH(F$6)+4,FALSE) -> 7 | G46: =VLOOKUP($B$4&" "&$B46,Actuals!$D$4:$AG$131,MONTH(G$6)+4,FALSE) -> 8 | H46: =VLOOKUP($B$4&" "&$B46,Actuals!$D$4:$AG$131,MONTH(H$6)+4,FALSE) -> 9 | I46: =VLOOKUP($B$4&" "&$B46,Actuals!$D$4:$AG$131,MONTH(I$6)+4,FALSE) -> 10 | J46: =VLOOKUP($B$4&" "&$B46,Actuals!$D$4:$AG$131,MONTH(J$6)+4,FALSE) -> 9 | K46: =VLOOKUP($B$4&" "&$B46,Actuals!$D$4:$AG$131,MONTH(K$6)+4,FALSE) -> 8 | L46: =VLOOKUP($B$4&" "&$B46,Actuals!$D$4:$AG$131,MONTH(L$6)+4,FALSE) -> 8 | ... P46: =VLOOKUP($B$4&" "&$B46,Actuals!$D$4:$AG$131,MONTH(P$6)+4,FALSE) -> 0 | Q46: =VLOOKUP($B$4&" "&$B46,Actuals!$D$4:$AR$131,MONTH(Q$6)+16,FALSE) -> 0 | R46: =VLOOKUP($B$4&" "&$B46,Actuals!$D$4:$AR$131,MONTH(R$6)+16,FALSE) -> 0 | S46: =VLOOKUP($B$4&" "&$B46,Actuals!$D$4:$AR$131,MONTH(S$6)+16,FALSE) -> 0 | T46: =VLOOKUP($B$4&" "&$B46,Actuals!$D$4:$AR$131,MONTH(T$6)+16,FALSE) -> 0 | U46: =VLOOKUP($B$4&" "&$B46,Actuals!$D$4:$AR$131,MONTH(U$6)+16,FALSE) -> 0 | V46: {=_xlfn.XLOOKUP( $B$4&" "&$B46, Actuals!$D:$D, _xlfn.XLOOKUP( V$6, Actuals!$H$3:$BD$3, Actuals!$H:$BD ) )} -> 0 | W46: {=_xlfn.XLOOKUP( $B$4&" "&$B46, Actuals!$D:$D, _xlfn.XLOOKUP( W$6, Actuals!$H$3:$BD$3, Actuals!$H:$BD ) )} -> 0 | X46: {=_xlfn.XLOOKUP( $B$4&" "&$B46, Actuals!$D:$D, _xlfn.XLOOKUP( X$6, Actuals!$H$3:$BD$3, Actuals!$H:$BD ) )} -> 0 | Y46: {=_xlfn.XLOOKUP( $B$4&" "&$B46, Actuals!$D:$D, _xlfn.XLOOKUP( Y$6, Actuals!$H$3:$BD$3, Actuals!$H:$BD ) )} -> 0 | Z46: {=_xlfn.XLOOKUP( $B$4&" "&$B46, Actuals!$D:$D, _xlfn.XLOOKUP( Z$6, Actuals!$H$3:$BD$3, Actuals!$H:$BD ) )} -> 0 | AA46: {=_xlfn.XLOOKUP( $B$4&" "&$B46, Actuals!$D:$D, _xlfn.XLOOKUP( AA$6, Actuals!$H$3:$BD$3, Actuals!$H:$BD ) )} -> 0 | AB46: {=_xlfn.XLOOKUP( $B$4&" "&$B46, Actuals!$D:$D, _xlfn.XLOOKUP( AB$6, Actuals!$H$3:$BD$3, Actuals!$H:$BD ) )} -> 0 | AC46: {=_xlfn.XLOOKUP( $B$4&" "&$B46, Actuals!$D:$D, _xlfn.XLOOKUP( AC$6, Actuals!$H$3:$BD$3, Actuals!$H:$BD ) )} -> 9 | ... AZ46: {=_xlfn.XLOOKUP( $B$4&" "&$B46, Actuals!$D:$D, _xlfn.XLOOKUP( AZ$6, Actuals!$H$3:$BD$3, Actuals!$H:$BD ) )} -> 0 | BB46: {=_xlfn.XLOOKUP( $B$4&" "&$B46, Actuals!$D:$D, _xlfn.XLOOKUP( BB$7, Actuals!$H$3:$BM$3, Actuals!$H:$BM ) )} -> 2 | BC46: =VLOOKUP($B$4&" "&$B46,Budget!$AG$4:$AL$132,$BB$5+1,FALSE) -> 0 | BD46: =BB46-BC46 -> 2 | BF46: {=_xlfn.XLOOKUP( $B$4&" "&$B46, Actuals!$D:$D, _xlfn.XLOOKUP( BF$7, Actuals!$H$3:$BM$3, Actuals!$H:$BM ) )} -> 0 | BG46: =VLOOKUP($B$4&" "&$B46,Budget!$AG$4:$AL$132,BF$5+1,FALSE) -> 8 | BH46: =BF46-BG46 -> -8 | BJ46: {=_xlfn.XLOOKUP( $B$4&" "&$B46, Actuals!$D:$D, _xlfn.XLOOKUP( BJ$7, Actuals!$H$3:$BM$3, Actuals!$H:$BM ) )} -> 0 | BK46: =VLOOKUP($B$4&" "&$B46,Budget!$AG$4:$AL$132,BJ$5+1,FALSE) -> 8 | BL46: =BJ46-BK46 -> -8 | BN46: {=_xlfn.XLOOKUP( $B$4&" "&$B46, Actuals!$D:$D, _xlfn.XLOOKUP( BN$7, Actuals!$H$3:$BM$3, Actuals!$H:$BM ) )} -> 0 | BO46: =VLOOKUP($B$4&" "&$B46,Budget!$AG$4:$AL$132,BN$5+1,FALSE) -> 8 | BR46: {=_xlfn.XLOOKUP( $B$4&" "&$B46, Actuals!$D:$D, _xlfn.XLOOKUP( BR$6, Actuals!$H$3:$BM$3, Actuals!$H:$BM ) )} -> 0 | BS46: =VLOOKUP($B$4&" "&$B46,Budget!$AG$4:$AL$132,6,FALSE) -> 8 | BT46: =BR46-BS46 -> -8 | BV46: {=_xlfn.XLOOKUP( $B$4&" "&$B46, Actuals!$D:$D, _xlfn.XLOOKUP( BV$6, Actuals!$H$3:$BM$3, Actuals!$H:$BM ) )} -> 4
B47: Sales expense | C47: L3M Avg | D47: =VLOOKUP($B$4&" "&$B47,Actuals!$D$4:$AG$131,3,FALSE) -> $ | E47: =VLOOKUP($B$4&" "&$B47,Actuals!$D$4:$AG$131,MONTH(E$6)+4,FALSE) -> 135237.53 | F47: =VLOOKUP($B$4&" "&$B47,Actuals!$D$4:$AG$131,MONTH(F$6)+4,FALSE) -> 118496.64 | G47: =VLOOKUP($B$4&" "&$B47,Actuals!$D$4:$AG$131,MONTH(G$6)+4,FALSE) -> 140726.63 | H47: =VLOOKUP($B$4&" "&$B47,Actuals!$D$4:$AG$131,MONTH(H$6)+4,FALSE) -> 148811.22 | I47: =VLOOKUP($B$4&" "&$B47,Actuals!$D$4:$AG$131,MONTH(I$6)+4,FALSE) -> 151250 | J47: =VLOOKUP($B$4&" "&$B47,Actuals!$D$4:$AG$131,MONTH(J$6)+4,FALSE) -> 146217.68 | K47: =VLOOKUP($B$4&" "&$B47,Actuals!$D$4:$AG$131,MONTH(K$6)+4,FALSE) -> 122131.65 | L47: =VLOOKUP($B$4&" "&$B47,Actuals!$D$4:$AG$131,MONTH(L$6)+4,FALSE) -> 128831.6 | ... P47: =VLOOKUP($B$4&" "&$B47,Actuals!$D$4:$AG$131,MONTH(P$6)+4,FALSE) -> 0 | Q47: =VLOOKUP($B$4&" "&$B47,Actuals!$D$4:$AR$131,MONTH(Q$6)+16,FALSE) -> 0 | R47: =VLOOKUP($B$4&" "&$B47,Actuals!$D$4:$AR$131,MONTH(R$6)+16,FALSE) -> 0 | S47: =VLOOKUP($B$4&" "&$B47,Actuals!$D$4:$AR$131,MONTH(S$6)+16,FALSE) -> 0 | T47: =VLOOKUP($B$4&" "&$B47,Actuals!$D$4:$AR$131,MONTH(T$6)+16,FALSE) -> 0 | U47: =VLOOKUP($B$4&" "&$B47,Actuals!$D$4:$AR$131,MONTH(U$6)+16,FALSE) -> 0 | V47: {=_xlfn.XLOOKUP( $B$4&" "&$B47, Actuals!$D:$D, _xlfn.XLOOKUP( V$6, Actuals!$H$3:$BD$3, Actuals!$H:$BD ) )} -> 0 | W47: {=_xlfn.XLOOKUP( $B$4&" "&$B47, Actuals!$D:$D, _xlfn.XLOOKUP( W$6, Actuals!$H$3:$BD$3, Actuals!$H:$BD ) )} -> 0 | X47: {=_xlfn.XLOOKUP( $B$4&" "&$B47, Actuals!$D:$D, _xlfn.XLOOKUP( X$6, Actuals!$H$3:$BD$3, Actuals!$H:$BD ) )} -> 0 | Y47: {=_xlfn.XLOOKUP( $B$4&" "&$B47, Actuals!$D:$D, _xlfn.XLOOKUP( Y$6, Actuals!$H$3:$BD$3, Actuals!$H:$BD ) )} -> 0 | Z47: {=_xlfn.XLOOKUP( $B$4&" "&$B47, Actuals!$D:$D, _xlfn.XLOOKUP( Z$6, Actuals!$H$3:$BD$3, Actuals!$H:$BD ) )} -> 0 | AA47: {=_xlfn.XLOOKUP( $B$4&" "&$B47, Actuals!$D:$D, _xlfn.XLOOKUP( AA$6, Actuals!$H$3:$BD$3, Actuals!$H:$BD ) )} -> 0 | AB47: {=_xlfn.XLOOKUP( $B$4&" "&$B47, Actuals!$D:$D, _xlfn.XLOOKUP( AB$6, Actuals!$H$3:$BD$3, Actuals!$H:$BD ) )} -> 0 | AC47: {=_xlfn.XLOOKUP( $B$4&" "&$B47, Actuals!$D:$D, _xlfn.XLOOKUP( AC$6, Actuals!$H$3:$BD$3, Actuals!$H:$BD ) )} -> 47234.7 | ... AZ47: {=_xlfn.XLOOKUP( $B$4&" "&$B47, Actuals!$D:$D, _xlfn.XLOOKUP( AZ$6, Actuals!$H$3:$BD$3, Actuals!$H:$BD ) )} -> 0 | BB47: {=_xlfn.XLOOKUP( $B$4&" "&$B47, Actuals!$D:$D, _xlfn.XLOOKUP( BB$7, Actuals!$H$3:$BM$3, Actuals!$H:$BM ) )} -> 161277.81 | BC47: =VLOOKUP($B$4&" "&$B47,Budget!$AG$4:$AL$132,$BB$5+1,FALSE) -> 442762 | BD47: =BB47-BC47 -> -281484.19 | BF47: {=_xlfn.XLOOKUP( $B$4&" "&$B47, Actuals!$D:$D, _xlfn.XLOOKUP( BF$7, Actuals!$H$3:$BM$3, Actuals!$H:$BM ) )} -> 0 | BG47: =VLOOKUP($B$4&" "&$B47,Budget!$AG$4:$AL$132,BF$5+1,FALSE) -> 401550 | BH47: =BF47-BG47 -> -401550 | BJ47: {=_xlfn.XLOOKUP( $B$4&" "&$B47, Actuals!$D:$D, _xlfn.XLOOKUP( BJ$7, Actuals!$H$3:$BM$3, Actuals!$H:$BM ) )} -> 0 | BK47: =VLOOKUP($B$4&" "&$B47,Budget!$AG$4:$AL$132,BJ$5+1,FALSE) -> 410176 | BL47: =BJ47-BK47 -> -410176 | BN47: {=_xlfn.XLOOKUP( $B$4&" "&$B47, Actuals!$D:$D, _xlfn.XLOOKUP( BN$7, Actuals!$H$3:$BM$3, Actuals!$H:$BM ) )} -> 0 | BO47: =VLOOKUP($B$4&" "&$B47,Budget!$AG$4:$AL$132,BN$5+1,FALSE) -> 409989 | BR47: {=_xlfn.XLOOKUP( $B$4&" "&$B47, Actuals!$D:$D, _xlfn.XLOOKUP( BR$6, Actuals!$H$3:$BM$3, Actuals!$H:$BM ) )} -> 161277.81 | BS47: =VLOOKUP($B$4&" "&$B47,Budget!$AG$4:$AL$132,6,FALSE) -> 1666090 | BT47: =BR47-BS47 -> -1504812.2 | BV47: {=_xlfn.XLOOKUP( $B$4&" "&$B47, Actuals!$D:$D, _xlfn.XLOOKUP( BV$6, Actuals!$H$3:$BM$3, Actuals!$H:$BM ) )} -> 605044.77
B48: Sales exp. per $1 ARR | C48: L3M Avg | D48: =VLOOKUP($B$4&" "&$B48,Actuals!$D$4:$AG$131,3,FALSE) -> $ | E48: =VLOOKUP($B$4&" "&$B48,Actuals!$D$4:$AG$131,MONTH(E$6)+4,FALSE) -> 2.7599496 | F48: =VLOOKUP($B$4&" "&$B48,Actuals!$D$4:$AG$131,MONTH(F$6)+4,FALSE) -> - | G48: =VLOOKUP($B$4&" "&$B48,Actuals!$D$4:$AG$131,MONTH(G$6)+4,FALSE) -> 2.1003975 | H48: =VLOOKUP($B$4&" "&$B48,Actuals!$D$4:$AG$131,MONTH(H$6)+4,FALSE) -> 23.809795 | I48: =VLOOKUP($B$4&" "&$B48,Actuals!$D$4:$AG$131,MONTH(I$6)+4,FALSE) -> - | J48: =VLOOKUP($B$4&" "&$B48,Actuals!$D$4:$AG$131,MONTH(J$6)+4,FALSE) -> 0.6799083 | K48: =VLOOKUP($B$4&" "&$B48,Actuals!$D$4:$AG$131,MONTH(K$6)+4,FALSE) -> - | L48: =VLOOKUP($B$4&" "&$B48,Actuals!$D$4:$AG$131,MONTH(L$6)+4,FALSE) -> 0.35496666 | ... P48: =VLOOKUP($B$4&" "&$B48,Actuals!$D$4:$AG$131,MONTH(P$6)+4,FALSE) -> - | Q48: =VLOOKUP($B$4&" "&$B48,Actuals!$D$4:$AR$131,MONTH(Q$6)+16,FALSE) -> - | R48: =VLOOKUP($B$4&" "&$B48,Actuals!$D$4:$AR$131,MONTH(R$6)+16,FALSE) -> - | S48: =VLOOKUP($B$4&" "&$B48,Actuals!$D$4:$AR$131,MONTH(S$6)+16,FALSE) -> - | T48: =VLOOKUP($B$4&" "&$B48,Actuals!$D$4:$AR$131,MONTH(T$6)+16,FALSE) -> - | U48: =VLOOKUP($B$4&" "&$B48,Actuals!$D$4:$AR$131,MONTH(U$6)+16,FALSE) -> - | V48: {=_xlfn.XLOOKUP( $B$4&" "&$B48, Actuals!$D:$D, _xlfn.XLOOKUP( V$6, Actuals!$H$3:$BD$3, Actuals!$H:$BD ) )} -> - | W48: {=_xlfn.XLOOKUP( $B$4&" "&$B48, Actuals!$D:$D, _xlfn.XLOOKUP( W$6, Actuals!$H$3:$BD$3, Actuals!$H:$BD ) )} -> - | X48: {=_xlfn.XLOOKUP( $B$4&" "&$B48, Actuals!$D:$D, _xlfn.XLOOKUP( X$6, Actuals!$H$3:$BD$3, Actuals!$H:$BD ) )} -> - | Y48: {=_xlfn.XLOOKUP( $B$4&" "&$B48, Actuals!$D:$D, _xlfn.XLOOKUP( Y$6, Actuals!$H$3:$BD$3, Actuals!$H:$BD ) )} -> - | Z48: {=_xlfn.XLOOKUP( $B$4&" "&$B48, Actuals!$D:$D, _xlfn.XLOOKUP( Z$6, Actuals!$H$3:$BD$3, Actuals!$H:$BD ) )} -> - | AA48: {=_xlfn.XLOOKUP( $B$4&" "&$B48, Actuals!$D:$D, _xlfn.XLOOKUP( AA$6, Actuals!$H$3:$BD$3, Actuals!$H:$BD ) )} -> - | AB48: {=_xlfn.XLOOKUP( $B$4&" "&$B48, Actuals!$D:$D, _xlfn.XLOOKUP( AB$6, Actuals!$H$3:$BD$3, Actuals!$H:$BD ) )} -> - | AC48: {=_xlfn.XLOOKUP( $B$4&" "&$B48, Actuals!$D:$D, _xlfn.XLOOKUP( AC$6, Actuals!$H$3:$BD$3, Actuals!$H:$BD ) )} -> - | ... AZ48: {=_xlfn.XLOOKUP( $B$4&" "&$B48, Actuals!$D:$D, _xlfn.XLOOKUP( AZ$6, Actuals!$H$3:$BD$3, Actuals!$H:$BD ) )} -> - | BB48: {=_xlfn.XLOOKUP( $B$4&" "&$B48, Actuals!$D:$D, _xlfn.XLOOKUP( BB$7, Actuals!$H$3:$BM$3, Actuals!$H:$BM ) )} -> - | BC48: =VLOOKUP($B$4&" "&$B48,Budget!$AG$4:$AL$132,$BB$5+1,FALSE) -> 1.3836313 | BD48: =IFERROR(BB48-BC48,"-") -> - | BF48: {=_xlfn.XLOOKUP( $B$4&" "&$B48, Actuals!$D:$D, _xlfn.XLOOKUP( BF$7, Actuals!$H$3:$BM$3, Actuals!$H:$BM ) )} -> - | BG48: =IFERROR(VLOOKUP($B$4&" "&$B48,Budget!$AG$4:$AL$132,$BF$5+1,FALSE),"n.a.") -> 0.89233333 | BH48: =IFERROR(BF48-BG48,"-") -> - | BJ48: {=_xlfn.XLOOKUP( $B$4&" "&$B48, Actuals!$D:$D, _xlfn.XLOOKUP( BJ$7, Actuals!$H$3:$BM$3, Actuals!$H:$BM ) )} -> - | BK48: =IFERROR(VLOOKUP($B$4&" "&$B48,Budget!$AG$4:$AL$132,$BJ$5+1,FALSE),"n.a.") -> 0.91150222 | BL48: =IFERROR(BJ48-BK48,"-") -> - | BN48: {=_xlfn.XLOOKUP( $B$4&" "&$B48, Actuals!$D:$D, _xlfn.XLOOKUP( BN$7, Actuals!$H$3:$BM$3, Actuals!$H:$BM ) )} -> - | BO48: =IFERROR(VLOOKUP($B$4&" "&$B48,Budget!$AG$4:$AL$132,$BN$5+1,FALSE),"n.a.") -> 0.70687759 | BR48: {=_xlfn.XLOOKUP( $B$4&" "&$B48, Actuals!$D:$D, _xlfn.XLOOKUP( BR$6, Actuals!$H$3:$BM$3, Actuals!$H:$BM ) )} -> 2.0575086 | BS48: =VLOOKUP($B$4&" "&$B48,Budget!$AG$4:$AL$132,6,FALSE) -> 0.92560556 | BT48: =BR48-BS48 -> 1.1319031 | BV48: {=_xlfn.XLOOKUP( $B$4&" "&$B48, Actuals!$D:$D, _xlfn.XLOOKUP( BV$6, Actuals!$H$3:$BM$3, Actuals!$H:$BM ) )}
B50: Notes
B51: (1) BDR-sourced opportunities are included with Marketing

Sheet Marketing
B2: ='2023 Control'!$C$3 -> Concertiv
B3: =('2024 Control'!$C$4)&" Reporting Package" -> December 2025 Reporting Package
B4: Marketing
E5: Monthly | BB5: 1 | BF5: 2 | BJ5: 3 | BN5: 4 | BR5: YTD vs. Budget
D6: Units | E6: 44957 | F6: 44985 | G6: 45016 | H6: =EOMONTH(G6,1) -> 45046 | I6: =EOMONTH(H6,1) -> 45077 | J6: =EOMONTH(I6,1) -> 45107 | K6: =EOMONTH(J6,1) -> 45138 | L6: =EOMONTH(K6,1) -> 45169 | M6: =EOMONTH(L6,1) -> 45199 | N6: =EOMONTH(M6,1) -> 45230 | O6: =EOMONTH(N6,1) -> 45260 | ... AZ6: =EOMONTH(AY6,1) -> 46387 | BB6: Act | BC6: Bgt. | BD6: Diff. | BF6: Act | BG6: Bgt. | BH6: Diff. | BJ6: Act | BK6: Bgt. | BL6: Diff. | BN6: Act | BO6: Bgt. | BP6: Diff. | BR6: YTD | BS6: Bgt. | BT6: Diff. | BV6: LTM
BB7: Q1 | BF7: Q2 | BJ7: Q3 | BN7: Q4
B8: New Leads Generated(1)
B9: Marketing Qualified Leads | C9: In-period | D9: =VLOOKUP($B$4&" "&$B9,Actuals!$D$4:$AG$131,3,FALSE) -> # | E9: {=_xlfn.XLOOKUP( $B$4&" "&$B9, Actuals!$D:$D, _xlfn.XLOOKUP( E$6, Actuals!$H$3:$BD$3, Actuals!$H:$BD ) )} -> 13 | F9: {=_xlfn.XLOOKUP( $B$4&" "&$B9, Actuals!$D:$D, _xlfn.XLOOKUP( F$6, Actuals!$H$3:$BD$3, Actuals!$H:$BD ) )} -> 2 | G9: {=_xlfn.XLOOKUP( $B$4&" "&$B9, Actuals!$D:$D, _xlfn.XLOOKUP( G$6, Actuals!$H$3:$BD$3, Actuals!$H:$BD ) )} -> 2 | H9: {=_xlfn.XLOOKUP( $B$4&" "&$B9, Actuals!$D:$D, _xlfn.XLOOKUP( H$6, Actuals!$H$3:$BD$3, Actuals!$H:$BD ) )} -> 0 | I9: {=_xlfn.XLOOKUP( $B$4&" "&$B9, Actuals!$D:$D, _xlfn.XLOOKUP( I$6, Actuals!$H$3:$BD$3, Actuals!$H:$BD ) )} -> 8 | J9: {=_xlfn.XLOOKUP( $B$4&" "&$B9, Actuals!$D:$D, _xlfn.XLOOKUP( J$6, Actuals!$H$3:$BD$3, Actuals!$H:$BD ) )} -> 20 | K9: {=_xlfn.XLOOKUP( $B$4&" "&$B9, Actuals!$D:$D, _xlfn.XLOOKUP( K$6, Actuals!$H$3:$BD$3, Actuals!$H:$BD ) )} -> 13 | L9: {=_xlfn.XLOOKUP( $B$4&" "&$B9, Actuals!$D:$D, _xlfn.XLOOKUP( L$6, Actuals!$H$3:$BD$3, Actuals!$H:$BD ) )} -> 0 | ... AZ9: {=_xlfn.XLOOKUP( $B$4&" "&$B9, Actuals!$D:$D, _xlfn.XLOOKUP( AZ$6, Actuals!$H$3:$BD$3, Actuals!$H:$BD ) )} -> 0 | BB9: {=_xlfn.XLOOKUP( $B$4&" "&$B9, Actuals!$D:$D, _xlfn.XLOOKUP( BB$7, Actuals!$H$3:$BM$3, Actuals!$H:$BM ) )} -> 0 | BC9: =VLOOKUP($B$4&" "&$B9,Budget!$AG$4:$AL$132,$BB$5+1,FALSE) -> 60 | BD9: =BB9-BC9 -> -60 | BF9: {=_xlfn.XLOOKUP( $B$4&" "&$B9, Actuals!$D:$D, _xlfn.XLOOKUP( BF$7, Actuals!$H$3:$BM$3, Actuals!$H:$BM ) )} -> 0 | BG9: =VLOOKUP($B$4&" "&$B9,Budget!$AG$4:$AL$132,BF$5+1,FALSE) -> 60 | BH9: =BF9-BG9 -> -60 | BJ9: {=_xlfn.XLOOKUP( $B$4&" "&$B9, Actuals!$D:$D, _xlfn.XLOOKUP( BJ$7, Actuals!$H$3:$BM$3, Actuals!$H:$BM ) )} -> 0 | BK9: =VLOOKUP($B$4&" "&$B9,Budget!$AG$4:$AL$132,BJ$5+1,FALSE) -> 60 | BL9: =BJ9-BK9 -> -60 | BN9: {=_xlfn.XLOOKUP( $B$4&" "&$B9, Actuals!$D:$D, _xlfn.XLOOKUP( BN$7, Actuals!$H$3:$BM$3, Actuals!$H:$BM ) )} -> 0 | BO9: =VLOOKUP($B$4&" "&$B9,Budget!$AG$4:$AL$132,BN$5+1,FALSE) -> 60 | BR9: {=_xlfn.XLOOKUP( $B$4&" "&$B9, Actuals!$D:$D, _xlfn.XLOOKUP( BR$6, Actuals!$H$3:$BM$3, Actuals!$H:$BM ) )} -> 0 | BS9: =VLOOKUP($B$4&" "&$B9,Budget!$AG$4:$AL$132,6,FALSE) -> 240 | BT9: =BR9-BS9 -> -240 | BV9: {=_xlfn.XLOOKUP( $B$4&" "&$B9, Actuals!$D:$D, _xlfn.XLOOKUP( BV$6, Actuals!$H$3:$BM$3, Actuals!$H:$BM ) )} -> 1868
B10: (x) MQL to New Opp. Conversion % | C10: In-period | D10: =VLOOKUP($B$4&" "&$B10,Actuals!$D$4:$AG$131,3,FALSE) -> % | E10: {=_xlfn.XLOOKUP( $B$4&" "&$B10, Actuals!$D:$D, _xlfn.XLOOKUP( E$6, Actuals!$H$3:$BD$3, Actuals!$H:$BD ) )} -> 0.38461538 | F10: {=_xlfn.XLOOKUP( $B$4&" "&$B10, Actuals!$D:$D, _xlfn.XLOOKUP( F$6, Actuals!$H$3:$BD$3, Actuals!$H:$BD ) )} -> 0.5 | G10: {=_xlfn.XLOOKUP( $B$4&" "&$B10, Actuals!$D:$D, _xlfn.XLOOKUP( G$6, Actuals!$H$3:$BD$3, Actuals!$H:$BD ) )} -> 1 | H10: {=_xlfn.XLOOKUP( $B$4&" "&$B10, Actuals!$D:$D, _xlfn.XLOOKUP( H$6, Actuals!$H$3:$BD$3, Actuals!$H:$BD ) )} | I10: {=_xlfn.XLOOKUP( $B$4&" "&$B10, Actuals!$D:$D, _xlfn.XLOOKUP( I$6, Actuals!$H$3:$BD$3, Actuals!$H:$BD ) )} -> 0.375 | J10: {=_xlfn.XLOOKUP( $B$4&" "&$B10, Actuals!$D:$D, _xlfn.XLOOKUP( J$6, Actuals!$H$3:$BD$3, Actuals!$H:$BD ) )} -> 0.35 | K10: {=_xlfn.XLOOKUP( $B$4&" "&$B10, Actuals!$D:$D, _xlfn.XLOOKUP( K$6, Actuals!$H$3:$BD$3, Actuals!$H:$BD ) )} -> 0.30769231 | L10: {=_xlfn.XLOOKUP( $B$4&" "&$B10, Actuals!$D:$D, _xlfn.XLOOKUP( L$6, Actuals!$H$3:$BD$3, Actuals!$H:$BD ) )} | ... AZ10: {=_xlfn.XLOOKUP( $B$4&" "&$B10, Actuals!$D:$D, _xlfn.XLOOKUP( AZ$6, Actuals!$H$3:$BD$3, Actuals!$H:$BD ) )} | BB10: {=_xlfn.XLOOKUP( $B$4&" "&$B10, Actuals!$D:$D, _xlfn.XLOOKUP( BB$7, Actuals!$H$3:$BM$3, Actuals!$H:$BM ) )} -> - | BC10: =VLOOKUP($B$4&" "&$B10,Budget!$AG$4:$AL$132,$BB$5+1,FALSE) -> 0.52 | BD10: =IFERROR(BB10-BC10,"-") -> - | BF10: {=_xlfn.XLOOKUP( $B$4&" "&$B10, Actuals!$D:$D, _xlfn.XLOOKUP( BF$7, Actuals!$H$3:$BM$3, Actuals!$H:$BM ) )} -> - | BG10: =IFERROR(VLOOKUP($B$4&" "&$B10,Budget!$AG$4:$AL$132,$BF$5+1,FALSE),"n.a.") -> 0.52 | BH10: =IFERROR(BF10-BG10,"-") -> - | BJ10: {=_xlfn.XLOOKUP( $B$4&" "&$B10, Actuals!$D:$D, _xlfn.XLOOKUP( BJ$7, Actuals!$H$3:$BM$3, Actuals!$H:$BM ) )} -> - | BK10: =IFERROR(VLOOKUP($B$4&" "&$B10,Budget!$AG$4:$AL$132,$BJ$5+1,FALSE),"n.a.") -> 0.52 | BL10: =IFERROR(BJ10-BK10,"-") -> - | BN10: {=_xlfn.XLOOKUP( $B$4&" "&$B10, Actuals!$D:$D, _xlfn.XLOOKUP( BN$7, Actuals!$H$3:$BM$3, Actuals!$H:$BM ) )} -> - | BO10: =IFERROR(VLOOKUP($B$4&" "&$B10,Budget!$AG$4:$AL$132,$BN$5+1,FALSE),"n.a.") -> 0.52 | BR10: {=_xlfn.XLOOKUP( $B$4&" "&$B10, Actuals!$D:$D, _xlfn.XLOOKUP( BR$6, Actuals!$H$3:$BM$3, Actuals!$H:$BM ) )} -> 0 | BS10: =VLOOKUP($B$4&" "&$B10,Budget!$AG$4:$AL$132,6,FALSE) -> 0.52 | BT10: =BR10-BS10 -> -0.52 | BV10: {=_xlfn.XLOOKUP( $B$4&" "&$B10, Actuals!$D:$D, _xlfn.XLOOKUP( BV$6, Actuals!$H$3:$BM$3, Actuals!$H:$BM ) )} -> 0.034803541
B11: = Mktg sourced New Opportunities | C11: In-period | D11: =VLOOKUP($B$4&" "&$B11,Actuals!$D$4:$AG$131,3,FALSE) -> # | E11: {=_xlfn.XLOOKUP( $B$4&" "&$B11, Actuals!$D:$D, _xlfn.XLOOKUP( E$6, Actuals!$H$3:$BD$3, Actuals!$H:$BD ) )} -> 5 | F11: {=_xlfn.XLOOKUP( $B$4&" "&$B11, Actuals!$D:$D, _xlfn.XLOOKUP( F$6, Actuals!$H$3:$BD$3, Actuals!$H:$BD ) )} -> 1 | G11: {=_xlfn.XLOOKUP( $B$4&" "&$B11, Actuals!$D:$D, _xlfn.XLOOKUP( G$6, Actuals!$H$3:$BD$3, Actuals!$H:$BD ) )} -> 2 | H11: {=_xlfn.XLOOKUP( $B$4&" "&$B11, Actuals!$D:$D, _xlfn.XLOOKUP( H$6, Actuals!$H$3:$BD$3, Actuals!$H:$BD ) )} -> 0 | I11: {=_xlfn.XLOOKUP( $B$4&" "&$B11, Actuals!$D:$D, _xlfn.XLOOKUP( I$6, Actuals!$H$3:$BD$3, Actuals!$H:$BD ) )} -> 3 | J11: {=_xlfn.XLOOKUP( $B$4&" "&$B11, Actuals!$D:$D, _xlfn.XLOOKUP( J$6, Actuals!$H$3:$BD$3, Actuals!$H:$BD ) )} -> 7 | K11: {=_xlfn.XLOOKUP( $B$4&" "&$B11, Actuals!$D:$D, _xlfn.XLOOKUP( K$6, Actuals!$H$3:$BD$3, Actuals!$H:$BD ) )} -> 4 | L11: {=_xlfn.XLOOKUP( $B$4&" "&$B11, Actuals!$D:$D, _xlfn.XLOOKUP( L$6, Actuals!$H$3:$BD$3, Actuals!$H:$BD ) )} -> 2 | ... AZ11: {=_xlfn.XLOOKUP( $B$4&" "&$B11, Actuals!$D:$D, _xlfn.XLOOKUP( AZ$6, Actuals!$H$3:$BD$3, Actuals!$H:$BD ) )} -> 0 | BB11: {=_xlfn.XLOOKUP( $B$4&" "&$B11, Actuals!$D:$D, _xlfn.XLOOKUP( BB$7, Actuals!$H$3:$BM$3, Actuals!$H:$BM ) )} -> 0 | BC11: =VLOOKUP($B$4&" "&$B11,Budget!$AG$4:$AL$132,$BB$5+1,FALSE) -> 31.2 | BD11: =BB11-BC11 -> -31.2 | BF11: {=_xlfn.XLOOKUP( $B$4&" "&$B11, Actuals!$D:$D, _xlfn.XLOOKUP( BF$7, Actuals!$H$3:$BM$3, Actuals!$H:$BM ) )} -> 0 | BG11: =VLOOKUP($B$4&" "&$B11,Budget!$AG$4:$AL$132,BF$5+1,FALSE) -> 31.2 | BH11: =BF11-BG11 -> -31.2 | BJ11: {=_xlfn.XLOOKUP( $B$4&" "&$B11, Actuals!$D:$D, _xlfn.XLOOKUP( BJ$7, Actuals!$H$3:$BM$3, Actuals!$H:$BM ) )} -> 0 | BK11: =VLOOKUP($B$4&" "&$B11,Budget!$AG$4:$AL$132,BJ$5+1,FALSE) -> 31.2 | BL11: =BJ11-BK11 -> -31.2 | BN11: {=_xlfn.XLOOKUP( $B$4&" "&$B11, Actuals!$D:$D, _xlfn.XLOOKUP( BN$7, Actuals!$H$3:$BM$3, Actuals!$H:$BM ) )} -> 0 | BO11: =VLOOKUP($B$4&" "&$B11,Budget!$AG$4:$AL$132,BN$5+1,FALSE) -> 31.2 | BR11: {=_xlfn.XLOOKUP( $B$4&" "&$B11, Actuals!$D:$D, _xlfn.XLOOKUP( BR$6, Actuals!$H$3:$BM$3, Actuals!$H:$BM ) )} -> 0 | BS11: =VLOOKUP($B$4&" "&$B11,Budget!$AG$4:$AL$132,6,FALSE) -> 124.8 | BT11: =BR11-BS11 -> -124.8 | BV11: {=_xlfn.XLOOKUP( $B$4&" "&$B11, Actuals!$D:$D, _xlfn.XLOOKUP( BV$6, Actuals!$H$3:$BM$3, Actuals!$H:$BM ) )} -> 48
B13: Effectiveness(1)
B14: Mktg sourced New Opportunities | C14: In-period | D14: =VLOOKUP($B$4&" "&$B14,Actuals!$D$4:$AG$131,3,FALSE) -> # | E14: {=_xlfn.XLOOKUP( $B$4&" "&$B14, Actuals!$D:$D, _xlfn.XLOOKUP( E$6, Actuals!$H$3:$BD$3, Actuals!$H:$BD ) )} -> 5 | F14: {=_xlfn.XLOOKUP( $B$4&" "&$B14, Actuals!$D:$D, _xlfn.XLOOKUP( F$6, Actuals!$H$3:$BD$3, Actuals!$H:$BD ) )} -> 1 | G14: {=_xlfn.XLOOKUP( $B$4&" "&$B14, Actuals!$D:$D, _xlfn.XLOOKUP( G$6, Actuals!$H$3:$BD$3, Actuals!$H:$BD ) )} -> 2 | H14: {=_xlfn.XLOOKUP( $B$4&" "&$B14, Actuals!$D:$D, _xlfn.XLOOKUP( H$6, Actuals!$H$3:$BD$3, Actuals!$H:$BD ) )} -> 0 | I14: {=_xlfn.XLOOKUP( $B$4&" "&$B14, Actuals!$D:$D, _xlfn.XLOOKUP( I$6, Actuals!$H$3:$BD$3, Actuals!$H:$BD ) )} -> 3 | J14: {=_xlfn.XLOOKUP( $B$4&" "&$B14, Actuals!$D:$D, _xlfn.XLOOKUP( J$6, Actuals!$H$3:$BD$3, Actuals!$H:$BD ) )} -> 7 | K14: {=_xlfn.XLOOKUP( $B$4&" "&$B14, Actuals!$D:$D, _xlfn.XLOOKUP( K$6, Actuals!$H$3:$BD$3, Actuals!$H:$BD ) )} -> 4 | L14: {=_xlfn.XLOOKUP( $B$4&" "&$B14, Actuals!$D:$D, _xlfn.XLOOKUP( L$6, Actuals!$H$3:$BD$3, Actuals!$H:$BD ) )} -> 2 | ... AZ14: {=_xlfn.XLOOKUP( $B$4&" "&$B14, Actuals!$D:$D, _xlfn.XLOOKUP( AZ$6, Actuals!$H$3:$BD$3, Actuals!$H:$BD ) )} -> 0 | BB14: {=_xlfn.XLOOKUP( $B$4&" "&$B14, Actuals!$D:$D, _xlfn.XLOOKUP( BB$7, Actuals!$H$3:$BM$3, Actuals!$H:$BM ) )} -> 0 | BC14: =VLOOKUP($B$4&" "&$B14,Budget!$AG$4:$AL$132,$BB$5+1,FALSE) -> 31.2 | BD14: =BB14-BC14 -> -31.2 | BF14: {=_xlfn.XLOOKUP( $B$4&" "&$B14, Actuals!$D:$D, _xlfn.XLOOKUP( BF$7, Actuals!$H$3:$BM$3, Actuals!$H:$BM ) )} -> 0 | BG14: =VLOOKUP($B$4&" "&$B14,Budget!$AG$4:$AL$132,BF$5+1,FALSE) -> 31.2 | BH14: =BF14-BG14 -> -31.2 | BJ14: {=_xlfn.XLOOKUP( $B$4&" "&$B14, Actuals!$D:$D, _xlfn.XLOOKUP( BJ$7, Actuals!$H$3:$BM$3, Actuals!$H:$BM ) )} -> 0 | BK14: =VLOOKUP($B$4&" "&$B14,Budget!$AG$4:$AL$132,BJ$5+1,FALSE) -> 31.2 | BL14: =BJ14-BK14 -> -31.2 | BN14: {=_xlfn.XLOOKUP( $B$4&" "&$B14, Actuals!$D:$D, _xlfn.XLOOKUP( BN$7, Actuals!$H$3:$BM$3, Actuals!$H:$BM ) )} -> 0 | BO14: =VLOOKUP($B$4&" "&$B14,Budget!$AG$4:$AL$132,BN$5+1,FALSE) -> 31.2 | BR14: {=_xlfn.XLOOKUP( $B$4&" "&$B14, Actuals!$D:$D, _xlfn.XLOOKUP( BR$6, Actuals!$H$3:$BM$3, Actuals!$H:$BM ) )} -> 0 | BS14: =VLOOKUP($B$4&" "&$B14,Budget!$AG$4:$AL$132,6,FALSE) -> 124.8 | BT14: =BR14-BS14 -> -124.8 | BV14: {=_xlfn.XLOOKUP( $B$4&" "&$B14, Actuals!$D:$D, _xlfn.XLOOKUP( BV$6, Actuals!$H$3:$BM$3, Actuals!$H:$BM ) )} -> 48
B15: (x) Mktg sourced New Opp. ACV | C15: In-period | D15: =VLOOKUP($B$4&" "&$B15,Actuals!$D$4:$AG$131,3,FALSE) -> $ | E15: {=_xlfn.XLOOKUP( $B$4&" "&$B15, Actuals!$D:$D, _xlfn.XLOOKUP( E$6, Actuals!$H$3:$BD$3, Actuals!$H:$BD ) )} -> 140000 | F15: {=_xlfn.XLOOKUP( $B$4&" "&$B15, Actuals!$D:$D, _xlfn.XLOOKUP( F$6, Actuals!$H$3:$BD$3, Actuals!$H:$BD ) )} -> 100000 | G15: {=_xlfn.XLOOKUP( $B$4&" "&$B15, Actuals!$D:$D, _xlfn.XLOOKUP( G$6, Actuals!$H$3:$BD$3, Actuals!$H:$BD ) )} -> 0 | H15: {=_xlfn.XLOOKUP( $B$4&" "&$B15, Actuals!$D:$D, _xlfn.XLOOKUP( H$6, Actuals!$H$3:$BD$3, Actuals!$H:$BD ) )} -> #DIV/0! | I15: {=_xlfn.XLOOKUP( $B$4&" "&$B15, Actuals!$D:$D, _xlfn.XLOOKUP( I$6, Actuals!$H$3:$BD$3, Actuals!$H:$BD ) )} -> 25000 | J15: {=_xlfn.XLOOKUP( $B$4&" "&$B15, Actuals!$D:$D, _xlfn.XLOOKUP( J$6, Actuals!$H$3:$BD$3, Actuals!$H:$BD ) )} -> 28571.429 | K15: {=_xlfn.XLOOKUP( $B$4&" "&$B15, Actuals!$D:$D, _xlfn.XLOOKUP( K$6, Actuals!$H$3:$BD$3, Actuals!$H:$BD ) )} -> 18750 | L15: {=_xlfn.XLOOKUP( $B$4&" "&$B15, Actuals!$D:$D, _xlfn.XLOOKUP( L$6, Actuals!$H$3:$BD$3, Actuals!$H:$BD ) )} -> 0 | ... AZ15: {=_xlfn.XLOOKUP( $B$4&" "&$B15, Actuals!$D:$D, _xlfn.XLOOKUP( AZ$6, Actuals!$H$3:$BD$3, Actuals!$H:$BD ) )} -> 0 | BB15: {=_xlfn.XLOOKUP( $B$4&" "&$B15, Actuals!$D:$D, _xlfn.XLOOKUP( BB$7, Actuals!$H$3:$BM$3, Actuals!$H:$BM ) )} -> - | BC15: =IFERROR(VLOOKUP($B$4&" "&$B15,Budget!$AG$4:$AL$132,$BB$5+1,FALSE),"n.a.") -> 75000 | BD15: =IFERROR(BB15-BC15,"-") -> - | BF15: {=_xlfn.XLOOKUP( $B$4&" "&$B15, Actuals!$D:$D, _xlfn.XLOOKUP( BF$7, Actuals!$H$3:$BM$3, Actuals!$H:$BM ) )} -> - | BG15: =IFERROR(VLOOKUP($B$4&" "&$B15,Budget!$AG$4:$AL$132,$BF$5+1,FALSE),"n.a.") -> 75000 | BH15: =IFERROR(BF15-BG15,"-") -> - | BJ15: {=_xlfn.XLOOKUP( $B$4&" "&$B15, Actuals!$D:$D, _xlfn.XLOOKUP( BJ$7, Actuals!$H$3:$BM$3, Actuals!$H:$BM ) )} -> - | BK15: =IFERROR(VLOOKUP($B$4&" "&$B15,Budget!$AG$4:$AL$132,$BJ$5+1,FALSE),"n.a.") -> 75000 | BL15: =IFERROR(BJ15-BK15,"-") -> - | BN15: {=_xlfn.XLOOKUP( $B$4&" "&$B15, Actuals!$D:$D, _xlfn.XLOOKUP( BN$7, Actuals!$H$3:$BM$3, Actuals!$H:$BM ) )} -> - | BO15: =IFERROR(VLOOKUP($B$4&" "&$B15,Budget!$AG$4:$AL$132,$BN$5+1,FALSE),"n.a.") -> 75000 | BR15: {=_xlfn.XLOOKUP( $B$4&" "&$B15, Actuals!$D:$D, _xlfn.XLOOKUP( BR$6, Actuals!$H$3:$BM$3, Actuals!$H:$BM ) )} -> 0 | BS15: =VLOOKUP($B$4&" "&$B15,Budget!$AG$4:$AL$132,6,FALSE) -> 75000 | BT15: =BR15-BS15 -> -75000 | BV15: {=_xlfn.XLOOKUP( $B$4&" "&$B15, Actuals!$D:$D, _xlfn.XLOOKUP( BV$6, Actuals!$H$3:$BM$3, Actuals!$H:$BM ) )} -> 68181.818
B16: = Mktg sourced New Opp. Value | C16: In-period | D16: =VLOOKUP($B$4&" "&$B16,Actuals!$D$4:$AG$131,3,FALSE) -> $ | E16: {=_xlfn.XLOOKUP( $B$4&" "&$B16, Actuals!$D:$D, _xlfn.XLOOKUP( E$6, Actuals!$H$3:$BD$3, Actuals!$H:$BD ) )} -> 700000 | F16: {=_xlfn.XLOOKUP( $B$4&" "&$B16, Actuals!$D:$D, _xlfn.XLOOKUP( F$6, Actuals!$H$3:$BD$3, Actuals!$H:$BD ) )} -> 100000 | G16: {=_xlfn.XLOOKUP( $B$4&" "&$B16, Actuals!$D:$D, _xlfn.XLOOKUP( G$6, Actuals!$H$3:$BD$3, Actuals!$H:$BD ) )} -> 0 | H16: {=_xlfn.XLOOKUP( $B$4&" "&$B16, Actuals!$D:$D, _xlfn.XLOOKUP( H$6, Actuals!$H$3:$BD$3, Actuals!$H:$BD ) )} -> 0 | I16: {=_xlfn.XLOOKUP( $B$4&" "&$B16, Actuals!$D:$D, _xlfn.XLOOKUP( I$6, Actuals!$H$3:$BD$3, Actuals!$H:$BD ) )} -> 75000 | J16: {=_xlfn.XLOOKUP( $B$4&" "&$B16, Actuals!$D:$D, _xlfn.XLOOKUP( J$6, Actuals!$H$3:$BD$3, Actuals!$H:$BD ) )} -> 200000 | K16: {=_xlfn.XLOOKUP( $B$4&" "&$B16, Actuals!$D:$D, _xlfn.XLOOKUP( K$6, Actuals!$H$3:$BD$3, Actuals!$H:$BD ) )} -> 75000 | L16: {=_xlfn.XLOOKUP( $B$4&" "&$B16, Actuals!$D:$D, _xlfn.XLOOKUP( L$6, Actuals!$H$3:$BD$3, Actuals!$H:$BD ) )} -> 0 | ... AZ16: {=_xlfn.XLOOKUP( $B$4&" "&$B16, Actuals!$D:$D, _xlfn.XLOOKUP( AZ$6, Actuals!$H$3:$BD$3, Actuals!$H:$BD ) )} -> 0 | BB16: {=_xlfn.XLOOKUP( $B$4&" "&$B16, Actuals!$D:$D, _xlfn.XLOOKUP( BB$7, Actuals!$H$3:$BM$3, Actuals!$H:$BM ) )} -> 0 | BC16: =VLOOKUP($B$4&" "&$B16,Budget!$AG$4:$AL$132,$BB$5+1,FALSE) -> 2340000 | BD16: =BB16-BC16 -> -2340000 | BF16: {=_xlfn.XLOOKUP( $B$4&" "&$B16, Actuals!$D:$D, _xlfn.XLOOKUP( BF$7, Actuals!$H$3:$BM$3, Actuals!$H:$BM ) )} -> 0 | BG16: =VLOOKUP($B$4&" "&$B16,Budget!$AG$4:$AL$132,BF$5+1,FALSE) -> 2340000 | BH16: =BF16-BG16 -> -2340000 | BJ16: {=_xlfn.XLOOKUP( $B$4&" "&$B16, Actuals!$D:$D, _xlfn.XLOOKUP( BJ$7, Actuals!$H$3:$BM$3, Actuals!$H:$BM ) )} -> 0 | BK16: =VLOOKUP($B$4&" "&$B16,Budget!$AG$4:$AL$132,BJ$5+1,FALSE) -> 2340000 | BL16: =BJ16-BK16 -> -2340000 | BN16: {=_xlfn.XLOOKUP( $B$4&" "&$B16, Actuals!$D:$D, _xlfn.XLOOKUP( BN$7, Actuals!$H$3:$BM$3, Actuals!$H:$BM ) )} -> 0 | BO16: =VLOOKUP($B$4&" "&$B16,Budget!$AG$4:$AL$132,BN$5+1,FALSE) -> 2340000 | BR16: {=_xlfn.XLOOKUP( $B$4&" "&$B16, Actuals!$D:$D, _xlfn.XLOOKUP( BR$6, Actuals!$H$3:$BM$3, Actuals!$H:$BM ) )} -> 0 | BS16: =VLOOKUP($B$4&" "&$B16,Budget!$AG$4:$AL$132,6,FALSE) -> 9360000 | BT16: =BR16-BS16 -> -9360000 | BV16: {=_xlfn.XLOOKUP( $B$4&" "&$B16, Actuals!$D:$D, _xlfn.XLOOKUP( BV$6, Actuals!$H$3:$BM$3, Actuals!$H:$BM ) )} -> 3450000
B17: (x) Expected Win Rate | C17: In-period | D17: =VLOOKUP($B$4&" "&$B17,Actuals!$D$4:$AG$131,3,FALSE) -> % | E17: {=_xlfn.XLOOKUP( $B$4&" "&$B17, Actuals!$D:$D, _xlfn.XLOOKUP( E$6, Actuals!$H$3:$BD$3, Actuals!$H:$BD ) )} -> 0.25 | F17: {=_xlfn.XLOOKUP( $B$4&" "&$B17, Actuals!$D:$D, _xlfn.XLOOKUP( F$6, Actuals!$H$3:$BD$3, Actuals!$H:$BD ) )} -> 0.25 | G17: {=_xlfn.XLOOKUP( $B$4&" "&$B17, Actuals!$D:$D, _xlfn.XLOOKUP( G$6, Actuals!$H$3:$BD$3, Actuals!$H:$BD ) )} -> 0.25 | H17: {=_xlfn.XLOOKUP( $B$4&" "&$B17, Actuals!$D:$D, _xlfn.XLOOKUP( H$6, Actuals!$H$3:$BD$3, Actuals!$H:$BD ) )} -> 0.25 | I17: {=_xlfn.XLOOKUP( $B$4&" "&$B17, Actuals!$D:$D, _xlfn.XLOOKUP( I$6, Actuals!$H$3:$BD$3, Actuals!$H:$BD ) )} -> 0.25 | J17: {=_xlfn.XLOOKUP( $B$4&" "&$B17, Actuals!$D:$D, _xlfn.XLOOKUP( J$6, Actuals!$H$3:$BD$3, Actuals!$H:$BD ) )} -> 0.25 | K17: {=_xlfn.XLOOKUP( $B$4&" "&$B17, Actuals!$D:$D, _xlfn.XLOOKUP( K$6, Actuals!$H$3:$BD$3, Actuals!$H:$BD ) )} -> 0.25 | L17: {=_xlfn.XLOOKUP( $B$4&" "&$B17, Actuals!$D:$D, _xlfn.XLOOKUP( L$6, Actuals!$H$3:$BD$3, Actuals!$H:$BD ) )} -> 0.25 | ... AZ17: {=_xlfn.XLOOKUP( $B$4&" "&$B17, Actuals!$D:$D, _xlfn.XLOOKUP( AZ$6, Actuals!$H$3:$BD$3, Actuals!$H:$BD ) )} -> 0 | BB17: {=_xlfn.XLOOKUP( $B$4&" "&$B17, Actuals!$D:$D, _xlfn.XLOOKUP( BB$7, Actuals!$H$3:$BM$3, Actuals!$H:$BM ) )} -> - | BC17: =IFERROR(VLOOKUP($B$4&" "&$B17,Budget!$AG$4:$AL$132,$BB$5+1,FALSE),"n.a.") -> 0.192 | BD17: =IFERROR(BB17-BC17,"-") -> - | BF17: {=_xlfn.XLOOKUP( $B$4&" "&$B17, Actuals!$D:$D, _xlfn.XLOOKUP( BF$7, Actuals!$H$3:$BM$3, Actuals!$H:$BM ) )} -> - | BG17: =IFERROR(VLOOKUP($B$4&" "&$B17,Budget!$AG$4:$AL$132,$BF$5+1,FALSE),"n.a.") -> 0.192 | BH17: =IFERROR(BF17-BG17,"-") -> - | BJ17: {=_xlfn.XLOOKUP( $B$4&" "&$B17, Actuals!$D:$D, _xlfn.XLOOKUP( BJ$7, Actuals!$H$3:$BM$3, Actuals!$H:$BM ) )} -> - | BK17: =IFERROR(VLOOKUP($B$4&" "&$B17,Budget!$AG$4:$AL$132,$BJ$5+1,FALSE),"n.a.") -> 0.192 | BL17: =IFERROR(BJ17-BK17,"-") -> - | BN17: {=_xlfn.XLOOKUP( $B$4&" "&$B17, Actuals!$D:$D, _xlfn.XLOOKUP( BN$7, Actuals!$H$3:$BM$3, Actuals!$H:$BM ) )} -> - | BO17: =IFERROR(VLOOKUP($B$4&" "&$B17,Budget!$AG$4:$AL$132,$BN$5+1,FALSE),"n.a.") -> 0.192 | BR17: {=_xlfn.XLOOKUP( $B$4&" "&$B17, Actuals!$D:$D, _xlfn.XLOOKUP( BR$6, Actuals!$H$3:$BM$3, Actuals!$H:$BM ) )} -> 0 | BS17: =VLOOKUP($B$4&" "&$B17,Budget!$AG$4:$AL$132,6,FALSE) -> 0.192 | BT17: =BR17-BS17 -> -0.192 | BV17: {=_xlfn.XLOOKUP( $B$4&" "&$B17, Actuals!$D:$D, _xlfn.XLOOKUP( BV$6, Actuals!$H$3:$BM$3, Actuals!$H:$BM ) )} -> 0.19727273
B18: = Expected Revenue of New Opp. | C18: In-period | D18: =VLOOKUP($B$4&" "&$B18,Actuals!$D$4:$AG$131,3,FALSE) -> $ | E18: {=_xlfn.XLOOKUP( $B$4&" "&$B18, Actuals!$D:$D, _xlfn.XLOOKUP( E$6, Actuals!$H$3:$BD$3, Actuals!$H:$BD ) )} -> 175000 | F18: {=_xlfn.XLOOKUP( $B$4&" "&$B18, Actuals!$D:$D, _xlfn.XLOOKUP( F$6, Actuals!$H$3:$BD$3, Actuals!$H:$BD ) )} -> 25000 | G18: {=_xlfn.XLOOKUP( $B$4&" "&$B18, Actuals!$D:$D, _xlfn.XLOOKUP( G$6, Actuals!$H$3:$BD$3, Actuals!$H:$BD ) )} -> 0 | H18: {=_xlfn.XLOOKUP( $B$4&" "&$B18, Actuals!$D:$D, _xlfn.XLOOKUP( H$6, Actuals!$H$3:$BD$3, Actuals!$H:$BD ) )} -> 0 | I18: {=_xlfn.XLOOKUP( $B$4&" "&$B18, Actuals!$D:$D, _xlfn.XLOOKUP( I$6, Actuals!$H$3:$BD$3, Actuals!$H:$BD ) )} -> 18750 | J18: {=_xlfn.XLOOKUP( $B$4&" "&$B18, Actuals!$D:$D, _xlfn.XLOOKUP( J$6, Actuals!$H$3:$BD$3, Actuals!$H:$BD ) )} -> 50000 | K18: {=_xlfn.XLOOKUP( $B$4&" "&$B18, Actuals!$D:$D, _xlfn.XLOOKUP( K$6, Actuals!$H$3:$BD$3, Actuals!$H:$BD ) )} -> 18750 | L18: {=_xlfn.XLOOKUP( $B$4&" "&$B18, Actuals!$D:$D, _xlfn.XLOOKUP( L$6, Actuals!$H$3:$BD$3, Actuals!$H:$BD ) )} -> 0 | ... AZ18: {=_xlfn.XLOOKUP( $B$4&" "&$B18, Actuals!$D:$D, _xlfn.XLOOKUP( AZ$6, Actuals!$H$3:$BD$3, Actuals!$H:$BD ) )} -> 0 | BB18: {=_xlfn.XLOOKUP( $B$4&" "&$B18, Actuals!$D:$D, _xlfn.XLOOKUP( BB$7, Actuals!$H$3:$BM$3, Actuals!$H:$BM ) )} -> 0 | BC18: =VLOOKUP($B$4&" "&$B18,Budget!$AG$4:$AL$132,$BB$5+1,FALSE) -> 449280 | BD18: =BB18-BC18 -> -449280 | BF18: {=_xlfn.XLOOKUP( $B$4&" "&$B18, Actuals!$D:$D, _xlfn.XLOOKUP( BF$7, Actuals!$H$3:$BM$3, Actuals!$H:$BM ) )} -> 0 | BG18: =VLOOKUP($B$4&" "&$B18,Budget!$AG$4:$AL$132,BF$5+1,FALSE) -> 449280 | BH18: =BF18-BG18 -> -449280 | BJ18: {=_xlfn.XLOOKUP( $B$4&" "&$B18, Actuals!$D:$D, _xlfn.XLOOKUP( BJ$7, Actuals!$H$3:$BM$3, Actuals!$H:$BM ) )} -> 0 | BK18: =VLOOKUP($B$4&" "&$B18,Budget!$AG$4:$AL$132,BJ$5+1,FALSE) -> 449280 | BL18: =BJ18-BK18 -> -449280 | BN18: {=_xlfn.XLOOKUP( $B$4&" "&$B18, Actuals!$D:$D, _xlfn.XLOOKUP( BN$7, Actuals!$H$3:$BM$3, Actuals!$H:$BM ) )} -> 0 | BO18: =VLOOKUP($B$4&" "&$B18,Budget!$AG$4:$AL$132,BN$5+1,FALSE) -> 449280 | BR18: {=_xlfn.XLOOKUP( $B$4&" "&$B18, Actuals!$D:$D, _xlfn.XLOOKUP( BR$6, Actuals!$H$3:$BM$3, Actuals!$H:$BM ) )} -> 0 | BS18: =VLOOKUP($B$4&" "&$B18,Budget!$AG$4:$AL$132,6,FALSE) -> 1797120 | BT18: =BR18-BS18 -> -1797120 | BV18: {=_xlfn.XLOOKUP( $B$4&" "&$B18, Actuals!$D:$D, _xlfn.XLOOKUP( BV$6, Actuals!$H$3:$BM$3, Actuals!$H:$BM ) )} -> 662400
B20: Pipeline & Revenue(1)
B21: Mktg sourced pipeline, EoP | C21: EoP | D21: =VLOOKUP($B$4&" "&$B21,Actuals!$D$4:$AG$131,3,FALSE) -> $ | E21: {=_xlfn.XLOOKUP( $B$4&" "&$B21, Actuals!$D:$D, _xlfn.XLOOKUP( E$6, Actuals!$H$3:$BD$3, Actuals!$H:$BD ) )} -> 2944783 | F21: {=_xlfn.XLOOKUP( $B$4&" "&$B21, Actuals!$D:$D, _xlfn.XLOOKUP( F$6, Actuals!$H$3:$BD$3, Actuals!$H:$BD ) )} -> 2272783 | G21: {=_xlfn.XLOOKUP( $B$4&" "&$B21, Actuals!$D:$D, _xlfn.XLOOKUP( G$6, Actuals!$H$3:$BD$3, Actuals!$H:$BD ) )} -> 820000 | H21: {=_xlfn.XLOOKUP( $B$4&" "&$B21, Actuals!$D:$D, _xlfn.XLOOKUP( H$6, Actuals!$H$3:$BD$3, Actuals!$H:$BD ) )} -> 700000 | I21: {=_xlfn.XLOOKUP( $B$4&" "&$B21, Actuals!$D:$D, _xlfn.XLOOKUP( I$6, Actuals!$H$3:$BD$3, Actuals!$H:$BD ) )} -> 700000 | J21: {=_xlfn.XLOOKUP( $B$4&" "&$B21, Actuals!$D:$D, _xlfn.XLOOKUP( J$6, Actuals!$H$3:$BD$3, Actuals!$H:$BD ) )} -> 766000 | K21: {=_xlfn.XLOOKUP( $B$4&" "&$B21, Actuals!$D:$D, _xlfn.XLOOKUP( K$6, Actuals!$H$3:$BD$3, Actuals!$H:$BD ) )} -> 918600 | L21: {=_xlfn.XLOOKUP( $B$4&" "&$B21, Actuals!$D:$D, _xlfn.XLOOKUP( L$6, Actuals!$H$3:$BD$3, Actuals!$H:$BD ) )} -> 703000 | ... AZ21: {=_xlfn.XLOOKUP( $B$4&" "&$B21, Actuals!$D:$D, _xlfn.XLOOKUP( AZ$6, Actuals!$H$3:$BD$3, Actuals!$H:$BD ) )} -> 0 | BB21: {=_xlfn.XLOOKUP( $B$4&" "&$B21, Actuals!$D:$D, _xlfn.XLOOKUP( BB$7, Actuals!$H$3:$BM$3, Actuals!$H:$BM ) )} -> 0 | BC21: =VLOOKUP($B$4&" "&$B21,Budget!$AG$4:$AL$132,$BB$5+1,FALSE) -> 0 | BD21: =BB21-BC21 -> 0 | BF21: {=_xlfn.XLOOKUP( $B$4&" "&$B21, Actuals!$D:$D, _xlfn.XLOOKUP( BF$7, Actuals!$H$3:$BM$3, Actuals!$H:$BM ) )} -> 0 | BG21: =VLOOKUP($B$4&" "&$B21,Budget!$AG$4:$AL$132,BF$5+1,FALSE) -> 0 | BH21: =BF21-BG21 -> 0 | BJ21: {=_xlfn.XLOOKUP( $B$4&" "&$B21, Actuals!$D:$D, _xlfn.XLOOKUP( BJ$7, Actuals!$H$3:$BM$3, Actuals!$H:$BM ) )} -> 0 | BK21: =VLOOKUP($B$4&" "&$B21,Budget!$AG$4:$AL$132,BJ$5+1,FALSE) -> 0 | BL21: =BJ21-BK21 -> 0 | BN21: {=_xlfn.XLOOKUP( $B$4&" "&$B21, Actuals!$D:$D, _xlfn.XLOOKUP( BN$7, Actuals!$H$3:$BM$3, Actuals!$H:$BM ) )} -> 0 | BO21: =VLOOKUP($B$4&" "&$B21,Budget!$AG$4:$AL$132,BN$5+1,FALSE) -> 0 | BR21: {=_xlfn.XLOOKUP( $B$4&" "&$B21, Actuals!$D:$D, _xlfn.XLOOKUP( BR$6, Actuals!$H$3:$BM$3, Actuals!$H:$BM ) )} -> 0 | BS21: =VLOOKUP($B$4&" "&$B21,Budget!$AG$4:$AL$132,6,FALSE) -> 0 | BT21: =BR21-BS21 -> 0 | BV21: {=_xlfn.XLOOKUP( $B$4&" "&$B21, Actuals!$D:$D, _xlfn.XLOOKUP( BV$6, Actuals!$H$3:$BM$3, Actuals!$H:$BM ) )} -> 0
B22: Mktg sourced Won ARR | C22: In-period | D22: =VLOOKUP($B$4&" "&$B22,Actuals!$D$4:$AG$131,3,FALSE) -> $ | E22: {=_xlfn.XLOOKUP( $B$4&" "&$B22, Actuals!$D:$D, _xlfn.XLOOKUP( E$6, Actuals!$H$3:$BD$3, Actuals!$H:$BD ) )} -> 49000 | F22: {=_xlfn.XLOOKUP( $B$4&" "&$B22, Actuals!$D:$D, _xlfn.XLOOKUP( F$6, Actuals!$H$3:$BD$3, Actuals!$H:$BD ) )} -> 0 | G22: {=_xlfn.XLOOKUP( $B$4&" "&$B22, Actuals!$D:$D, _xlfn.XLOOKUP( G$6, Actuals!$H$3:$BD$3, Actuals!$H:$BD ) )} -> 67000 | H22: {=_xlfn.XLOOKUP( $B$4&" "&$B22, Actuals!$D:$D, _xlfn.XLOOKUP( H$6, Actuals!$H$3:$BD$3, Actuals!$H:$BD ) )} -> 0 | I22: {=_xlfn.XLOOKUP( $B$4&" "&$B22, Actuals!$D:$D, _xlfn.XLOOKUP( I$6, Actuals!$H$3:$BD$3, Actuals!$H:$BD ) )} -> 0 | J22: {=_xlfn.XLOOKUP( $B$4&" "&$B22, Actuals!$D:$D, _xlfn.XLOOKUP( J$6, Actuals!$H$3:$BD$3, Actuals!$H:$BD ) )} -> 0 | K22: {=_xlfn.XLOOKUP( $B$4&" "&$B22, Actuals!$D:$D, _xlfn.XLOOKUP( K$6, Actuals!$H$3:$BD$3, Actuals!$H:$BD ) )} -> 0 | L22: {=_xlfn.XLOOKUP( $B$4&" "&$B22, Actuals!$D:$D, _xlfn.XLOOKUP( L$6, Actuals!$H$3:$BD$3, Actuals!$H:$BD ) )} -> 0 | ... AZ22: {=_xlfn.XLOOKUP( $B$4&" "&$B22, Actuals!$D:$D, _xlfn.XLOOKUP( AZ$6, Actuals!$H$3:$BD$3, Actuals!$H:$BD ) )} -> 0 | BB22: {=_xlfn.XLOOKUP( $B$4&" "&$B22, Actuals!$D:$D, _xlfn.XLOOKUP( BB$7, Actuals!$H$3:$BM$3, Actuals!$H:$BM ) )} -> 0 | BC22: =VLOOKUP($B$4&" "&$B22,Budget!$AG$4:$AL$132,$BB$5+1,FALSE) -> 320000 | BD22: =BB22-BC22 -> -320000 | BF22: {=_xlfn.XLOOKUP( $B$4&" "&$B22, Actuals!$D:$D, _xlfn.XLOOKUP( BF$7, Actuals!$H$3:$BM$3, Actuals!$H:$BM ) )} -> 0 | BG22: =VLOOKUP($B$4&" "&$B22,Budget!$AG$4:$AL$132,BF$5+1,FALSE) -> 450000 | BH22: =BF22-BG22 -> -450000 | BJ22: {=_xlfn.XLOOKUP( $B$4&" "&$B22, Actuals!$D:$D, _xlfn.XLOOKUP( BJ$7, Actuals!$H$3:$BM$3, Actuals!$H:$BM ) )} -> 0 | BK22: =VLOOKUP($B$4&" "&$B22,Budget!$AG$4:$AL$132,BJ$5+1,FALSE) -> 450000 | BL22: =BJ22-BK22 -> -450000 | BN22: {=_xlfn.XLOOKUP( $B$4&" "&$B22, Actuals!$D:$D, _xlfn.XLOOKUP( BN$7, Actuals!$H$3:$BM$3, Actuals!$H:$BM ) )} -> 0 | BO22: =VLOOKUP($B$4&" "&$B22,Budget!$AG$4:$AL$132,BN$5+1,FALSE) -> 580000 | BR22: {=_xlfn.XLOOKUP( $B$4&" "&$B22, Actuals!$D:$D, _xlfn.XLOOKUP( BR$6, Actuals!$H$3:$BM$3, Actuals!$H:$BM ) )} -> 0 | BS22: =VLOOKUP($B$4&" "&$B22,Budget!$AG$4:$AL$132,6,FALSE) -> 1800000 | BT22: =BR22-BS22 -> -1800000 | BV22: {=_xlfn.XLOOKUP( $B$4&" "&$B22, Actuals!$D:$D, _xlfn.XLOOKUP( BV$6, Actuals!$H$3:$BM$3, Actuals!$H:$BM ) )} -> 0
B24: Lead Generation (MQLs)
B25: Leads - Digital (Paid) | C25: In-period | D25: =VLOOKUP($B$4&" "&$B25,Actuals!$D$4:$AG$131,3,FALSE) -> # | E25: {=_xlfn.XLOOKUP( $B$4&" "&$B25, Actuals!$D:$D, _xlfn.XLOOKUP( E$6, Actuals!$H$3:$BD$3, Actuals!$H:$BD ) )} -> 0 | F25: {=_xlfn.XLOOKUP( $B$4&" "&$B25, Actuals!$D:$D, _xlfn.XLOOKUP( F$6, Actuals!$H$3:$BD$3, Actuals!$H:$BD ) )} -> 0 | G25: {=_xlfn.XLOOKUP( $B$4&" "&$B25, Actuals!$D:$D, _xlfn.XLOOKUP( G$6, Actuals!$H$3:$BD$3, Actuals!$H:$BD ) )} -> 0 | H25: {=_xlfn.XLOOKUP( $B$4&" "&$B25, Actuals!$D:$D, _xlfn.XLOOKUP( H$6, Actuals!$H$3:$BD$3, Actuals!$H:$BD ) )} -> 0 | I25: {=_xlfn.XLOOKUP( $B$4&" "&$B25, Actuals!$D:$D, _xlfn.XLOOKUP( I$6, Actuals!$H$3:$BD$3, Actuals!$H:$BD ) )} -> 0 | J25: {=_xlfn.XLOOKUP( $B$4&" "&$B25, Actuals!$D:$D, _xlfn.XLOOKUP( J$6, Actuals!$H$3:$BD$3, Actuals!$H:$BD ) )} -> 0 | K25: {=_xlfn.XLOOKUP( $B$4&" "&$B25, Actuals!$D:$D, _xlfn.XLOOKUP( K$6, Actuals!$H$3:$BD$3, Actuals!$H:$BD ) )} -> 0 | L25: {=_xlfn.XLOOKUP( $B$4&" "&$B25, Actuals!$D:$D, _xlfn.XLOOKUP( L$6, Actuals!$H$3:$BD$3, Actuals!$H:$BD ) )} -> 0 | ... AZ25: {=_xlfn.XLOOKUP( $B$4&" "&$B25, Actuals!$D:$D, _xlfn.XLOOKUP( AZ$6, Actuals!$H$3:$BD$3, Actuals!$H:$BD ) )} -> 0 | BB25: {=_xlfn.XLOOKUP( $B$4&" "&$B25, Actuals!$D:$D, _xlfn.XLOOKUP( BB$7, Actuals!$H$3:$BM$3, Actuals!$H:$BM ) )} -> 0 | BC25: =VLOOKUP($B$4&" "&$B25,Budget!$AG$4:$AL$132,$BB$5+1,FALSE) -> 7.5 | BD25: =BB25-BC25 -> -7.5 | BF25: {=_xlfn.XLOOKUP( $B$4&" "&$B25, Actuals!$D:$D, _xlfn.XLOOKUP( BF$7, Actuals!$H$3:$BM$3, Actuals!$H:$BM ) )} -> 0 | BG25: =VLOOKUP($B$4&" "&$B25,Budget!$AG$4:$AL$132,BF$5+1,FALSE) -> 7.5 | BH25: =BF25-BG25 -> -7.5 | BJ25: {=_xlfn.XLOOKUP( $B$4&" "&$B25, Actuals!$D:$D, _xlfn.XLOOKUP( BJ$7, Actuals!$H$3:$BM$3, Actuals!$H:$BM ) )} -> 0 | BK25: =VLOOKUP($B$4&" "&$B25,Budget!$AG$4:$AL$132,BJ$5+1,FALSE) -> 7.5 | BL25: =BJ25-BK25 -> -7.5 | BN25: {=_xlfn.XLOOKUP( $B$4&" "&$B25, Actuals!$D:$D, _xlfn.XLOOKUP( BN$7, Actuals!$H$3:$BM$3, Actuals!$H:$BM ) )} -> 0 | BO25: =VLOOKUP($B$4&" "&$B25,Budget!$AG$4:$AL$132,BN$5+1,FALSE) -> 7.5 | BR25: {=_xlfn.XLOOKUP( $B$4&" "&$B25, Actuals!$D:$D, _xlfn.XLOOKUP( BR$6, Actuals!$H$3:$BM$3, Actuals!$H:$BM ) )} -> 0 | BS25: =VLOOKUP($B$4&" "&$B25,Budget!$AG$4:$AL$132,6,FALSE) -> 30 | BT25: =BR25-BS25 -> -30 | BV25: {=_xlfn.XLOOKUP( $B$4&" "&$B25, Actuals!$D:$D, _xlfn.XLOOKUP( BV$6, Actuals!$H$3:$BM$3, Actuals!$H:$BM ) )} -> 4
B26: Leads - Digital (Organic) | C26: In-period | D26: =VLOOKUP($B$4&" "&$B26,Actuals!$D$4:$AG$131,3,FALSE) -> # | E26: {=_xlfn.XLOOKUP( $B$4&" "&$B26, Actuals!$D:$D, _xlfn.XLOOKUP( E$6, Actuals!$H$3:$BD$3, Actuals!$H:$BD ) )} -> 0 | F26: {=_xlfn.XLOOKUP( $B$4&" "&$B26, Actuals!$D:$D, _xlfn.XLOOKUP( F$6, Actuals!$H$3:$BD$3, Actuals!$H:$BD ) )} -> 0 | G26: {=_xlfn.XLOOKUP( $B$4&" "&$B26, Actuals!$D:$D, _xlfn.XLOOKUP( G$6, Actuals!$H$3:$BD$3, Actuals!$H:$BD ) )} -> 0 | H26: {=_xlfn.XLOOKUP( $B$4&" "&$B26, Actuals!$D:$D, _xlfn.XLOOKUP( H$6, Actuals!$H$3:$BD$3, Actuals!$H:$BD ) )} -> 0 | I26: {=_xlfn.XLOOKUP( $B$4&" "&$B26, Actuals!$D:$D, _xlfn.XLOOKUP( I$6, Actuals!$H$3:$BD$3, Actuals!$H:$BD ) )} -> 0 | J26: {=_xlfn.XLOOKUP( $B$4&" "&$B26, Actuals!$D:$D, _xlfn.XLOOKUP( J$6, Actuals!$H$3:$BD$3, Actuals!$H:$BD ) )} -> 0 | K26: {=_xlfn.XLOOKUP( $B$4&" "&$B26, Actuals!$D:$D, _xlfn.XLOOKUP( K$6, Actuals!$H$3:$BD$3, Actuals!$H:$BD ) )} -> 0 | L26: {=_xlfn.XLOOKUP( $B$4&" "&$B26, Actuals!$D:$D, _xlfn.XLOOKUP( L$6, Actuals!$H$3:$BD$3, Actuals!$H:$BD ) )} -> 0 | ... AZ26: {=_xlfn.XLOOKUP( $B$4&" "&$B26, Actuals!$D:$D, _xlfn.XLOOKUP( AZ$6, Actuals!$H$3:$BD$3, Actuals!$H:$BD ) )} -> 0 | BB26: {=_xlfn.XLOOKUP( $B$4&" "&$B26, Actuals!$D:$D, _xlfn.XLOOKUP( BB$7, Actuals!$H$3:$BM$3, Actuals!$H:$BM ) )} -> 0 | BC26: =VLOOKUP($B$4&" "&$B26,Budget!$AG$4:$AL$132,$BB$5+1,FALSE) -> 7.5 | BD26: =BB26-BC26 -> -7.5 | BF26: {=_xlfn.XLOOKUP( $B$4&" "&$B26, Actuals!$D:$D, _xlfn.XLOOKUP( BF$7, Actuals!$H$3:$BM$3, Actuals!$H:$BM ) )} -> 0 | BG26: =VLOOKUP($B$4&" "&$B26,Budget!$AG$4:$AL$132,BF$5+1,FALSE) -> 7.5 | BH26: =BF26-BG26 -> -7.5 | BJ26: {=_xlfn.XLOOKUP( $B$4&" "&$B26, Actuals!$D:$D, _xlfn.XLOOKUP( BJ$7, Actuals!$H$3:$BM$3, Actuals!$H:$BM ) )} -> 0 | BK26: =VLOOKUP($B$4&" "&$B26,Budget!$AG$4:$AL$132,BJ$5+1,FALSE) -> 7.5 | BL26: =BJ26-BK26 -> -7.5 | BN26: {=_xlfn.XLOOKUP( $B$4&" "&$B26, Actuals!$D:$D, _xlfn.XLOOKUP( BN$7, Actuals!$H$3:$BM$3, Actuals!$H:$BM ) )} -> 0 | BO26: =VLOOKUP($B$4&" "&$B26,Budget!$AG$4:$AL$132,BN$5+1,FALSE) -> 7.5 | BR26: {=_xlfn.XLOOKUP( $B$4&" "&$B26, Actuals!$D:$D, _xlfn.XLOOKUP( BR$6, Actuals!$H$3:$BM$3, Actuals!$H:$BM ) )} -> 0 | BS26: =VLOOKUP($B$4&" "&$B26,Budget!$AG$4:$AL$132,6,FALSE) -> 30 | BT26: =BR26-BS26 -> -30 | BV26: {=_xlfn.XLOOKUP( $B$4&" "&$B26, Actuals!$D:$D, _xlfn.XLOOKUP( BV$6, Actuals!$H$3:$BM$3, Actuals!$H:$BM ) )} -> 5
B27: Leads - Events / Conferences | C27: In-period | D27: =VLOOKUP($B$4&" "&$B27,Actuals!$D$4:$AG$131,3,FALSE) -> # | E27: {=_xlfn.XLOOKUP( $B$4&" "&$B27, Actuals!$D:$D, _xlfn.XLOOKUP( E$6, Actuals!$H$3:$BD$3, Actuals!$H:$BD ) )} -> 0 | F27: {=_xlfn.XLOOKUP( $B$4&" "&$B27, Actuals!$D:$D, _xlfn.XLOOKUP( F$6, Actuals!$H$3:$BD$3, Actuals!$H:$BD ) )} -> 0 | G27: {=_xlfn.XLOOKUP( $B$4&" "&$B27, Actuals!$D:$D, _xlfn.XLOOKUP( G$6, Actuals!$H$3:$BD$3, Actuals!$H:$BD ) )} -> 0 | H27: {=_xlfn.XLOOKUP( $B$4&" "&$B27, Actuals!$D:$D, _xlfn.XLOOKUP( H$6, Actuals!$H$3:$BD$3, Actuals!$H:$BD ) )} -> 0 | I27: {=_xlfn.XLOOKUP( $B$4&" "&$B27, Actuals!$D:$D, _xlfn.XLOOKUP( I$6, Actuals!$H$3:$BD$3, Actuals!$H:$BD ) )} -> 0 | J27: {=_xlfn.XLOOKUP( $B$4&" "&$B27, Actuals!$D:$D, _xlfn.XLOOKUP( J$6, Actuals!$H$3:$BD$3, Actuals!$H:$BD ) )} -> 0 | K27: {=_xlfn.XLOOKUP( $B$4&" "&$B27, Actuals!$D:$D, _xlfn.XLOOKUP( K$6, Actuals!$H$3:$BD$3, Actuals!$H:$BD ) )} -> 0 | L27: {=_xlfn.XLOOKUP( $B$4&" "&$B27, Actuals!$D:$D, _xlfn.XLOOKUP( L$6, Actuals!$H$3:$BD$3, Actuals!$H:$BD ) )} -> 0 | ... AZ27: {=_xlfn.XLOOKUP( $B$4&" "&$B27, Actuals!$D:$D, _xlfn.XLOOKUP( AZ$6, Actuals!$H$3:$BD$3, Actuals!$H:$BD ) )} -> 0 | BB27: {=_xlfn.XLOOKUP( $B$4&" "&$B27, Actuals!$D:$D, _xlfn.XLOOKUP( BB$7, Actuals!$H$3:$BM$3, Actuals!$H:$BM ) )} -> 0 | BC27: =VLOOKUP($B$4&" "&$B27,Budget!$AG$4:$AL$132,$BB$5+1,FALSE) -> 15 | BD27: =BB27-BC27 -> -15 | BF27: {=_xlfn.XLOOKUP( $B$4&" "&$B27, Actuals!$D:$D, _xlfn.XLOOKUP( BF$7, Actuals!$H$3:$BM$3, Actuals!$H:$BM ) )} -> 0 | BG27: =VLOOKUP($B$4&" "&$B27,Budget!$AG$4:$AL$132,BF$5+1,FALSE) -> 15 | BH27: =BF27-BG27 -> -15 | BJ27: {=_xlfn.XLOOKUP( $B$4&" "&$B27, Actuals!$D:$D, _xlfn.XLOOKUP( BJ$7, Actuals!$H$3:$BM$3, Actuals!$H:$BM ) )} -> 0 | BK27: =VLOOKUP($B$4&" "&$B27,Budget!$AG$4:$AL$132,BJ$5+1,FALSE) -> 15 | BL27: =BJ27-BK27 -> -15 | BN27: {=_xlfn.XLOOKUP( $B$4&" "&$B27, Actuals!$D:$D, _xlfn.XLOOKUP( BN$7, Actuals!$H$3:$BM$3, Actuals!$H:$BM ) )} -> 0 | BO27: =VLOOKUP($B$4&" "&$B27,Budget!$AG$4:$AL$132,BN$5+1,FALSE) -> 15 | BR27: {=_xlfn.XLOOKUP( $B$4&" "&$B27, Actuals!$D:$D, _xlfn.XLOOKUP( BR$6, Actuals!$H$3:$BM$3, Actuals!$H:$BM ) )} -> 0 | BS27: =VLOOKUP($B$4&" "&$B27,Budget!$AG$4:$AL$132,6,FALSE) -> 60 | BT27: =BR27-BS27 -> -60 | BV27: {=_xlfn.XLOOKUP( $B$4&" "&$B27, Actuals!$D:$D, _xlfn.XLOOKUP( BV$6, Actuals!$H$3:$BM$3, Actuals!$H:$BM ) )} -> 26
B28: Leads - Outbound (BDR) | C28: In-period | D28: =VLOOKUP($B$4&" "&$B28,Actuals!$D$4:$AG$131,3,FALSE) -> # | E28: {=_xlfn.XLOOKUP( $B$4&" "&$B28, Actuals!$D:$D, _xlfn.XLOOKUP( E$6, Actuals!$H$3:$BD$3, Actuals!$H:$BD ) )} -> 0 | F28: {=_xlfn.XLOOKUP( $B$4&" "&$B28, Actuals!$D:$D, _xlfn.XLOOKUP( F$6, Actuals!$H$3:$BD$3, Actuals!$H:$BD ) )} -> 0 | G28: {=_xlfn.XLOOKUP( $B$4&" "&$B28, Actuals!$D:$D, _xlfn.XLOOKUP( G$6, Actuals!$H$3:$BD$3, Actuals!$H:$BD ) )} -> 0 | H28: {=_xlfn.XLOOKUP( $B$4&" "&$B28, Actuals!$D:$D, _xlfn.XLOOKUP( H$6, Actuals!$H$3:$BD$3, Actuals!$H:$BD ) )} -> 0 | I28: {=_xlfn.XLOOKUP( $B$4&" "&$B28, Actuals!$D:$D, _xlfn.XLOOKUP( I$6, Actuals!$H$3:$BD$3, Actuals!$H:$BD ) )} -> 0 | J28: {=_xlfn.XLOOKUP( $B$4&" "&$B28, Actuals!$D:$D, _xlfn.XLOOKUP( J$6, Actuals!$H$3:$BD$3, Actuals!$H:$BD ) )} -> 0 | K28: {=_xlfn.XLOOKUP( $B$4&" "&$B28, Actuals!$D:$D, _xlfn.XLOOKUP( K$6, Actuals!$H$3:$BD$3, Actuals!$H:$BD ) )} -> 0 | L28: {=_xlfn.XLOOKUP( $B$4&" "&$B28, Actuals!$D:$D, _xlfn.XLOOKUP( L$6, Actuals!$H$3:$BD$3, Actuals!$H:$BD ) )} -> 0 | ... AZ28: {=_xlfn.XLOOKUP( $B$4&" "&$B28, Actuals!$D:$D, _xlfn.XLOOKUP( AZ$6, Actuals!$H$3:$BD$3, Actuals!$H:$BD ) )} -> 0 | BB28: {=_xlfn.XLOOKUP( $B$4&" "&$B28, Actuals!$D:$D, _xlfn.XLOOKUP( BB$7, Actuals!$H$3:$BM$3, Actuals!$H:$BM ) )} -> 0 | BC28: =VLOOKUP($B$4&" "&$B28,Budget!$AG$4:$AL$132,$BB$5+1,FALSE) -> 30 | BD28: =BB28-BC28 -> -30 | BF28: {=_xlfn.XLOOKUP( $B$4&" "&$B28, Actuals!$D:$D, _xlfn.XLOOKUP( BF$7, Actuals!$H$3:$BM$3, Actuals!$H:$BM ) )} -> 0 | BG28: =VLOOKUP($B$4&" "&$B28,Budget!$AG$4:$AL$132,BF$5+1,FALSE) -> 30 | BH28: =BF28-BG28 -> -30 | BJ28: {=_xlfn.XLOOKUP( $B$4&" "&$B28, Actuals!$D:$D, _xlfn.XLOOKUP( BJ$7, Actuals!$H$3:$BM$3, Actuals!$H:$BM ) )} -> 0 | BK28: =VLOOKUP($B$4&" "&$B28,Budget!$AG$4:$AL$132,BJ$5+1,FALSE) -> 30 | BL28: =BJ28-BK28 -> -30 | BN28: {=_xlfn.XLOOKUP( $B$4&" "&$B28, Actuals!$D:$D, _xlfn.XLOOKUP( BN$7, Actuals!$H$3:$BM$3, Actuals!$H:$BM ) )} -> 0 | BO28: =VLOOKUP($B$4&" "&$B28,Budget!$AG$4:$AL$132,BN$5+1,FALSE) -> 30 | BR28: {=_xlfn.XLOOKUP( $B$4&" "&$B28, Actuals!$D:$D, _xlfn.XLOOKUP( BR$6, Actuals!$H$3:$BM$3, Actuals!$H:$BM ) )} -> 0 | BS28: =VLOOKUP($B$4&" "&$B28,Budget!$AG$4:$AL$132,6,FALSE) -> 120 | BT28: =BR28-BS28 -> -120 | BV28: {=_xlfn.XLOOKUP( $B$4&" "&$B28, Actuals!$D:$D, _xlfn.XLOOKUP( BV$6, Actuals!$H$3:$BM$3, Actuals!$H:$BM ) )} -> 0
B29: Leads - Other | C29: In-period | D29: =VLOOKUP($B$4&" "&$B29,Actuals!$D$4:$AG$131,3,FALSE) -> # | E29: {=_xlfn.XLOOKUP( $B$4&" "&$B29, Actuals!$D:$D, _xlfn.XLOOKUP( E$6, Actuals!$H$3:$BD$3, Actuals!$H:$BD ) )} -> 0 | F29: {=_xlfn.XLOOKUP( $B$4&" "&$B29, Actuals!$D:$D, _xlfn.XLOOKUP( F$6, Actuals!$H$3:$BD$3, Actuals!$H:$BD ) )} -> 0 | G29: {=_xlfn.XLOOKUP( $B$4&" "&$B29, Actuals!$D:$D, _xlfn.XLOOKUP( G$6, Actuals!$H$3:$BD$3, Actuals!$H:$BD ) )} -> 0 | H29: {=_xlfn.XLOOKUP( $B$4&" "&$B29, Actuals!$D:$D, _xlfn.XLOOKUP( H$6, Actuals!$H$3:$BD$3, Actuals!$H:$BD ) )} -> 0 | I29: {=_xlfn.XLOOKUP( $B$4&" "&$B29, Actuals!$D:$D, _xlfn.XLOOKUP( I$6, Actuals!$H$3:$BD$3, Actuals!$H:$BD ) )} -> 0 | J29: {=_xlfn.XLOOKUP( $B$4&" "&$B29, Actuals!$D:$D, _xlfn.XLOOKUP( J$6, Actuals!$H$3:$BD$3, Actuals!$H:$BD ) )} -> 0 | K29: {=_xlfn.XLOOKUP( $B$4&" "&$B29, Actuals!$D:$D, _xlfn.XLOOKUP( K$6, Actuals!$H$3:$BD$3, Actuals!$H:$BD ) )} -> 0 | L29: {=_xlfn.XLOOKUP( $B$4&" "&$B29, Actuals!$D:$D, _xlfn.XLOOKUP( L$6, Actuals!$H$3:$BD$3, Actuals!$H:$BD ) )} -> 0 | ... AZ29: {=_xlfn.XLOOKUP( $B$4&" "&$B29, Actuals!$D:$D, _xlfn.XLOOKUP( AZ$6, Actuals!$H$3:$BD$3, Actuals!$H:$BD ) )} -> 0 | BB29: {=_xlfn.XLOOKUP( $B$4&" "&$B29, Actuals!$D:$D, _xlfn.XLOOKUP( BB$7, Actuals!$H$3:$BM$3, Actuals!$H:$BM ) )} -> 0 | BC29: =VLOOKUP($B$4&" "&$B29,Budget!$AG$4:$AL$132,$BB$5+1,FALSE) -> 0 | BD29: =BB29-BC29 -> 0 | BF29: {=_xlfn.XLOOKUP( $B$4&" "&$B29, Actuals!$D:$D, _xlfn.XLOOKUP( BF$7, Actuals!$H$3:$BM$3, Actuals!$H:$BM ) )} -> 0 | BG29: =VLOOKUP($B$4&" "&$B29,Budget!$AG$4:$AL$132,BF$5+1,FALSE) -> 0 | BH29: =BF29-BG29 -> 0 | BJ29: {=_xlfn.XLOOKUP( $B$4&" "&$B29, Actuals!$D:$D, _xlfn.XLOOKUP( BJ$7, Actuals!$H$3:$BM$3, Actuals!$H:$BM ) )} -> 0 | BK29: =VLOOKUP($B$4&" "&$B29,Budget!$AG$4:$AL$132,BJ$5+1,FALSE) -> 0 | BL29: =BJ29-BK29 -> 0 | BN29: {=_xlfn.XLOOKUP( $B$4&" "&$B29, Actuals!$D:$D, _xlfn.XLOOKUP( BN$7, Actuals!$H$3:$BM$3, Actuals!$H:$BM ) )} -> 0 | BO29: =VLOOKUP($B$4&" "&$B29,Budget!$AG$4:$AL$132,BN$5+1,FALSE) -> 0 | BR29: {=_xlfn.XLOOKUP( $B$4&" "&$B29, Actuals!$D:$D, _xlfn.XLOOKUP( BR$6, Actuals!$H$3:$BM$3, Actuals!$H:$BM ) )} -> 0 | BS29: =VLOOKUP($B$4&" "&$B29,Budget!$AG$4:$AL$132,6,FALSE) -> 0 | BT29: =BR29-BS29 -> 0 | BV29: {=_xlfn.XLOOKUP( $B$4&" "&$B29, Actuals!$D:$D, _xlfn.XLOOKUP( BV$6, Actuals!$H$3:$BM$3, Actuals!$H:$BM ) )} -> 13
B30: Spend - Digital (Paid) | C30: In-period | D30: =VLOOKUP($B$4&" "&$B30,Actuals!$D$4:$AG$131,3,FALSE) -> $ | E30: {=_xlfn.XLOOKUP( $B$4&" "&$B30, Actuals!$D:$D, _xlfn.XLOOKUP( E$6, Actuals!$H$3:$BD$3, Actuals!$H:$BD ) )} -> 0 | F30: {=_xlfn.XLOOKUP( $B$4&" "&$B30, Actuals!$D:$D, _xlfn.XLOOKUP( F$6, Actuals!$H$3:$BD$3, Actuals!$H:$BD ) )} -> 0 | G30: {=_xlfn.XLOOKUP( $B$4&" "&$B30, Actuals!$D:$D, _xlfn.XLOOKUP( G$6, Actuals!$H$3:$BD$3, Actuals!$H:$BD ) )} -> 0 | H30: {=_xlfn.XLOOKUP( $B$4&" "&$B30, Actuals!$D:$D, _xlfn.XLOOKUP( H$6, Actuals!$H$3:$BD$3, Actuals!$H:$BD ) )} -> 0 | I30: {=_xlfn.XLOOKUP( $B$4&" "&$B30, Actuals!$D:$D, _xlfn.XLOOKUP( I$6, Actuals!$H$3:$BD$3, Actuals!$H:$BD ) )} -> 0 | J30: {=_xlfn.XLOOKUP( $B$4&" "&$B30, Actuals!$D:$D, _xlfn.XLOOKUP( J$6, Actuals!$H$3:$BD$3, Actuals!$H:$BD ) )} -> 0 | K30: {=_xlfn.XLOOKUP( $B$4&" "&$B30, Actuals!$D:$D, _xlfn.XLOOKUP( K$6, Actuals!$H$3:$BD$3, Actuals!$H:$BD ) )} -> 0 | L30: {=_xlfn.XLOOKUP( $B$4&" "&$B30, Actuals!$D:$D, _xlfn.XLOOKUP( L$6, Actuals!$H$3:$BD$3, Actuals!$H:$BD ) )} -> 0 | ... AZ30: {=_xlfn.XLOOKUP( $B$4&" "&$B30, Actuals!$D:$D, _xlfn.XLOOKUP( AZ$6, Actuals!$H$3:$BD$3, Actuals!$H:$BD ) )} -> 0 | BB30: {=_xlfn.XLOOKUP( $B$4&" "&$B30, Actuals!$D:$D, _xlfn.XLOOKUP( BB$7, Actuals!$H$3:$BM$3, Actuals!$H:$BM ) )} -> 0 | BC30: =VLOOKUP($B$4&" "&$B30,Budget!$AG$4:$AL$132,$BB$5+1,FALSE) -> 15000 | BD30: =BB30-BC30 -> -15000 | BF30: {=_xlfn.XLOOKUP( $B$4&" "&$B30, Actuals!$D:$D, _xlfn.XLOOKUP( BF$7, Actuals!$H$3:$BM$3, Actuals!$H:$BM ) )} -> 0 | BG30: =VLOOKUP($B$4&" "&$B30,Budget!$AG$4:$AL$132,BF$5+1,FALSE) -> 15000 | BH30: =BF30-BG30 -> -15000 | BJ30: {=_xlfn.XLOOKUP( $B$4&" "&$B30, Actuals!$D:$D, _xlfn.XLOOKUP( BJ$7, Actuals!$H$3:$BM$3, Actuals!$H:$BM ) )} -> 0 | BK30: =VLOOKUP($B$4&" "&$B30,Budget!$AG$4:$AL$132,BJ$5+1,FALSE) -> 15000 | BL30: =BJ30-BK30 -> -15000 | BN30: {=_xlfn.XLOOKUP( $B$4&" "&$B30, Actuals!$D:$D, _xlfn.XLOOKUP( BN$7, Actuals!$H$3:$BM$3, Actuals!$H:$BM ) )} -> 0 | BO30: =VLOOKUP($B$4&" "&$B30,Budget!$AG$4:$AL$132,BN$5+1,FALSE) -> 15000 | BR30: {=_xlfn.XLOOKUP( $B$4&" "&$B30, Actuals!$D:$D, _xlfn.XLOOKUP( BR$6, Actuals!$H$3:$BM$3, Actuals!$H:$BM ) )} -> 0 | BS30: =VLOOKUP($B$4&" "&$B30,Budget!$AG$4:$AL$132,6,FALSE) -> 60000 | BT30: =BR30-BS30 -> -60000 | BV30: {=_xlfn.XLOOKUP( $B$4&" "&$B30, Actuals!$D:$D, _xlfn.XLOOKUP( BV$6, Actuals!$H$3:$BM$3, Actuals!$H:$BM ) )} -> 5283.29
B31: Spend - Digital (Organic) | C31: In-period | D31: =VLOOKUP($B$4&" "&$B31,Actuals!$D$4:$AG$131,3,FALSE) -> $ | E31: {=_xlfn.XLOOKUP( $B$4&" "&$B31, Actuals!$D:$D, _xlfn.XLOOKUP( E$6, Actuals!$H$3:$BD$3, Actuals!$H:$BD ) )} -> 0 | F31: {=_xlfn.XLOOKUP( $B$4&" "&$B31, Actuals!$D:$D, _xlfn.XLOOKUP( F$6, Actuals!$H$3:$BD$3, Actuals!$H:$BD ) )} -> 0 | G31: {=_xlfn.XLOOKUP( $B$4&" "&$B31, Actuals!$D:$D, _xlfn.XLOOKUP( G$6, Actuals!$H$3:$BD$3, Actuals!$H:$BD ) )} -> 0 | H31: {=_xlfn.XLOOKUP( $B$4&" "&$B31, Actuals!$D:$D, _xlfn.XLOOKUP( H$6, Actuals!$H$3:$BD$3, Actuals!$H:$BD ) )} -> 0 | I31: {=_xlfn.XLOOKUP( $B$4&" "&$B31, Actuals!$D:$D, _xlfn.XLOOKUP( I$6, Actuals!$H$3:$BD$3, Actuals!$H:$BD ) )} -> 0 | J31: {=_xlfn.XLOOKUP( $B$4&" "&$B31, Actuals!$D:$D, _xlfn.XLOOKUP( J$6, Actuals!$H$3:$BD$3, Actuals!$H:$BD ) )} -> 0 | K31: {=_xlfn.XLOOKUP( $B$4&" "&$B31, Actuals!$D:$D, _xlfn.XLOOKUP( K$6, Actuals!$H$3:$BD$3, Actuals!$H:$BD ) )} -> 0 | L31: {=_xlfn.XLOOKUP( $B$4&" "&$B31, Actuals!$D:$D, _xlfn.XLOOKUP( L$6, Actuals!$H$3:$BD$3, Actuals!$H:$BD ) )} -> 0 | ... AZ31: {=_xlfn.XLOOKUP( $B$4&" "&$B31, Actuals!$D:$D, _xlfn.XLOOKUP( AZ$6, Actuals!$H$3:$BD$3, Actuals!$H:$BD ) )} -> 0 | BB31: {=_xlfn.XLOOKUP( $B$4&" "&$B31, Actuals!$D:$D, _xlfn.XLOOKUP( BB$7, Actuals!$H$3:$BM$3, Actuals!$H:$BM ) )} -> 0 | BC31: =VLOOKUP($B$4&" "&$B31,Budget!$AG$4:$AL$132,$BB$5+1,FALSE) -> 0 | BD31: =BB31-BC31 -> 0 | BF31: {=_xlfn.XLOOKUP( $B$4&" "&$B31, Actuals!$D:$D, _xlfn.XLOOKUP( BF$7, Actuals!$H$3:$BM$3, Actuals!$H:$BM ) )} -> 0 | BG31: =VLOOKUP($B$4&" "&$B31,Budget!$AG$4:$AL$132,BF$5+1,FALSE) -> 0 | BH31: =BF31-BG31 -> 0 | BJ31: {=_xlfn.XLOOKUP( $B$4&" "&$B31, Actuals!$D:$D, _xlfn.XLOOKUP( BJ$7, Actuals!$H$3:$BM$3, Actuals!$H:$BM ) )} -> 0 | BK31: =VLOOKUP($B$4&" "&$B31,Budget!$AG$4:$AL$132,BJ$5+1,FALSE) -> 0 | BL31: =BJ31-BK31 -> 0 | BN31: {=_xlfn.XLOOKUP( $B$4&" "&$B31, Actuals!$D:$D, _xlfn.XLOOKUP( BN$7, Actuals!$H$3:$BM$3, Actuals!$H:$BM ) )} -> 0 | BO31: =VLOOKUP($B$4&" "&$B31,Budget!$AG$4:$AL$132,BN$5+1,FALSE) -> 0 | BR31: {=_xlfn.XLOOKUP( $B$4&" "&$B31, Actuals!$D:$D, _xlfn.XLOOKUP( BR$6, Actuals!$H$3:$BM$3, Actuals!$H:$BM ) )} -> 0 | BS31: =VLOOKUP($B$4&" "&$B31,Budget!$AG$4:$AL$132,6,FALSE) -> 0 | BT31: =BR31-BS31 -> 0 | BV31: {=_xlfn.XLOOKUP( $B$4&" "&$B31, Actuals!$D:$D, _xlfn.XLOOKUP( BV$6, Actuals!$H$3:$BM$3, Actuals!$H:$BM ) )} -> 0
B32: Spend - Events / Conferences | C32: In-period | D32: =VLOOKUP($B$4&" "&$B32,Actuals!$D$4:$AG$131,3,FALSE) -> $ | E32: {=_xlfn.XLOOKUP( $B$4&" "&$B32, Actuals!$D:$D, _xlfn.XLOOKUP( E$6, Actuals!$H$3:$BD$3, Actuals!$H:$BD ) )} -> 0 | F32: {=_xlfn.XLOOKUP( $B$4&" "&$B32, Actuals!$D:$D, _xlfn.XLOOKUP( F$6, Actuals!$H$3:$BD$3, Actuals!$H:$BD ) )} -> 0 | G32: {=_xlfn.XLOOKUP( $B$4&" "&$B32, Actuals!$D:$D, _xlfn.XLOOKUP( G$6, Actuals!$H$3:$BD$3, Actuals!$H:$BD ) )} -> 0 | H32: {=_xlfn.XLOOKUP( $B$4&" "&$B32, Actuals!$D:$D, _xlfn.XLOOKUP( H$6, Actuals!$H$3:$BD$3, Actuals!$H:$BD ) )} -> 0 | I32: {=_xlfn.XLOOKUP( $B$4&" "&$B32, Actuals!$D:$D, _xlfn.XLOOKUP( I$6, Actuals!$H$3:$BD$3, Actuals!$H:$BD ) )} -> 0 | J32: {=_xlfn.XLOOKUP( $B$4&" "&$B32, Actuals!$D:$D, _xlfn.XLOOKUP( J$6, Actuals!$H$3:$BD$3, Actuals!$H:$BD ) )} -> 0 | K32: {=_xlfn.XLOOKUP( $B$4&" "&$B32, Actuals!$D:$D, _xlfn.XLOOKUP( K$6, Actuals!$H$3:$BD$3, Actuals!$H:$BD ) )} -> 0 | L32: {=_xlfn.XLOOKUP( $B$4&" "&$B32, Actuals!$D:$D, _xlfn.XLOOKUP( L$6, Actuals!$H$3:$BD$3, Actuals!$H:$BD ) )} -> 0 | ... AZ32: {=_xlfn.XLOOKUP( $B$4&" "&$B32, Actuals!$D:$D, _xlfn.XLOOKUP( AZ$6, Actuals!$H$3:$BD$3, Actuals!$H:$BD ) )} -> 0 | BB32: {=_xlfn.XLOOKUP( $B$4&" "&$B32, Actuals!$D:$D, _xlfn.XLOOKUP( BB$7, Actuals!$H$3:$BM$3, Actuals!$H:$BM ) )} -> 0 | BC32: =VLOOKUP($B$4&" "&$B32,Budget!$AG$4:$AL$132,$BB$5+1,FALSE) -> 0 | BD32: =BB32-BC32 -> 0 | BF32: {=_xlfn.XLOOKUP( $B$4&" "&$B32, Actuals!$D:$D, _xlfn.XLOOKUP( BF$7, Actuals!$H$3:$BM$3, Actuals!$H:$BM ) )} -> 0 | BG32: =VLOOKUP($B$4&" "&$B32,Budget!$AG$4:$AL$132,BF$5+1,FALSE) -> 0 | BH32: =BF32-BG32 -> 0 | BJ32: {=_xlfn.XLOOKUP( $B$4&" "&$B32, Actuals!$D:$D, _xlfn.XLOOKUP( BJ$7, Actuals!$H$3:$BM$3, Actuals!$H:$BM ) )} -> 0 | BK32: =VLOOKUP($B$4&" "&$B32,Budget!$AG$4:$AL$132,BJ$5+1,FALSE) -> 0 | BL32: =BJ32-BK32 -> 0 | BN32: {=_xlfn.XLOOKUP( $B$4&" "&$B32, Actuals!$D:$D, _xlfn.XLOOKUP( BN$7, Actuals!$H$3:$BM$3, Actuals!$H:$BM ) )} -> 0 | BO32: =VLOOKUP($B$4&" "&$B32,Budget!$AG$4:$AL$132,BN$5+1,FALSE) -> 0 | BR32: {=_xlfn.XLOOKUP( $B$4&" "&$B32, Actuals!$D:$D, _xlfn.XLOOKUP( BR$6, Actuals!$H$3:$BM$3, Actuals!$H:$BM ) )} -> 0 | BS32: =VLOOKUP($B$4&" "&$B32,Budget!$AG$4:$AL$132,6,FALSE) -> 0 | BT32: =BR32-BS32 -> 0 | BV32: {=_xlfn.XLOOKUP( $B$4&" "&$B32, Actuals!$D:$D, _xlfn.XLOOKUP( BV$6, Actuals!$H$3:$BM$3, Actuals!$H:$BM ) )} -> 85000
B33: Spend - Outbound (BDR) | C33: In-period | D33: =VLOOKUP($B$4&" "&$B33,Actuals!$D$4:$AG$131,3,FALSE) -> $ | E33: {=_xlfn.XLOOKUP( $B$4&" "&$B33, Actuals!$D:$D, _xlfn.XLOOKUP( E$6, Actuals!$H$3:$BD$3, Actuals!$H:$BD ) )} -> 0 | F33: {=_xlfn.XLOOKUP( $B$4&" "&$B33, Actuals!$D:$D, _xlfn.XLOOKUP( F$6, Actuals!$H$3:$BD$3, Actuals!$H:$BD ) )} -> 0 | G33: {=_xlfn.XLOOKUP( $B$4&" "&$B33, Actuals!$D:$D, _xlfn.XLOOKUP( G$6, Actuals!$H$3:$BD$3, Actuals!$H:$BD ) )} -> 0 | H33: {=_xlfn.XLOOKUP( $B$4&" "&$B33, Actuals!$D:$D, _xlfn.XLOOKUP( H$6, Actuals!$H$3:$BD$3, Actuals!$H:$BD ) )} -> 0 | I33: {=_xlfn.XLOOKUP( $B$4&" "&$B33, Actuals!$D:$D, _xlfn.XLOOKUP( I$6, Actuals!$H$3:$BD$3, Actuals!$H:$BD ) )} -> 0 | J33: {=_xlfn.XLOOKUP( $B$4&" "&$B33, Actuals!$D:$D, _xlfn.XLOOKUP( J$6, Actuals!$H$3:$BD$3, Actuals!$H:$BD ) )} -> 0 | K33: {=_xlfn.XLOOKUP( $B$4&" "&$B33, Actuals!$D:$D, _xlfn.XLOOKUP( K$6, Actuals!$H$3:$BD$3, Actuals!$H:$BD ) )} -> 0 | L33: {=_xlfn.XLOOKUP( $B$4&" "&$B33, Actuals!$D:$D, _xlfn.XLOOKUP( L$6, Actuals!$H$3:$BD$3, Actuals!$H:$BD ) )} -> 0 | ... AZ33: {=_xlfn.XLOOKUP( $B$4&" "&$B33, Actuals!$D:$D, _xlfn.XLOOKUP( AZ$6, Actuals!$H$3:$BD$3, Actuals!$H:$BD ) )} -> 0 | BB33: {=_xlfn.XLOOKUP( $B$4&" "&$B33, Actuals!$D:$D, _xlfn.XLOOKUP( BB$7, Actuals!$H$3:$BM$3, Actuals!$H:$BM ) )} -> 0 | BC33: =VLOOKUP($B$4&" "&$B33,Budget!$AG$4:$AL$132,$BB$5+1,FALSE) -> 65550 | BD33: =BB33-BC33 -> -65550 | BF33: {=_xlfn.XLOOKUP( $B$4&" "&$B33, Actuals!$D:$D, _xlfn.XLOOKUP( BF$7, Actuals!$H$3:$BM$3, Actuals!$H:$BM ) )} -> 0 | BG33: =VLOOKUP($B$4&" "&$B33,Budget!$AG$4:$AL$132,BF$5+1,FALSE) -> 65550 | BH33: =BF33-BG33 -> -65550 | BJ33: {=_xlfn.XLOOKUP( $B$4&" "&$B33, Actuals!$D:$D, _xlfn.XLOOKUP( BJ$7, Actuals!$H$3:$BM$3, Actuals!$H:$BM ) )} -> 0 | BK33: =VLOOKUP($B$4&" "&$B33,Budget!$AG$4:$AL$132,BJ$5+1,FALSE) -> 67736 | BL33: =BJ33-BK33 -> -67736 | BN33: {=_xlfn.XLOOKUP( $B$4&" "&$B33, Actuals!$D:$D, _xlfn.XLOOKUP( BN$7, Actuals!$H$3:$BM$3, Actuals!$H:$BM ) )} -> 0 | BO33: =VLOOKUP($B$4&" "&$B33,Budget!$AG$4:$AL$132,BN$5+1,FALSE) -> 68829 | BR33: {=_xlfn.XLOOKUP( $B$4&" "&$B33, Actuals!$D:$D, _xlfn.XLOOKUP( BR$6, Actuals!$H$3:$BM$3, Actuals!$H:$BM ) )} -> 0 | BS33: =VLOOKUP($B$4&" "&$B33,Budget!$AG$4:$AL$132,6,FALSE) -> 268758 | BT33: =BR33-BS33 -> -268758 | BV33: {=_xlfn.XLOOKUP( $B$4&" "&$B33, Actuals!$D:$D, _xlfn.XLOOKUP( BV$6, Actuals!$H$3:$BM$3, Actuals!$H:$BM ) )} -> 0
B34: Spend - Other | C34: In-period | D34: =VLOOKUP($B$4&" "&$B34,Actuals!$D$4:$AG$131,3,FALSE) -> $ | E34: {=_xlfn.XLOOKUP( $B$4&" "&$B34, Actuals!$D:$D, _xlfn.XLOOKUP( E$6, Actuals!$H$3:$BD$3, Actuals!$H:$BD ) )} -> 0 | F34: {=_xlfn.XLOOKUP( $B$4&" "&$B34, Actuals!$D:$D, _xlfn.XLOOKUP( F$6, Actuals!$H$3:$BD$3, Actuals!$H:$BD ) )} -> 0 | G34: {=_xlfn.XLOOKUP( $B$4&" "&$B34, Actuals!$D:$D, _xlfn.XLOOKUP( G$6, Actuals!$H$3:$BD$3, Actuals!$H:$BD ) )} -> 0 | H34: {=_xlfn.XLOOKUP( $B$4&" "&$B34, Actuals!$D:$D, _xlfn.XLOOKUP( H$6, Actuals!$H$3:$BD$3, Actuals!$H:$BD ) )} -> 0 | I34: {=_xlfn.XLOOKUP( $B$4&" "&$B34, Actuals!$D:$D, _xlfn.XLOOKUP( I$6, Actuals!$H$3:$BD$3, Actuals!$H:$BD ) )} -> 0 | J34: {=_xlfn.XLOOKUP( $B$4&" "&$B34, Actuals!$D:$D, _xlfn.XLOOKUP( J$6, Actuals!$H$3:$BD$3, Actuals!$H:$BD ) )} -> 0 | K34: {=_xlfn.XLOOKUP( $B$4&" "&$B34, Actuals!$D:$D, _xlfn.XLOOKUP( K$6, Actuals!$H$3:$BD$3, Actuals!$H:$BD ) )} -> 0 | L34: {=_xlfn.XLOOKUP( $B$4&" "&$B34, Actuals!$D:$D, _xlfn.XLOOKUP( L$6, Actuals!$H$3:$BD$3, Actuals!$H:$BD ) )} -> 0 | ... AZ34: {=_xlfn.XLOOKUP( $B$4&" "&$B34, Actuals!$D:$D, _xlfn.XLOOKUP( AZ$6, Actuals!$H$3:$BD$3, Actuals!$H:$BD ) )} -> 0 | BB34: {=_xlfn.XLOOKUP( $B$4&" "&$B34, Actuals!$D:$D, _xlfn.XLOOKUP( BB$7, Actuals!$H$3:$BM$3, Actuals!$H:$BM ) )} -> 0 | BC34: =VLOOKUP($B$4&" "&$B34,Budget!$AG$4:$AL$132,$BB$5+1,FALSE) -> 0 | BD34: =BB34-BC34 -> 0 | BF34: {=_xlfn.XLOOKUP( $B$4&" "&$B34, Actuals!$D:$D, _xlfn.XLOOKUP( BF$7, Actuals!$H$3:$BM$3, Actuals!$H:$BM ) )} -> 0 | BG34: =VLOOKUP($B$4&" "&$B34,Budget!$AG$4:$AL$132,BF$5+1,FALSE) -> 0 | BH34: =BF34-BG34 -> 0 | BJ34: {=_xlfn.XLOOKUP( $B$4&" "&$B34, Actuals!$D:$D, _xlfn.XLOOKUP( BJ$7, Actuals!$H$3:$BM$3, Actuals!$H:$BM ) )} -> 0 | BK34: =VLOOKUP($B$4&" "&$B34,Budget!$AG$4:$AL$132,BJ$5+1,FALSE) -> 0 | BL34: =BJ34-BK34 -> 0 | BN34: {=_xlfn.XLOOKUP( $B$4&" "&$B34, Actuals!$D:$D, _xlfn.XLOOKUP( BN$7, Actuals!$H$3:$BM$3, Actuals!$H:$BM ) )} -> 0 | BO34: =VLOOKUP($B$4&" "&$B34,Budget!$AG$4:$AL$132,BN$5+1,FALSE) -> 0 | BR34: {=_xlfn.XLOOKUP( $B$4&" "&$B34, Actuals!$D:$D, _xlfn.XLOOKUP( BR$6, Actuals!$H$3:$BM$3, Actuals!$H:$BM ) )} -> 0 | BS34: =VLOOKUP($B$4&" "&$B34,Budget!$AG$4:$AL$132,6,FALSE) -> 0 | BT34: =BR34-BS34 -> 0 | BV34: {=_xlfn.XLOOKUP( $B$4&" "&$B34, Actuals!$D:$D, _xlfn.XLOOKUP( BV$6, Actuals!$H$3:$BM$3, Actuals!$H:$BM ) )} -> 9790
B35: $ / Lead - Digital (Paid) | C35: In-period | D35: =VLOOKUP($B$4&" "&$B35,Actuals!$D$4:$AG$131,3,FALSE) -> #N/A | E35: {=_xlfn.XLOOKUP( $B$4&" "&$B35, Actuals!$D:$D, _xlfn.XLOOKUP( E$6, Actuals!$H$3:$BD$3, Actuals!$H:$BD ) )} -> #N/A | F35: {=_xlfn.XLOOKUP( $B$4&" "&$B35, Actuals!$D:$D, _xlfn.XLOOKUP( F$6, Actuals!$H$3:$BD$3, Actuals!$H:$BD ) )} -> #N/A | G35: {=_xlfn.XLOOKUP( $B$4&" "&$B35, Actuals!$D:$D, _xlfn.XLOOKUP( G$6, Actuals!$H$3:$BD$3, Actuals!$H:$BD ) )} -> #N/A | H35: {=_xlfn.XLOOKUP( $B$4&" "&$B35, Actuals!$D:$D, _xlfn.XLOOKUP( H$6, Actuals!$H$3:$BD$3, Actuals!$H:$BD ) )} -> #N/A | I35: {=_xlfn.XLOOKUP( $B$4&" "&$B35, Actuals!$D:$D, _xlfn.XLOOKUP( I$6, Actuals!$H$3:$BD$3, Actuals!$H:$BD ) )} -> #N/A | J35: {=_xlfn.XLOOKUP( $B$4&" "&$B35, Actuals!$D:$D, _xlfn.XLOOKUP( J$6, Actuals!$H$3:$BD$3, Actuals!$H:$BD ) )} -> #N/A | K35: {=_xlfn.XLOOKUP( $B$4&" "&$B35, Actuals!$D:$D, _xlfn.XLOOKUP( K$6, Actuals!$H$3:$BD$3, Actuals!$H:$BD ) )} -> #N/A | L35: {=_xlfn.XLOOKUP( $B$4&" "&$B35, Actuals!$D:$D, _xlfn.XLOOKUP( L$6, Actuals!$H$3:$BD$3, Actuals!$H:$BD ) )} -> #N/A | ... AZ35: {=_xlfn.XLOOKUP( $B$4&" "&$B35, Actuals!$D:$D, _xlfn.XLOOKUP( AZ$6, Actuals!$H$3:$BD$3, Actuals!$H:$BD ) )} -> #N/A | BB35: {=_xlfn.XLOOKUP( $B$4&" "&$B35, Actuals!$D:$D, _xlfn.XLOOKUP( BB$7, Actuals!$H$3:$BM$3, Actuals!$H:$BM ) )} -> #N/A | BC35: =IFERROR(BC30/BC25,"-") -> 2000 | BD35: =BB35-BC35 -> #N/A | BF35: {=_xlfn.XLOOKUP( $B$4&" "&$B35, Actuals!$D:$D, _xlfn.XLOOKUP( BF$7, Actuals!$H$3:$BM$3, Actuals!$H:$BM ) )} -> #N/A | BG35: =IFERROR(BG30/BG25,"-") -> 2000 | BH35: =BF35-BG35 -> #N/A | BJ35: {=_xlfn.XLOOKUP( $B$4&" "&$B35, Actuals!$D:$D, _xlfn.XLOOKUP( BJ$7, Actuals!$H$3:$BM$3, Actuals!$H:$BM ) )} -> #N/A | BK35: =IFERROR(BK30/BK25,"-") -> 2000 | BL35: =BJ35-BK35 -> #N/A | BN35: {=_xlfn.XLOOKUP( $B$4&" "&$B35, Actuals!$D:$D, _xlfn.XLOOKUP( BN$7, Actuals!$H$3:$BM$3, Actuals!$H:$BM ) )} -> #N/A | BO35: =IFERROR(BO30/BO25,"-") -> 2000 | BR35: {=_xlfn.XLOOKUP( $B$4&" "&$B35, Actuals!$D:$D, _xlfn.XLOOKUP( BR$6, Actuals!$H$3:$BM$3, Actuals!$H:$BM ) )} -> #N/A | BS35: =IFERROR(BS30/BS25,"-") -> 2000 | BT35: =BR35-BS35 -> #N/A | BV35: {=_xlfn.XLOOKUP( $B$4&" "&$B35, Actuals!$D:$D, _xlfn.XLOOKUP( BV$6, Actuals!$H$3:$BM$3, Actuals!$H:$BM ) )} -> #N/A
B36: $ / Lead - Digital (Organic) | C36: In-period | D36: =VLOOKUP($B$4&" "&$B36,Actuals!$D$4:$AG$131,3,FALSE) -> #N/A | E36: {=_xlfn.XLOOKUP( $B$4&" "&$B36, Actuals!$D:$D, _xlfn.XLOOKUP( E$6, Actuals!$H$3:$BD$3, Actuals!$H:$BD ) )} -> #N/A | F36: {=_xlfn.XLOOKUP( $B$4&" "&$B36, Actuals!$D:$D, _xlfn.XLOOKUP( F$6, Actuals!$H$3:$BD$3, Actuals!$H:$BD ) )} -> #N/A | G36: {=_xlfn.XLOOKUP( $B$4&" "&$B36, Actuals!$D:$D, _xlfn.XLOOKUP( G$6, Actuals!$H$3:$BD$3, Actuals!$H:$BD ) )} -> #N/A | H36: {=_xlfn.XLOOKUP( $B$4&" "&$B36, Actuals!$D:$D, _xlfn.XLOOKUP( H$6, Actuals!$H$3:$BD$3, Actuals!$H:$BD ) )} -> #N/A | I36: {=_xlfn.XLOOKUP( $B$4&" "&$B36, Actuals!$D:$D, _xlfn.XLOOKUP( I$6, Actuals!$H$3:$BD$3, Actuals!$H:$BD ) )} -> #N/A | J36: {=_xlfn.XLOOKUP( $B$4&" "&$B36, Actuals!$D:$D, _xlfn.XLOOKUP( J$6, Actuals!$H$3:$BD$3, Actuals!$H:$BD ) )} -> #N/A | K36: {=_xlfn.XLOOKUP( $B$4&" "&$B36, Actuals!$D:$D, _xlfn.XLOOKUP( K$6, Actuals!$H$3:$BD$3, Actuals!$H:$BD ) )} -> #N/A | L36: {=_xlfn.XLOOKUP( $B$4&" "&$B36, Actuals!$D:$D, _xlfn.XLOOKUP( L$6, Actuals!$H$3:$BD$3, Actuals!$H:$BD ) )} -> #N/A | ... AZ36: {=_xlfn.XLOOKUP( $B$4&" "&$B36, Actuals!$D:$D, _xlfn.XLOOKUP( AZ$6, Actuals!$H$3:$BD$3, Actuals!$H:$BD ) )} -> #N/A | BB36: {=_xlfn.XLOOKUP( $B$4&" "&$B36, Actuals!$D:$D, _xlfn.XLOOKUP( BB$7, Actuals!$H$3:$BM$3, Actuals!$H:$BM ) )} -> #N/A | BC36: =IFERROR(BC31/BC26,"-") -> 0 | BD36: =BB36-BC36 -> #N/A | BF36: {=_xlfn.XLOOKUP( $B$4&" "&$B36, Actuals!$D:$D, _xlfn.XLOOKUP( BF$7, Actuals!$H$3:$BM$3, Actuals!$H:$BM ) )} -> #N/A | BG36: =IFERROR(BG31/BG26,"-") -> 0 | BH36: =BF36-BG36 -> #N/A | BJ36: {=_xlfn.XLOOKUP( $B$4&" "&$B36, Actuals!$D:$D, _xlfn.XLOOKUP( BJ$7, Actuals!$H$3:$BM$3, Actuals!$H:$BM ) )} -> #N/A | BK36: =IFERROR(BK31/BK26,"-") -> 0 | BL36: =BJ36-BK36 -> #N/A | BN36: {=_xlfn.XLOOKUP( $B$4&" "&$B36, Actuals!$D:$D, _xlfn.XLOOKUP( BN$7, Actuals!$H$3:$BM$3, Actuals!$H:$BM ) )} -> #N/A | BO36: =IFERROR(BO31/BO26,"-") -> 0 | BR36: {=_xlfn.XLOOKUP( $B$4&" "&$B36, Actuals!$D:$D, _xlfn.XLOOKUP( BR$6, Actuals!$H$3:$BM$3, Actuals!$H:$BM ) )} -> #N/A | BS36: =IFERROR(BS31/BS26,"-") -> 0 | BT36: =BR36-BS36 -> #N/A | BV36: {=_xlfn.XLOOKUP( $B$4&" "&$B36, Actuals!$D:$D, _xlfn.XLOOKUP( BV$6, Actuals!$H$3:$BM$3, Actuals!$H:$BM ) )} -> #N/A
B37: $ / Lead - Events / Conferences | C37: In-period | D37: =VLOOKUP($B$4&" "&$B37,Actuals!$D$4:$AG$131,3,FALSE) -> #N/A | E37: {=_xlfn.XLOOKUP( $B$4&" "&$B37, Actuals!$D:$D, _xlfn.XLOOKUP( E$6, Actuals!$H$3:$BD$3, Actuals!$H:$BD ) )} -> #N/A | F37: {=_xlfn.XLOOKUP( $B$4&" "&$B37, Actuals!$D:$D, _xlfn.XLOOKUP( F$6, Actuals!$H$3:$BD$3, Actuals!$H:$BD ) )} -> #N/A | G37: {=_xlfn.XLOOKUP( $B$4&" "&$B37, Actuals!$D:$D, _xlfn.XLOOKUP( G$6, Actuals!$H$3:$BD$3, Actuals!$H:$BD ) )} -> #N/A | H37: {=_xlfn.XLOOKUP( $B$4&" "&$B37, Actuals!$D:$D, _xlfn.XLOOKUP( H$6, Actuals!$H$3:$BD$3, Actuals!$H:$BD ) )} -> #N/A | I37: {=_xlfn.XLOOKUP( $B$4&" "&$B37, Actuals!$D:$D, _xlfn.XLOOKUP( I$6, Actuals!$H$3:$BD$3, Actuals!$H:$BD ) )} -> #N/A | J37: {=_xlfn.XLOOKUP( $B$4&" "&$B37, Actuals!$D:$D, _xlfn.XLOOKUP( J$6, Actuals!$H$3:$BD$3, Actuals!$H:$BD ) )} -> #N/A | K37: {=_xlfn.XLOOKUP( $B$4&" "&$B37, Actuals!$D:$D, _xlfn.XLOOKUP( K$6, Actuals!$H$3:$BD$3, Actuals!$H:$BD ) )} -> #N/A | L37: {=_xlfn.XLOOKUP( $B$4&" "&$B37, Actuals!$D:$D, _xlfn.XLOOKUP( L$6, Actuals!$H$3:$BD$3, Actuals!$H:$BD ) )} -> #N/A | ... AZ37: {=_xlfn.XLOOKUP( $B$4&" "&$B37, Actuals!$D:$D, _xlfn.XLOOKUP( AZ$6, Actuals!$H$3:$BD$3, Actuals!$H:$BD ) )} -> #N/A | BB37: {=_xlfn.XLOOKUP( $B$4&" "&$B37, Actuals!$D:$D, _xlfn.XLOOKUP( BB$7, Actuals!$H$3:$BM$3, Actuals!$H:$BM ) )} -> #N/A | BC37: =IFERROR(BC32/BC27,"-") -> 0 | BD37: =BB37-BC37 -> #N/A | BF37: {=_xlfn.XLOOKUP( $B$4&" "&$B37, Actuals!$D:$D, _xlfn.XLOOKUP( BF$7, Actuals!$H$3:$BM$3, Actuals!$H:$BM ) )} -> #N/A | BG37: =IFERROR(BG32/BG27,"-") -> 0 | BH37: =BF37-BG37 -> #N/A | BJ37: {=_xlfn.XLOOKUP( $B$4&" "&$B37, Actuals!$D:$D, _xlfn.XLOOKUP( BJ$7, Actuals!$H$3:$BM$3, Actuals!$H:$BM ) )} -> #N/A | BK37: =IFERROR(BK32/BK27,"-") -> 0 | BL37: =BJ37-BK37 -> #N/A | BN37: {=_xlfn.XLOOKUP( $B$4&" "&$B37, Actuals!$D:$D, _xlfn.XLOOKUP( BN$7, Actuals!$H$3:$BM$3, Actuals!$H:$BM ) )} -> #N/A | BO37: =IFERROR(BO32/BO27,"-") -> 0 | BR37: {=_xlfn.XLOOKUP( $B$4&" "&$B37, Actuals!$D:$D, _xlfn.XLOOKUP( BR$6, Actuals!$H$3:$BM$3, Actuals!$H:$BM ) )} -> #N/A | BS37: =IFERROR(BS32/BS27,"-") -> 0 | BT37: =BR37-BS37 -> #N/A | BV37: {=_xlfn.XLOOKUP( $B$4&" "&$B37, Actuals!$D:$D, _xlfn.XLOOKUP( BV$6, Actuals!$H$3:$BM$3, Actuals!$H:$BM ) )} -> #N/A
B38: $ / Lead - Outbound (BDR) | C38: In-period | D38: =VLOOKUP($B$4&" "&$B38,Actuals!$D$4:$AG$131,3,FALSE) -> #N/A | E38: {=_xlfn.XLOOKUP( $B$4&" "&$B38, Actuals!$D:$D, _xlfn.XLOOKUP( E$6, Actuals!$H$3:$BD$3, Actuals!$H:$BD ) )} -> #N/A | F38: {=_xlfn.XLOOKUP( $B$4&" "&$B38, Actuals!$D:$D, _xlfn.XLOOKUP( F$6, Actuals!$H$3:$BD$3, Actuals!$H:$BD ) )} -> #N/A | G38: {=_xlfn.XLOOKUP( $B$4&" "&$B38, Actuals!$D:$D, _xlfn.XLOOKUP( G$6, Actuals!$H$3:$BD$3, Actuals!$H:$BD ) )} -> #N/A | H38: {=_xlfn.XLOOKUP( $B$4&" "&$B38, Actuals!$D:$D, _xlfn.XLOOKUP( H$6, Actuals!$H$3:$BD$3, Actuals!$H:$BD ) )} -> #N/A | I38: {=_xlfn.XLOOKUP( $B$4&" "&$B38, Actuals!$D:$D, _xlfn.XLOOKUP( I$6, Actuals!$H$3:$BD$3, Actuals!$H:$BD ) )} -> #N/A | J38: {=_xlfn.XLOOKUP( $B$4&" "&$B38, Actuals!$D:$D, _xlfn.XLOOKUP( J$6, Actuals!$H$3:$BD$3, Actuals!$H:$BD ) )} -> #N/A | K38: {=_xlfn.XLOOKUP( $B$4&" "&$B38, Actuals!$D:$D, _xlfn.XLOOKUP( K$6, Actuals!$H$3:$BD$3, Actuals!$H:$BD ) )} -> #N/A | L38: {=_xlfn.XLOOKUP( $B$4&" "&$B38, Actuals!$D:$D, _xlfn.XLOOKUP( L$6, Actuals!$H$3:$BD$3, Actuals!$H:$BD ) )} -> #N/A | ... AZ38: {=_xlfn.XLOOKUP( $B$4&" "&$B38, Actuals!$D:$D, _xlfn.XLOOKUP( AZ$6, Actuals!$H$3:$BD$3, Actuals!$H:$BD ) )} -> #N/A | BB38: {=_xlfn.XLOOKUP( $B$4&" "&$B38, Actuals!$D:$D, _xlfn.XLOOKUP( BB$7, Actuals!$H$3:$BM$3, Actuals!$H:$BM ) )} -> #N/A | BC38: =IFERROR(BC33/BC28,"-") -> 2185 | BD38: =BB38-BC38 -> #N/A | BF38: {=_xlfn.XLOOKUP( $B$4&" "&$B38, Actuals!$D:$D, _xlfn.XLOOKUP( BF$7, Actuals!$H$3:$BM$3, Actuals!$H:$BM ) )} -> #N/A | BG38: =IFERROR(BG33/BG28,"-") -> 2185 | BH38: =BF38-BG38 -> #N/A | BJ38: {=_xlfn.XLOOKUP( $B$4&" "&$B38, Actuals!$D:$D, _xlfn.XLOOKUP( BJ$7, Actuals!$H$3:$BM$3, Actuals!$H:$BM ) )} -> #N/A | BK38: =IFERROR(BK33/BK28,"-") -> 2257.8667 | BL38: =BJ38-BK38 -> #N/A | BN38: {=_xlfn.XLOOKUP( $B$4&" "&$B38, Actuals!$D:$D, _xlfn.XLOOKUP( BN$7, Actuals!$H$3:$BM$3, Actuals!$H:$BM ) )} -> #N/A | BO38: =IFERROR(BO33/BO28,"-") -> 2294.3 | BR38: {=_xlfn.XLOOKUP( $B$4&" "&$B38, Actuals!$D:$D, _xlfn.XLOOKUP( BR$6, Actuals!$H$3:$BM$3, Actuals!$H:$BM ) )} -> #N/A | BS38: =IFERROR(BS33/BS28,"-") -> 2239.65 | BT38: =BR38-BS38 -> #N/A | BV38: {=_xlfn.XLOOKUP( $B$4&" "&$B38, Actuals!$D:$D, _xlfn.XLOOKUP( BV$6, Actuals!$H$3:$BM$3, Actuals!$H:$BM ) )} -> #N/A
B39: $ / Lead - Other | C39: In-period | D39: =VLOOKUP($B$4&" "&$B39,Actuals!$D$4:$AG$131,3,FALSE) -> #N/A | E39: {=_xlfn.XLOOKUP( $B$4&" "&$B39, Actuals!$D:$D, _xlfn.XLOOKUP( E$6, Actuals!$H$3:$BD$3, Actuals!$H:$BD ) )} -> #N/A | F39: {=_xlfn.XLOOKUP( $B$4&" "&$B39, Actuals!$D:$D, _xlfn.XLOOKUP( F$6, Actuals!$H$3:$BD$3, Actuals!$H:$BD ) )} -> #N/A | G39: {=_xlfn.XLOOKUP( $B$4&" "&$B39, Actuals!$D:$D, _xlfn.XLOOKUP( G$6, Actuals!$H$3:$BD$3, Actuals!$H:$BD ) )} -> #N/A | H39: {=_xlfn.XLOOKUP( $B$4&" "&$B39, Actuals!$D:$D, _xlfn.XLOOKUP( H$6, Actuals!$H$3:$BD$3, Actuals!$H:$BD ) )} -> #N/A | I39: {=_xlfn.XLOOKUP( $B$4&" "&$B39, Actuals!$D:$D, _xlfn.XLOOKUP( I$6, Actuals!$H$3:$BD$3, Actuals!$H:$BD ) )} -> #N/A | J39: {=_xlfn.XLOOKUP( $B$4&" "&$B39, Actuals!$D:$D, _xlfn.XLOOKUP( J$6, Actuals!$H$3:$BD$3, Actuals!$H:$BD ) )} -> #N/A | K39: {=_xlfn.XLOOKUP( $B$4&" "&$B39, Actuals!$D:$D, _xlfn.XLOOKUP( K$6, Actuals!$H$3:$BD$3, Actuals!$H:$BD ) )} -> #N/A | L39: {=_xlfn.XLOOKUP( $B$4&" "&$B39, Actuals!$D:$D, _xlfn.XLOOKUP( L$6, Actuals!$H$3:$BD$3, Actuals!$H:$BD ) )} -> #N/A | ... AZ39: {=_xlfn.XLOOKUP( $B$4&" "&$B39, Actuals!$D:$D, _xlfn.XLOOKUP( AZ$6, Actuals!$H$3:$BD$3, Actuals!$H:$BD ) )} -> #N/A | BB39: {=_xlfn.XLOOKUP( $B$4&" "&$B39, Actuals!$D:$D, _xlfn.XLOOKUP( BB$7, Actuals!$H$3:$BM$3, Actuals!$H:$BM ) )} -> #N/A | BC39: =IFERROR(BC34/BC29,"-") -> - | BD39: =BB39-BC39 -> #N/A | BF39: {=_xlfn.XLOOKUP( $B$4&" "&$B39, Actuals!$D:$D, _xlfn.XLOOKUP( BF$7, Actuals!$H$3:$BM$3, Actuals!$H:$BM ) )} -> #N/A | BG39: =IFERROR(BG34/BG29,"-") -> - | BH39: =BF39-BG39 -> #N/A | BJ39: {=_xlfn.XLOOKUP( $B$4&" "&$B39, Actuals!$D:$D, _xlfn.XLOOKUP( BJ$7, Actuals!$H$3:$BM$3, Actuals!$H:$BM ) )} -> #N/A | BK39: =IFERROR(BK34/BK29,"-") -> - | BL39: =BJ39-BK39 -> #N/A | BN39: {=_xlfn.XLOOKUP( $B$4&" "&$B39, Actuals!$D:$D, _xlfn.XLOOKUP( BN$7, Actuals!$H$3:$BM$3, Actuals!$H:$BM ) )} -> #N/A | BO39: =IFERROR(BO34/BO29,"-") -> - | BR39: {=_xlfn.XLOOKUP( $B$4&" "&$B39, Actuals!$D:$D, _xlfn.XLOOKUP( BR$6, Actuals!$H$3:$BM$3, Actuals!$H:$BM ) )} -> #N/A | BS39: =IFERROR(BS34/BS29,"-") -> - | BT39: =BR39-BS39 -> #N/A | BV39: {=_xlfn.XLOOKUP( $B$4&" "&$B39, Actuals!$D:$D, _xlfn.XLOOKUP( BV$6, Actuals!$H$3:$BM$3, Actuals!$H:$BM ) )} -> #N/A
B41: Efficiency
B42: Headcount | C42: EoP | D42: =VLOOKUP($B$4&" "&$B42,Actuals!$D$4:$AG$131,3,FALSE) -> # | E42: {=_xlfn.XLOOKUP( $B$4&" "&$B42, Actuals!$D:$D, _xlfn.XLOOKUP( E$6, Actuals!$H$3:$BD$3, Actuals!$H:$BD ) )} -> 2 | F42: {=_xlfn.XLOOKUP( $B$4&" "&$B42, Actuals!$D:$D, _xlfn.XLOOKUP( F$6, Actuals!$H$3:$BD$3, Actuals!$H:$BD ) )} -> 2 | G42: {=_xlfn.XLOOKUP( $B$4&" "&$B42, Actuals!$D:$D, _xlfn.XLOOKUP( G$6, Actuals!$H$3:$BD$3, Actuals!$H:$BD ) )} -> 2 | H42: {=_xlfn.XLOOKUP( $B$4&" "&$B42, Actuals!$D:$D, _xlfn.XLOOKUP( H$6, Actuals!$H$3:$BD$3, Actuals!$H:$BD ) )} -> 2 | I42: {=_xlfn.XLOOKUP( $B$4&" "&$B42, Actuals!$D:$D, _xlfn.XLOOKUP( I$6, Actuals!$H$3:$BD$3, Actuals!$H:$BD ) )} -> 2 | J42: {=_xlfn.XLOOKUP( $B$4&" "&$B42, Actuals!$D:$D, _xlfn.XLOOKUP( J$6, Actuals!$H$3:$BD$3, Actuals!$H:$BD ) )} -> 2 | K42: {=_xlfn.XLOOKUP( $B$4&" "&$B42, Actuals!$D:$D, _xlfn.XLOOKUP( K$6, Actuals!$H$3:$BD$3, Actuals!$H:$BD ) )} -> 2 | L42: {=_xlfn.XLOOKUP( $B$4&" "&$B42, Actuals!$D:$D, _xlfn.XLOOKUP( L$6, Actuals!$H$3:$BD$3, Actuals!$H:$BD ) )} -> 2 | ... AZ42: {=_xlfn.XLOOKUP( $B$4&" "&$B42, Actuals!$D:$D, _xlfn.XLOOKUP( AZ$6, Actuals!$H$3:$BD$3, Actuals!$H:$BD ) )} -> 0 | BB42: {=_xlfn.XLOOKUP( $B$4&" "&$B42, Actuals!$D:$D, _xlfn.XLOOKUP( BB$7, Actuals!$H$3:$BM$3, Actuals!$H:$BM ) )} -> 0 | BC42: =VLOOKUP($B$4&" "&$B42,Budget!$AG$4:$AL$132,$BB$5+1,FALSE) -> 0 | BD42: =BB42-BC42 -> 0 | BF42: {=_xlfn.XLOOKUP( $B$4&" "&$B42, Actuals!$D:$D, _xlfn.XLOOKUP( BF$7, Actuals!$H$3:$BM$3, Actuals!$H:$BM ) )} -> 0 | BG42: =VLOOKUP($B$4&" "&$B42,Budget!$AG$4:$AL$132,BF$5+1,FALSE) -> 3 | BH42: =BF42-BG42 -> -3 | BJ42: {=_xlfn.XLOOKUP( $B$4&" "&$B42, Actuals!$D:$D, _xlfn.XLOOKUP( BJ$7, Actuals!$H$3:$BM$3, Actuals!$H:$BM ) )} -> 0 | BK42: =VLOOKUP($B$4&" "&$B42,Budget!$AG$4:$AL$132,BJ$5+1,FALSE) -> 3 | BL42: =BJ42-BK42 -> -3 | BN42: {=_xlfn.XLOOKUP( $B$4&" "&$B42, Actuals!$D:$D, _xlfn.XLOOKUP( BN$7, Actuals!$H$3:$BM$3, Actuals!$H:$BM ) )} -> 0 | BO42: =VLOOKUP($B$4&" "&$B42,Budget!$AG$4:$AL$132,BN$5+1,FALSE) -> 3 | BR42: {=_xlfn.XLOOKUP( $B$4&" "&$B42, Actuals!$D:$D, _xlfn.XLOOKUP( BR$6, Actuals!$H$3:$BM$3, Actuals!$H:$BM ) )} -> 0 | BS42: =VLOOKUP($B$4&" "&$B42,Budget!$AG$4:$AL$132,6,FALSE) -> 3 | BT42: =BR42-BS42 -> -3 | BV42: {=_xlfn.XLOOKUP( $B$4&" "&$B42, Actuals!$D:$D, _xlfn.XLOOKUP( BV$6, Actuals!$H$3:$BM$3, Actuals!$H:$BM ) )} -> 1
B43: Mktg expense | C43: L3M Avg | D43: =VLOOKUP($B$4&" "&$B43,Actuals!$D$4:$AG$131,3,FALSE) -> $ | E43: {=_xlfn.XLOOKUP( $B$4&" "&$B43, Actuals!$D:$D, _xlfn.XLOOKUP( E$6, Actuals!$H$3:$BD$3, Actuals!$H:$BD ) )} -> 78031.94 | F43: {=_xlfn.XLOOKUP( $B$4&" "&$B43, Actuals!$D:$D, _xlfn.XLOOKUP( F$6, Actuals!$H$3:$BD$3, Actuals!$H:$BD ) )} -> 32094.64 | G43: {=_xlfn.XLOOKUP( $B$4&" "&$B43, Actuals!$D:$D, _xlfn.XLOOKUP( G$6, Actuals!$H$3:$BD$3, Actuals!$H:$BD ) )} -> 30347.64 | H43: {=_xlfn.XLOOKUP( $B$4&" "&$B43, Actuals!$D:$D, _xlfn.XLOOKUP( H$6, Actuals!$H$3:$BD$3, Actuals!$H:$BD ) )} -> 41967.63 | I43: {=_xlfn.XLOOKUP( $B$4&" "&$B43, Actuals!$D:$D, _xlfn.XLOOKUP( I$6, Actuals!$H$3:$BD$3, Actuals!$H:$BD ) )} -> 39689.32 | J43: {=_xlfn.XLOOKUP( $B$4&" "&$B43, Actuals!$D:$D, _xlfn.XLOOKUP( J$6, Actuals!$H$3:$BD$3, Actuals!$H:$BD ) )} -> 55421.7 | K43: {=_xlfn.XLOOKUP( $B$4&" "&$B43, Actuals!$D:$D, _xlfn.XLOOKUP( K$6, Actuals!$H$3:$BD$3, Actuals!$H:$BD ) )} -> 38982.49 | L43: {=_xlfn.XLOOKUP( $B$4&" "&$B43, Actuals!$D:$D, _xlfn.XLOOKUP( L$6, Actuals!$H$3:$BD$3, Actuals!$H:$BD ) )} -> 56691.51 | ... AZ43: {=_xlfn.XLOOKUP( $B$4&" "&$B43, Actuals!$D:$D, _xlfn.XLOOKUP( AZ$6, Actuals!$H$3:$BD$3, Actuals!$H:$BD ) )} -> 0 | BB43: {=_xlfn.XLOOKUP( $B$4&" "&$B43, Actuals!$D:$D, _xlfn.XLOOKUP( BB$7, Actuals!$H$3:$BM$3, Actuals!$H:$BM ) )} -> 244635.97 | BC43: =VLOOKUP($B$4&" "&$B43,Budget!$AG$4:$AL$132,$BB$5+1,FALSE) -> 232860 | BD43: =BB43-BC43 -> 11775.966 | BF43: {=_xlfn.XLOOKUP( $B$4&" "&$B43, Actuals!$D:$D, _xlfn.XLOOKUP( BF$7, Actuals!$H$3:$BM$3, Actuals!$H:$BM ) )} -> 0 | BG43: =VLOOKUP($B$4&" "&$B43,Budget!$AG$4:$AL$132,BF$5+1,FALSE) -> 252873 | BH43: =BF43-BG43 -> -252873 | BJ43: {=_xlfn.XLOOKUP( $B$4&" "&$B43, Actuals!$D:$D, _xlfn.XLOOKUP( BJ$7, Actuals!$H$3:$BM$3, Actuals!$H:$BM ) )} -> 0 | BK43: =VLOOKUP($B$4&" "&$B43,Budget!$AG$4:$AL$132,BJ$5+1,FALSE) -> 252013 | BL43: =BJ43-BK43 -> -252013 | BN43: {=_xlfn.XLOOKUP( $B$4&" "&$B43, Actuals!$D:$D, _xlfn.XLOOKUP( BN$7, Actuals!$H$3:$BM$3, Actuals!$H:$BM ) )} -> 0 | BO43: =VLOOKUP($B$4&" "&$B43,Budget!$AG$4:$AL$132,BN$5+1,FALSE) -> 256683 | BR43: {=_xlfn.XLOOKUP( $B$4&" "&$B43, Actuals!$D:$D, _xlfn.XLOOKUP( BR$6, Actuals!$H$3:$BM$3, Actuals!$H:$BM ) )} -> 244635.97 | BS43: =VLOOKUP($B$4&" "&$B43,Budget!$AG$4:$AL$132,6,FALSE) -> 996099 | BT43: =BR43-BS43 -> -751463.03 | BV43: {=_xlfn.XLOOKUP( $B$4&" "&$B43, Actuals!$D:$D, _xlfn.XLOOKUP( BV$6, Actuals!$H$3:$BM$3, Actuals!$H:$BM ) )} -> 917768.63
B44: Mktg exp. per $1 ARR | C44: L3M Avg | D44: =VLOOKUP($B$4&" "&$B44,Actuals!$D$4:$AG$131,3,FALSE) -> $ | E44: {=_xlfn.XLOOKUP( $B$4&" "&$B44, Actuals!$D:$D, _xlfn.XLOOKUP( E$6, Actuals!$H$3:$BD$3, Actuals!$H:$BD ) )} -> 1.5924886 | F44: {=_xlfn.XLOOKUP( $B$4&" "&$B44, Actuals!$D:$D, _xlfn.XLOOKUP( F$6, Actuals!$H$3:$BD$3, Actuals!$H:$BD ) )} -> - | G44: {=_xlfn.XLOOKUP( $B$4&" "&$B44, Actuals!$D:$D, _xlfn.XLOOKUP( G$6, Actuals!$H$3:$BD$3, Actuals!$H:$BD ) )} -> 0.45294985 | H44: {=_xlfn.XLOOKUP( $B$4&" "&$B44, Actuals!$D:$D, _xlfn.XLOOKUP( H$6, Actuals!$H$3:$BD$3, Actuals!$H:$BD ) )} -> 6.7148208 | I44: {=_xlfn.XLOOKUP( $B$4&" "&$B44, Actuals!$D:$D, _xlfn.XLOOKUP( I$6, Actuals!$H$3:$BD$3, Actuals!$H:$BD ) )} -> - | J44: {=_xlfn.XLOOKUP( $B$4&" "&$B44, Actuals!$D:$D, _xlfn.XLOOKUP( J$6, Actuals!$H$3:$BD$3, Actuals!$H:$BD ) )} -> 0.25770942 | K44: {=_xlfn.XLOOKUP( $B$4&" "&$B44, Actuals!$D:$D, _xlfn.XLOOKUP( K$6, Actuals!$H$3:$BD$3, Actuals!$H:$BD ) )} -> - | L44: {=_xlfn.XLOOKUP( $B$4&" "&$B44, Actuals!$D:$D, _xlfn.XLOOKUP( L$6, Actuals!$H$3:$BD$3, Actuals!$H:$BD ) )} -> 0.15620078 | ... AZ44: {=_xlfn.XLOOKUP( $B$4&" "&$B44, Actuals!$D:$D, _xlfn.XLOOKUP( AZ$6, Actuals!$H$3:$BD$3, Actuals!$H:$BD ) )} -> - | BB44: {=_xlfn.XLOOKUP( $B$4&" "&$B44, Actuals!$D:$D, _xlfn.XLOOKUP( BB$7, Actuals!$H$3:$BM$3, Actuals!$H:$BM ) )} -> - | BC44: =IFERROR(VLOOKUP($B$4&" "&$B44,Budget!$AG$4:$AL$132,$BB$5+1,FALSE),"n.a.") -> 0.7276875 | BD44: =IFERROR(BB44-BC44,"-") -> - | BF44: {=_xlfn.XLOOKUP( $B$4&" "&$B44, Actuals!$D:$D, _xlfn.XLOOKUP( BF$7, Actuals!$H$3:$BM$3, Actuals!$H:$BM ) )} -> - | BG44: =IFERROR(VLOOKUP($B$4&" "&$B44,Budget!$AG$4:$AL$132,$BF$5+1,FALSE),"n.a.") -> 0.56194 | BH44: =IFERROR(BF44-BG44,"-") -> - | BJ44: {=_xlfn.XLOOKUP( $B$4&" "&$B44, Actuals!$D:$D, _xlfn.XLOOKUP( BJ$7, Actuals!$H$3:$BM$3, Actuals!$H:$BM ) )} -> - | BK44: =IFERROR(VLOOKUP($B$4&" "&$B44,Budget!$AG$4:$AL$132,$BJ$5+1,FALSE),"n.a.") -> 0.56002889 | BL44: =IFERROR(BJ44-BK44,"-") -> - | BN44: {=_xlfn.XLOOKUP( $B$4&" "&$B44, Actuals!$D:$D, _xlfn.XLOOKUP( BN$7, Actuals!$H$3:$BM$3, Actuals!$H:$BM ) )} -> - | BO44: =IFERROR(VLOOKUP($B$4&" "&$B44,Budget!$AG$4:$AL$132,$BN$5+1,FALSE),"n.a.") -> 0.4425569 | BR44: {=_xlfn.XLOOKUP( $B$4&" "&$B44, Actuals!$D:$D, _xlfn.XLOOKUP( BR$6, Actuals!$H$3:$BM$3, Actuals!$H:$BM ) )} -> 3.1209539 | BS44: =VLOOKUP($B$4&" "&$B44,Budget!$AG$4:$AL$132,6,FALSE) -> 0.55338833 | BT44: =BR44-BS44 -> 2.5675656 | BV44: {=_xlfn.XLOOKUP( $B$4&" "&$B44, Actuals!$D:$D, _xlfn.XLOOKUP( BV$6, Actuals!$H$3:$BM$3, Actuals!$H:$BM ) )}
B46: Notes
B47: (1) BDR expense is included in Sales not Marketing department costs. BDR sourced opportunities and pipeline are included with Marketing efforts. A breakout is provided in Lead Generation

Sheet Sales old)
B2: [PortCo Name]
B3: [Month] [Year] Reporting Package
B4: Sales
D5: Monthly | K5: QTD vs. Budget | O5: YTD vs. Budget | T5: Last 4 Quarters | W5: L3M
D6: M-5 | E6: M-4 | F6: M-3 | G6: M-2 | H6: M-1 | I6: M | K6: QTD | L6: Bgt. | M6: Diff. | O6: YTD | P6: Bgt. | Q6: Diff. | S6: Q1 22 | T6: Q2 22 | U6: Q3 22 | V6: Q4 22 | W6: L3M | Y6: FN terminology
B8: Opportunities(1)
B9: Opportunities from Sales | C9: In-period
B10: Opportunities from Marketing | C10: In-period
B11: Total New Opportunities | C11: In-period
B13: Pipeline Activity
B14: New Pipeline Opportunities | C14: In-period
B15: Nurture | C15: In-period
B16: Lost | C16: In-period
B17: Won | C17: In-period
B18: Win rate: Total | C18: In-period
B19: Win rate: HTH | C19: In-period
B20: Avg ACV | C20: In-period
B21: Weeks in pipe | C21: In-period
B23: Pipeline Value
B24: Early | C24: EoP
B25: Intermediate | C25: EoP
B26: Advanced | C26: EoP
B27: Total | C27: EoP
B29: Pipeline Count
B30: Early | C30: EoP
B31: Intermediate | C31: EoP
B32: Advanced | C32: EoP
B33: Total | C33: EoP
B35: Pipeline Weeks
B36: Early | C36: EoP
B37: Intermediate | C37: EoP
B38: Advanced | C38: EoP
B39: Total | C39: EoP
B41: Efficiency
B42: Headcount | C42: EoP
B43: Sales expense | C43: L3M Avg
B44: Sales exp. per $1 ARR | C44: L3M Avg

Sheet Customer Success
B2: ='2023 Control'!$C$3 -> Concertiv
B3: =('2024 Control'!$C$4)&" Reporting Package" -> December 2025 Reporting Package
B4: Customer Success
E5: Monthly | BB5: 1 | BF5: 2 | BJ5: 3 | BN5: 4 | BR5: YTD vs. Budget
D6: Units | E6: 44957 | F6: 44985 | G6: 45016 | H6: =EOMONTH(G6,1) -> 45046 | I6: =EOMONTH(H6,1) -> 45077 | J6: =EOMONTH(I6,1) -> 45107 | K6: =EOMONTH(J6,1) -> 45138 | L6: =EOMONTH(K6,1) -> 45169 | M6: =EOMONTH(L6,1) -> 45199 | N6: =EOMONTH(M6,1) -> 45230 | O6: =EOMONTH(N6,1) -> 45260 | ... AZ6: =EOMONTH(AY6,1) -> 46387 | BB6: Act | BC6: Bgt. | BD6: Diff. | BF6: Act | BG6: Bgt. | BH6: Diff. | BJ6: Act | BK6: Bgt. | BL6: Diff. | BN6: Act | BO6: Bgt. | BP6: Diff. | BR6: YTD | BS6: Bgt. | BT6: Diff. | BV6: LTM
BB7: Q1 | BF7: Q2 | BJ7: Q3 | BN7: Q4
B8: Customer Success ARR ($)
B9: Cross-sell | C9: In-period | D9: =VLOOKUP($B$4&" "&$B9,Actuals!$D$4:$AG$131,3,FALSE) -> $ | E9: {=_xlfn.XLOOKUP( $B$4&" "&$B9, Actuals!$D:$D, _xlfn.XLOOKUP( E$6, Actuals!$H$3:$BD$3, Actuals!$H:$BD ) )} -> 27907 | F9: {=_xlfn.XLOOKUP( $B$4&" "&$B9, Actuals!$D:$D, _xlfn.XLOOKUP( F$6, Actuals!$H$3:$BD$3, Actuals!$H:$BD ) )} -> 0 | G9: {=_xlfn.XLOOKUP( $B$4&" "&$B9, Actuals!$D:$D, _xlfn.XLOOKUP( G$6, Actuals!$H$3:$BD$3, Actuals!$H:$BD ) )} -> 15000 | H9: {=_xlfn.XLOOKUP( $B$4&" "&$B9, Actuals!$D:$D, _xlfn.XLOOKUP( H$6, Actuals!$H$3:$BD$3, Actuals!$H:$BD ) )} -> 80000 | I9: {=_xlfn.XLOOKUP( $B$4&" "&$B9, Actuals!$D:$D, _xlfn.XLOOKUP( I$6, Actuals!$H$3:$BD$3, Actuals!$H:$BD ) )} -> 0 | J9: {=_xlfn.XLOOKUP( $B$4&" "&$B9, Actuals!$D:$D, _xlfn.XLOOKUP( J$6, Actuals!$H$3:$BD$3, Actuals!$H:$BD ) )} -> 0 | K9: {=_xlfn.XLOOKUP( $B$4&" "&$B9, Actuals!$D:$D, _xlfn.XLOOKUP( K$6, Actuals!$H$3:$BD$3, Actuals!$H:$BD ) )} -> 0 | L9: {=_xlfn.XLOOKUP( $B$4&" "&$B9, Actuals!$D:$D, _xlfn.XLOOKUP( L$6, Actuals!$H$3:$BD$3, Actuals!$H:$BD ) )} -> -15000 | ... AZ9: {=_xlfn.XLOOKUP( $B$4&" "&$B9, Actuals!$D:$D, _xlfn.XLOOKUP( AZ$6, Actuals!$H$3:$BD$3, Actuals!$H:$BD ) )} -> 0 | BB9: {=_xlfn.XLOOKUP( $B$4&" "&$B9, Actuals!$D:$D, _xlfn.XLOOKUP( BB$7, Actuals!$H$3:$BM$3, Actuals!$H:$BM ) )} -> 0 | BC9: =VLOOKUP($B$4&" "&$B9,Budget!$AG$4:$AL$132,$BB$5+1,FALSE) -> 0 | BD9: =BB9-BC9 -> 0 | BF9: {=_xlfn.XLOOKUP( $B$4&" "&$B9, Actuals!$D:$D, _xlfn.XLOOKUP( BF$7, Actuals!$H$3:$BM$3, Actuals!$H:$BM ) )} -> 0 | BG9: =VLOOKUP($B$4&" "&$B9,Budget!$AG$4:$AL$132,BF$5+1,FALSE) -> 0 | BH9: =BF9-BG9 -> 0 | BJ9: {=_xlfn.XLOOKUP( $B$4&" "&$B9, Actuals!$D:$D, _xlfn.XLOOKUP( BJ$7, Actuals!$H$3:$BM$3, Actuals!$H:$BM ) )} -> 0 | BK9: =VLOOKUP($B$4&" "&$B9,Budget!$AG$4:$AL$132,BJ$5+1,FALSE) -> 0 | BL9: =BJ9-BK9 -> 0 | BN9: {=_xlfn.XLOOKUP( $B$4&" "&$B9, Actuals!$D:$D, _xlfn.XLOOKUP( BN$7, Actuals!$H$3:$BM$3, Actuals!$H:$BM ) )} -> 0 | BO9: =VLOOKUP($B$4&" "&$B9,Budget!$AG$4:$AL$132,BN$5+1,FALSE) -> 0 | BR9: {=_xlfn.XLOOKUP( $B$4&" "&$B9, Actuals!$D:$D, _xlfn.XLOOKUP( BR$6, Actuals!$H$3:$BM$3, Actuals!$H:$BM ) )} -> 0 | BS9: =VLOOKUP($B$4&" "&$B9,Budget!$AG$4:$AL$132,6,FALSE) -> 0 | BT9: =BR9-BS9 -> 0 | BV9: {=_xlfn.XLOOKUP( $B$4&" "&$B9, Actuals!$D:$D, _xlfn.XLOOKUP( BV$6, Actuals!$H$3:$BM$3, Actuals!$H:$BM ) )} -> 0
B10: Upsell | C10: In-period | D10: =VLOOKUP($B$4&" "&$B10,Actuals!$D$4:$AG$131,3,FALSE) -> $ | E10: {=_xlfn.XLOOKUP( $B$4&" "&$B10, Actuals!$D:$D, _xlfn.XLOOKUP( E$6, Actuals!$H$3:$BD$3, Actuals!$H:$BD ) )} -> 25880 | F10: {=_xlfn.XLOOKUP( $B$4&" "&$B10, Actuals!$D:$D, _xlfn.XLOOKUP( F$6, Actuals!$H$3:$BD$3, Actuals!$H:$BD ) )} -> 123093 | G10: {=_xlfn.XLOOKUP( $B$4&" "&$B10, Actuals!$D:$D, _xlfn.XLOOKUP( G$6, Actuals!$H$3:$BD$3, Actuals!$H:$BD ) )} -> 126667 | H10: {=_xlfn.XLOOKUP( $B$4&" "&$B10, Actuals!$D:$D, _xlfn.XLOOKUP( H$6, Actuals!$H$3:$BD$3, Actuals!$H:$BD ) )} -> 163490 | I10: {=_xlfn.XLOOKUP( $B$4&" "&$B10, Actuals!$D:$D, _xlfn.XLOOKUP( I$6, Actuals!$H$3:$BD$3, Actuals!$H:$BD ) )} -> 39445 | J10: {=_xlfn.XLOOKUP( $B$4&" "&$B10, Actuals!$D:$D, _xlfn.XLOOKUP( J$6, Actuals!$H$3:$BD$3, Actuals!$H:$BD ) )} -> 30218 | K10: {=_xlfn.XLOOKUP( $B$4&" "&$B10, Actuals!$D:$D, _xlfn.XLOOKUP( K$6, Actuals!$H$3:$BD$3, Actuals!$H:$BD ) )} -> 6250 | L10: {=_xlfn.XLOOKUP( $B$4&" "&$B10, Actuals!$D:$D, _xlfn.XLOOKUP( L$6, Actuals!$H$3:$BD$3, Actuals!$H:$BD ) )} -> 23447 | ... AZ10: {=_xlfn.XLOOKUP( $B$4&" "&$B10, Actuals!$D:$D, _xlfn.XLOOKUP( AZ$6, Actuals!$H$3:$BD$3, Actuals!$H:$BD ) )} -> 0 | BB10: {=_xlfn.XLOOKUP( $B$4&" "&$B10, Actuals!$D:$D, _xlfn.XLOOKUP( BB$7, Actuals!$H$3:$BM$3, Actuals!$H:$BM ) )} -> 0 | BC10: =VLOOKUP($B$4&" "&$B10,Budget!$AG$4:$AL$132,$BB$5+1,FALSE) -> 0 | BD10: =BB10-BC10 -> 0 | BF10: {=_xlfn.XLOOKUP( $B$4&" "&$B10, Actuals!$D:$D, _xlfn.XLOOKUP( BF$7, Actuals!$H$3:$BM$3, Actuals!$H:$BM ) )} -> 0 | BG10: =VLOOKUP($B$4&" "&$B10,Budget!$AG$4:$AL$132,BF$5+1,FALSE) -> 0 | BH10: =BF10-BG10 -> 0 | BJ10: {=_xlfn.XLOOKUP( $B$4&" "&$B10, Actuals!$D:$D, _xlfn.XLOOKUP( BJ$7, Actuals!$H$3:$BM$3, Actuals!$H:$BM ) )} -> 0 | BK10: =VLOOKUP($B$4&" "&$B10,Budget!$AG$4:$AL$132,BJ$5+1,FALSE) -> 0 | BL10: =BJ10-BK10 -> 0 | BN10: {=_xlfn.XLOOKUP( $B$4&" "&$B10, Actuals!$D:$D, _xlfn.XLOOKUP( BN$7, Actuals!$H$3:$BM$3, Actuals!$H:$BM ) )} -> 0 | BO10: =VLOOKUP($B$4&" "&$B10,Budget!$AG$4:$AL$132,BN$5+1,FALSE) -> 0 | BR10: {=_xlfn.XLOOKUP( $B$4&" "&$B10, Actuals!$D:$D, _xlfn.XLOOKUP( BR$6, Actuals!$H$3:$BM$3, Actuals!$H:$BM ) )} -> 0 | BS10: =VLOOKUP($B$4&" "&$B10,Budget!$AG$4:$AL$132,6,FALSE) -> 0 | BT10: =BR10-BS10 -> 0 | BV10: {=_xlfn.XLOOKUP( $B$4&" "&$B10, Actuals!$D:$D, _xlfn.XLOOKUP( BV$6, Actuals!$H$3:$BM$3, Actuals!$H:$BM ) )} -> 30000
B11: Price | C11: In-period | D11: =VLOOKUP($B$4&" "&$B11,Actuals!$D$4:$AG$131,3,FALSE) -> $ | E11: {=_xlfn.XLOOKUP( $B$4&" "&$B11, Actuals!$D:$D, _xlfn.XLOOKUP( E$6, Actuals!$H$3:$BD$3, Actuals!$H:$BD ) )} -> 0 | F11: {=_xlfn.XLOOKUP( $B$4&" "&$B11, Actuals!$D:$D, _xlfn.XLOOKUP( F$6, Actuals!$H$3:$BD$3, Actuals!$H:$BD ) )} -> 0 | G11: {=_xlfn.XLOOKUP( $B$4&" "&$B11, Actuals!$D:$D, _xlfn.XLOOKUP( G$6, Actuals!$H$3:$BD$3, Actuals!$H:$BD ) )} -> 0 | H11: {=_xlfn.XLOOKUP( $B$4&" "&$B11, Actuals!$D:$D, _xlfn.XLOOKUP( H$6, Actuals!$H$3:$BD$3, Actuals!$H:$BD ) )} -> 0 | I11: {=_xlfn.XLOOKUP( $B$4&" "&$B11, Actuals!$D:$D, _xlfn.XLOOKUP( I$6, Actuals!$H$3:$BD$3, Actuals!$H:$BD ) )} -> 0 | J11: {=_xlfn.XLOOKUP( $B$4&" "&$B11, Actuals!$D:$D, _xlfn.XLOOKUP( J$6, Actuals!$H$3:$BD$3, Actuals!$H:$BD ) )} -> 0 | K11: {=_xlfn.XLOOKUP( $B$4&" "&$B11, Actuals!$D:$D, _xlfn.XLOOKUP( K$6, Actuals!$H$3:$BD$3, Actuals!$H:$BD ) )} -> 0 | L11: {=_xlfn.XLOOKUP( $B$4&" "&$B11, Actuals!$D:$D, _xlfn.XLOOKUP( L$6, Actuals!$H$3:$BD$3, Actuals!$H:$BD ) )} -> 0 | ... AZ11: {=_xlfn.XLOOKUP( $B$4&" "&$B11, Actuals!$D:$D, _xlfn.XLOOKUP( AZ$6, Actuals!$H$3:$BD$3, Actuals!$H:$BD ) )} -> 0 | BB11: {=_xlfn.XLOOKUP( $B$4&" "&$B11, Actuals!$D:$D, _xlfn.XLOOKUP( BB$7, Actuals!$H$3:$BM$3, Actuals!$H:$BM ) )} -> 0 | BC11: =VLOOKUP($B$4&" "&$B11,Budget!$AG$4:$AL$132,$BB$5+1,FALSE) -> 0 | BD11: =BB11-BC11 -> 0 | BF11: {=_xlfn.XLOOKUP( $B$4&" "&$B11, Actuals!$D:$D, _xlfn.XLOOKUP( BF$7, Actuals!$H$3:$BM$3, Actuals!$H:$BM ) )} -> 0 | BG11: =VLOOKUP($B$4&" "&$B11,Budget!$AG$4:$AL$132,BF$5+1,FALSE) -> 0 | BH11: =BF11-BG11 -> 0 | BJ11: {=_xlfn.XLOOKUP( $B$4&" "&$B11, Actuals!$D:$D, _xlfn.XLOOKUP( BJ$7, Actuals!$H$3:$BM$3, Actuals!$H:$BM ) )} -> 0 | BK11: =VLOOKUP($B$4&" "&$B11,Budget!$AG$4:$AL$132,BJ$5+1,FALSE) -> 0 | BL11: =BJ11-BK11 -> 0 | BN11: {=_xlfn.XLOOKUP( $B$4&" "&$B11, Actuals!$D:$D, _xlfn.XLOOKUP( BN$7, Actuals!$H$3:$BM$3, Actuals!$H:$BM ) )} -> 0 | BO11: =VLOOKUP($B$4&" "&$B11,Budget!$AG$4:$AL$132,BN$5+1,FALSE) -> 0 | BR11: {=_xlfn.XLOOKUP( $B$4&" "&$B11, Actuals!$D:$D, _xlfn.XLOOKUP( BR$6, Actuals!$H$3:$BM$3, Actuals!$H:$BM ) )} -> 0 | BS11: =VLOOKUP($B$4&" "&$B11,Budget!$AG$4:$AL$132,6,FALSE) -> 0 | BT11: =BR11-BS11 -> 0 | BV11: {=_xlfn.XLOOKUP( $B$4&" "&$B11, Actuals!$D:$D, _xlfn.XLOOKUP( BV$6, Actuals!$H$3:$BM$3, Actuals!$H:$BM ) )} -> 360197
B12: Total Gross Growth | C12: In-period | D12: =VLOOKUP($B$4&" "&$B12,Actuals!$D$4:$AG$131,3,FALSE) -> $ | E12: {=_xlfn.XLOOKUP( $B$4&" "&$B12, Actuals!$D:$D, _xlfn.XLOOKUP( E$6, Actuals!$H$3:$BD$3, Actuals!$H:$BD ) )} -> 53787 | F12: {=_xlfn.XLOOKUP( $B$4&" "&$B12, Actuals!$D:$D, _xlfn.XLOOKUP( F$6, Actuals!$H$3:$BD$3, Actuals!$H:$BD ) )} -> 123093 | G12: {=_xlfn.XLOOKUP( $B$4&" "&$B12, Actuals!$D:$D, _xlfn.XLOOKUP( G$6, Actuals!$H$3:$BD$3, Actuals!$H:$BD ) )} -> 141667 | H12: {=_xlfn.XLOOKUP( $B$4&" "&$B12, Actuals!$D:$D, _xlfn.XLOOKUP( H$6, Actuals!$H$3:$BD$3, Actuals!$H:$BD ) )} -> 243490 | I12: {=_xlfn.XLOOKUP( $B$4&" "&$B12, Actuals!$D:$D, _xlfn.XLOOKUP( I$6, Actuals!$H$3:$BD$3, Actuals!$H:$BD ) )} -> 39445 | J12: {=_xlfn.XLOOKUP( $B$4&" "&$B12, Actuals!$D:$D, _xlfn.XLOOKUP( J$6, Actuals!$H$3:$BD$3, Actuals!$H:$BD ) )} -> 30218 | K12: {=_xlfn.XLOOKUP( $B$4&" "&$B12, Actuals!$D:$D, _xlfn.XLOOKUP( K$6, Actuals!$H$3:$BD$3, Actuals!$H:$BD ) )} -> 6250 | L12: {=_xlfn.XLOOKUP( $B$4&" "&$B12, Actuals!$D:$D, _xlfn.XLOOKUP( L$6, Actuals!$H$3:$BD$3, Actuals!$H:$BD ) )} -> 8447 | ... AZ12: {=_xlfn.XLOOKUP( $B$4&" "&$B12, Actuals!$D:$D, _xlfn.XLOOKUP( AZ$6, Actuals!$H$3:$BD$3, Actuals!$H:$BD ) )} -> 0 | BB12: {=_xlfn.XLOOKUP( $B$4&" "&$B12, Actuals!$D:$D, _xlfn.XLOOKUP( BB$7, Actuals!$H$3:$BM$3, Actuals!$H:$BM ) )} -> 0 | BC12: =VLOOKUP($B$4&" "&$B12,Budget!$AG$4:$AL$132,$BB$5+1,FALSE) -> 239000 | BD12: =BB12-BC12 -> -239000 | BF12: {=_xlfn.XLOOKUP( $B$4&" "&$B12, Actuals!$D:$D, _xlfn.XLOOKUP( BF$7, Actuals!$H$3:$BM$3, Actuals!$H:$BM ) )} -> 0 | BG12: =VLOOKUP($B$4&" "&$B12,Budget!$AG$4:$AL$132,BF$5+1,FALSE) -> 344000 | BH12: =BF12-BG12 -> -344000 | BJ12: {=_xlfn.XLOOKUP( $B$4&" "&$B12, Actuals!$D:$D, _xlfn.XLOOKUP( BJ$7, Actuals!$H$3:$BM$3, Actuals!$H:$BM ) )} -> 0 | BK12: =VLOOKUP($B$4&" "&$B12,Budget!$AG$4:$AL$132,BJ$5+1,FALSE) -> 344000 | BL12: =BJ12-BK12 -> -344000 | BN12: {=_xlfn.XLOOKUP( $B$4&" "&$B12, Actuals!$D:$D, _xlfn.XLOOKUP( BN$7, Actuals!$H$3:$BM$3, Actuals!$H:$BM ) )} -> 0 | BO12: =VLOOKUP($B$4&" "&$B12,Budget!$AG$4:$AL$132,BN$5+1,FALSE) -> 449000 | BR12: {=_xlfn.XLOOKUP( $B$4&" "&$B12, Actuals!$D:$D, _xlfn.XLOOKUP( BR$6, Actuals!$H$3:$BM$3, Actuals!$H:$BM ) )} -> 0 | BS12: =VLOOKUP($B$4&" "&$B12,Budget!$AG$4:$AL$132,6,FALSE) -> 1376000 | BT12: =BR12-BS12 -> -1376000 | BV12: {=_xlfn.XLOOKUP( $B$4&" "&$B12, Actuals!$D:$D, _xlfn.XLOOKUP( BV$6, Actuals!$H$3:$BM$3, Actuals!$H:$BM ) )} -> 390197
B13: (-) Churn | C13: In-period | D13: =VLOOKUP($B$4&" "&$B13,Actuals!$D$4:$AG$131,3,FALSE) -> $ | E13: {=_xlfn.XLOOKUP( $B$4&" "&$B13, Actuals!$D:$D, _xlfn.XLOOKUP( E$6, Actuals!$H$3:$BD$3, Actuals!$H:$BD ) )} -> -44750 | F13: {=_xlfn.XLOOKUP( $B$4&" "&$B13, Actuals!$D:$D, _xlfn.XLOOKUP( F$6, Actuals!$H$3:$BD$3, Actuals!$H:$BD ) )} -> 0 | G13: {=_xlfn.XLOOKUP( $B$4&" "&$B13, Actuals!$D:$D, _xlfn.XLOOKUP( G$6, Actuals!$H$3:$BD$3, Actuals!$H:$BD ) )} -> 0 | H13: {=_xlfn.XLOOKUP( $B$4&" "&$B13, Actuals!$D:$D, _xlfn.XLOOKUP( H$6, Actuals!$H$3:$BD$3, Actuals!$H:$BD ) )} -> -40000 | I13: {=_xlfn.XLOOKUP( $B$4&" "&$B13, Actuals!$D:$D, _xlfn.XLOOKUP( I$6, Actuals!$H$3:$BD$3, Actuals!$H:$BD ) )} -> 0 | J13: {=_xlfn.XLOOKUP( $B$4&" "&$B13, Actuals!$D:$D, _xlfn.XLOOKUP( J$6, Actuals!$H$3:$BD$3, Actuals!$H:$BD ) )} -> -55000 | K13: {=_xlfn.XLOOKUP( $B$4&" "&$B13, Actuals!$D:$D, _xlfn.XLOOKUP( K$6, Actuals!$H$3:$BD$3, Actuals!$H:$BD ) )} -> -88500 | L13: {=_xlfn.XLOOKUP( $B$4&" "&$B13, Actuals!$D:$D, _xlfn.XLOOKUP( L$6, Actuals!$H$3:$BD$3, Actuals!$H:$BD ) )} -> -4583 | ... AZ13: {=_xlfn.XLOOKUP( $B$4&" "&$B13, Actuals!$D:$D, _xlfn.XLOOKUP( AZ$6, Actuals!$H$3:$BD$3, Actuals!$H:$BD ) )} -> 0 | BB13: {=_xlfn.XLOOKUP( $B$4&" "&$B13, Actuals!$D:$D, _xlfn.XLOOKUP( BB$7, Actuals!$H$3:$BM$3, Actuals!$H:$BM ) )} -> 0 | BC13: =VLOOKUP($B$4&" "&$B13,Budget!$AG$4:$AL$132,$BB$5+1,FALSE) -> -207648 | BD13: =BB13-BC13 -> 207648 | BF13: {=_xlfn.XLOOKUP( $B$4&" "&$B13, Actuals!$D:$D, _xlfn.XLOOKUP( BF$7, Actuals!$H$3:$BM$3, Actuals!$H:$BM ) )} -> 0 | BG13: =VLOOKUP($B$4&" "&$B13,Budget!$AG$4:$AL$132,BF$5+1,FALSE) -> -202716 | BH13: =BF13-BG13 -> 202716 | BJ13: {=_xlfn.XLOOKUP( $B$4&" "&$B13, Actuals!$D:$D, _xlfn.XLOOKUP( BJ$7, Actuals!$H$3:$BM$3, Actuals!$H:$BM ) )} -> 0 | BK13: =VLOOKUP($B$4&" "&$B13,Budget!$AG$4:$AL$132,BJ$5+1,FALSE) -> -199092 | BL13: =BJ13-BK13 -> 199092 | BN13: {=_xlfn.XLOOKUP( $B$4&" "&$B13, Actuals!$D:$D, _xlfn.XLOOKUP( BN$7, Actuals!$H$3:$BM$3, Actuals!$H:$BM ) )} -> 0 | BO13: =VLOOKUP($B$4&" "&$B13,Budget!$AG$4:$AL$132,BN$5+1,FALSE) -> -192036 | BR13: {=_xlfn.XLOOKUP( $B$4&" "&$B13, Actuals!$D:$D, _xlfn.XLOOKUP( BR$6, Actuals!$H$3:$BM$3, Actuals!$H:$BM ) )} -> 0 | BS13: =VLOOKUP($B$4&" "&$B13,Budget!$AG$4:$AL$132,6,FALSE) -> -799704 | BT13: =BR13-BS13 -> 799704 | BV13: {=_xlfn.XLOOKUP( $B$4&" "&$B13, Actuals!$D:$D, _xlfn.XLOOKUP( BV$6, Actuals!$H$3:$BM$3, Actuals!$H:$BM ) )} -> 0
B14: Total Net Growth | C14: In-period | D14: =VLOOKUP($B$4&" "&$B14,Actuals!$D$4:$AG$131,3,FALSE) -> $ | E14: {=_xlfn.XLOOKUP( $B$4&" "&$B14, Actuals!$D:$D, _xlfn.XLOOKUP( E$6, Actuals!$H$3:$BD$3, Actuals!$H:$BD ) )} -> 9037 | F14: {=_xlfn.XLOOKUP( $B$4&" "&$B14, Actuals!$D:$D, _xlfn.XLOOKUP( F$6, Actuals!$H$3:$BD$3, Actuals!$H:$BD ) )} -> 123093 | G14: {=_xlfn.XLOOKUP( $B$4&" "&$B14, Actuals!$D:$D, _xlfn.XLOOKUP( G$6, Actuals!$H$3:$BD$3, Actuals!$H:$BD ) )} -> 141667 | H14: {=_xlfn.XLOOKUP( $B$4&" "&$B14, Actuals!$D:$D, _xlfn.XLOOKUP( H$6, Actuals!$H$3:$BD$3, Actuals!$H:$BD ) )} -> 203490 | I14: {=_xlfn.XLOOKUP( $B$4&" "&$B14, Actuals!$D:$D, _xlfn.XLOOKUP( I$6, Actuals!$H$3:$BD$3, Actuals!$H:$BD ) )} -> 39445 | J14: {=_xlfn.XLOOKUP( $B$4&" "&$B14, Actuals!$D:$D, _xlfn.XLOOKUP( J$6, Actuals!$H$3:$BD$3, Actuals!$H:$BD ) )} -> -24782 | K14: {=_xlfn.XLOOKUP( $B$4&" "&$B14, Actuals!$D:$D, _xlfn.XLOOKUP( K$6, Actuals!$H$3:$BD$3, Actuals!$H:$BD ) )} -> -82250 | L14: {=_xlfn.XLOOKUP( $B$4&" "&$B14, Actuals!$D:$D, _xlfn.XLOOKUP( L$6, Actuals!$H$3:$BD$3, Actuals!$H:$BD ) )} -> 3864 | ... AZ14: {=_xlfn.XLOOKUP( $B$4&" "&$B14, Actuals!$D:$D, _xlfn.XLOOKUP( AZ$6, Actuals!$H$3:$BD$3, Actuals!$H:$BD ) )} -> 0 | BB14: {=_xlfn.XLOOKUP( $B$4&" "&$B14, Actuals!$D:$D, _xlfn.XLOOKUP( BB$7, Actuals!$H$3:$BM$3, Actuals!$H:$BM ) )} -> 0 | BC14: =VLOOKUP($B$4&" "&$B14,Budget!$AG$4:$AL$132,$BB$5+1,FALSE) -> 31352 | BD14: =BB14-BC14 -> -31352 | BF14: {=_xlfn.XLOOKUP( $B$4&" "&$B14, Actuals!$D:$D, _xlfn.XLOOKUP( BF$7, Actuals!$H$3:$BM$3, Actuals!$H:$BM ) )} -> 0 | BG14: =VLOOKUP($B$4&" "&$B14,Budget!$AG$4:$AL$132,BF$5+1,FALSE) -> 141284 | BH14: =BF14-BG14 -> -141284 | BJ14: {=_xlfn.XLOOKUP( $B$4&" "&$B14, Actuals!$D:$D, _xlfn.XLOOKUP( BJ$7, Actuals!$H$3:$BM$3, Actuals!$H:$BM ) )} -> 0 | BK14: =VLOOKUP($B$4&" "&$B14,Budget!$AG$4:$AL$132,BJ$5+1,FALSE) -> 144908 | BL14: =BJ14-BK14 -> -144908 | BN14: {=_xlfn.XLOOKUP( $B$4&" "&$B14, Actuals!$D:$D, _xlfn.XLOOKUP( BN$7, Actuals!$H$3:$BM$3, Actuals!$H:$BM ) )} -> 0 | BO14: =VLOOKUP($B$4&" "&$B14,Budget!$AG$4:$AL$132,BN$5+1,FALSE) -> 256964 | BR14: {=_xlfn.XLOOKUP( $B$4&" "&$B14, Actuals!$D:$D, _xlfn.XLOOKUP( BR$6, Actuals!$H$3:$BM$3, Actuals!$H:$BM ) )} -> 0 | BS14: =VLOOKUP($B$4&" "&$B14,Budget!$AG$4:$AL$132,6,FALSE) -> 576296 | BT14: =BR14-BS14 -> -576296 | BV14: {=_xlfn.XLOOKUP( $B$4&" "&$B14, Actuals!$D:$D, _xlfn.XLOOKUP( BV$6, Actuals!$H$3:$BM$3, Actuals!$H:$BM ) )} -> -105003.5
B16: Gross Growth % | C16: In-period | D16: =VLOOKUP($B$4&" "&$B16,Actuals!$D$4:$AG$131,3,FALSE) -> $ | E16: {=_xlfn.XLOOKUP( $B$4&" "&$B16, Actuals!$D:$D, _xlfn.XLOOKUP( E$6, Actuals!$H$3:$BD$3, Actuals!$H:$BD ) )} -> 0.0077695351 | F16: {=_xlfn.XLOOKUP( $B$4&" "&$B16, Actuals!$D:$D, _xlfn.XLOOKUP( F$6, Actuals!$H$3:$BD$3, Actuals!$H:$BD ) )} -> 0.017780791 | G16: {=_xlfn.XLOOKUP( $B$4&" "&$B16, Actuals!$D:$D, _xlfn.XLOOKUP( G$6, Actuals!$H$3:$BD$3, Actuals!$H:$BD ) )} -> 0.020463806 | H16: {=_xlfn.XLOOKUP( $B$4&" "&$B16, Actuals!$D:$D, _xlfn.XLOOKUP( H$6, Actuals!$H$3:$BD$3, Actuals!$H:$BD ) )} -> 0.035172144 | I16: {=_xlfn.XLOOKUP( $B$4&" "&$B16, Actuals!$D:$D, _xlfn.XLOOKUP( I$6, Actuals!$H$3:$BD$3, Actuals!$H:$BD ) )} -> 0.0056978324 | J16: {=_xlfn.XLOOKUP( $B$4&" "&$B16, Actuals!$D:$D, _xlfn.XLOOKUP( J$6, Actuals!$H$3:$BD$3, Actuals!$H:$BD ) )} -> 0.0043649918 | K16: {=_xlfn.XLOOKUP( $B$4&" "&$B16, Actuals!$D:$D, _xlfn.XLOOKUP( K$6, Actuals!$H$3:$BD$3, Actuals!$H:$BD ) )} -> 0.00090281285 | L16: {=_xlfn.XLOOKUP( $B$4&" "&$B16, Actuals!$D:$D, _xlfn.XLOOKUP( L$6, Actuals!$H$3:$BD$3, Actuals!$H:$BD ) )} -> 0.0012201696 | ... AZ16: {=_xlfn.XLOOKUP( $B$4&" "&$B16, Actuals!$D:$D, _xlfn.XLOOKUP( AZ$6, Actuals!$H$3:$BD$3, Actuals!$H:$BD ) )} -> 0 | BB16: {=_xlfn.XLOOKUP( $B$4&" "&$B16, Actuals!$D:$D, _xlfn.XLOOKUP( BB$7, Actuals!$H$3:$BM$3, Actuals!$H:$BM ) )} -> 0 | BC16: =VLOOKUP($B$4&" "&$B16,Budget!$AG$4:$AL$132,$BB$5+1,FALSE) -> 0.0097173883 | BD16: =IFERROR(BB16-BC16,"-") -> -0.0097173883 | BF16: {=_xlfn.XLOOKUP( $B$4&" "&$B16, Actuals!$D:$D, _xlfn.XLOOKUP( BF$7, Actuals!$H$3:$BM$3, Actuals!$H:$BM ) )} -> 0 | BG16: =VLOOKUP($B$4&" "&$B16,Budget!$AG$4:$AL$132,BF$5+1,FALSE) -> 0.013986534 | BH16: =IFERROR(BF16-BG16,"-") -> -0.013986534 | BJ16: {=_xlfn.XLOOKUP( $B$4&" "&$B16, Actuals!$D:$D, _xlfn.XLOOKUP( BJ$7, Actuals!$H$3:$BM$3, Actuals!$H:$BM ) )} -> 0 | BK16: =VLOOKUP($B$4&" "&$B16,Budget!$AG$4:$AL$132,BJ$5+1,FALSE) -> 0.013986534 | BL16: =IFERROR(BJ16-BK16,"-") -> -0.013986534 | BN16: {=_xlfn.XLOOKUP( $B$4&" "&$B16, Actuals!$D:$D, _xlfn.XLOOKUP( BN$7, Actuals!$H$3:$BM$3, Actuals!$H:$BM ) )} -> 0 | BO16: =VLOOKUP($B$4&" "&$B16,Budget!$AG$4:$AL$132,BN$5+1,FALSE) -> 0.018255679 | BR16: {=_xlfn.XLOOKUP( $B$4&" "&$B16, Actuals!$D:$D, _xlfn.XLOOKUP( BR$6, Actuals!$H$3:$BM$3, Actuals!$H:$BM ) )} -> 0 | BS16: =VLOOKUP($B$4&" "&$B16,Budget!$AG$4:$AL$132,6,FALSE) -> 0.013986534 | BT16: =BR16-BS16 -> -0.013986534 | BV16: {=_xlfn.XLOOKUP( $B$4&" "&$B16, Actuals!$D:$D, _xlfn.XLOOKUP( BV$6, Actuals!$H$3:$BM$3, Actuals!$H:$BM ) )} -> 0.0039662089
